Workbook

Sheet Premissas
A1: FASE 2 - REDE | premissas
A3: Celulas em bege sao de entrada. Tudo o mais e formula.
A5: UNIDADE FRANQUEADA (praca tipica de 30 a 80 mil hab)
A6: Receita madura da unidade/mes | B6: 48000
A7: Custo variavel + meios (% da receita) | B7: 0.293
A8: Custo fixo da unidade sem aluguel | B8: 8550
A10: TAXAS DA REDE
A11: Royalty (% da receita) | B11: 0.06
A12: Fundo de marketing (% da receita) | B12: 0.02 | C12: vinculado: nao e margem da franqueadora
A13: Taxa de tecnologia/mes por unidade | B13: 700
A14: Taxa de franquia (na assinatura) | B14: 40000
A16: ESTRUTURA DO PONTO COMERCIAL
A17: A - aluguel de mercado (franqueado paga a terceiro) | B17: 3000
A18: B1 - aluguel que cobramos (compramos o ponto) | B18: 4000 | C18: janela que fecha dos dois lados: 5.000 a 5.500
A19: B2 - sublocacao (alugamos longo e sublocamos) | B19: 6500
A20: Terreno por ponto | B20: 280000
A21: Obra da baia por ponto | B21: 220000
A22: B1 - IPTU, seguro, manutencao estrutural/mes | B22: 650
A23: B2 - manutencao estrutural/mes | B23: 350
A25: INVESTIMENTO DO FRANQUEADO
A26: A - ele constroi tudo (taxa 50k + capex + giro) | B26: 504060
A27: B1/B2 - ponto pronto: so maquina e equipamentos | B27: 310100
A28: A - capex dentro do investimento | B28: 399060 | C28: o resto e taxa de franquia (50 mil) e giro (55 mil)
A29: B1/B2 - capex dentro do investimento | B29: 224100 | C29: o resto e taxa de franquia (40 mil) e giro (46 mil)
A30: Valor residual do capex no mes 60 | B30: 0.3 | C30: nao incide sobre taxa de franquia nem sobre giro
A32: FRANQUEADORA
A33: Tributos sobre servicos (royalty + tecnologia) | B33: 0.16 | C33: Lucro Presumido - ESTIMATIVA
A34: Tributos sobre aluguel | B34: 0.115
A35: TMA (a.a.) | B35: 0.18
A36: Meses entre pagar o ponto e inaugurar | B36: 6
A37: Estrutura da franqueadora - ano 1 (R$/mes) | B37: 11250
A38: Estrutura da franqueadora - ano 2 (R$/mes) | B38: 28000
A39: Estrutura da franqueadora - ano 3 (R$/mes) | B39: 42000
A40: Estrutura da franqueadora - ano 4 (R$/mes) | B40: 52000
A41: Estrutura da franqueadora - ano 5 (R$/mes) | B41: 60000
A42: Estrutura da franqueadora - ano 6 (R$/mes) | B42: 68000
A43: Estrutura da franqueadora - ano 7 (R$/mes) | B43: 76000
A44: Estrutura da franqueadora - ano 8 (R$/mes) | B44: 86000
A45: Estrutura da franqueadora - ano 9 (R$/mes) | B45: 94000
A46: Estrutura da franqueadora - ano 10 (R$/mes) | B46: 102000

Sheet Franqueado
A1: O FRANQUEADO NAS TRES ESTRUTURAS DE PONTO | 60 meses
A3: Mes | B3: Rampa | C3: Receita | D3: FCL A: aluga | E3: FCL B1: compramos | F3: FCL B2: sublocamos
A4: 1 | B4: =IF(A4<=3,0.35,IF(A4<=6,0.55,IF(A4<=9,0.75,IF(A4<=12,0.88,1)))) | C4: =Premissas!$B$6*B4 | D4: =(C4*(1-(IF((C4*12)<=0,0.06,IF((C4*12)<=180000,0.06,IF((C4*12)<=360000,((C4*12)*0.112-9360)/(C4*12),IF((C4*12)<=720000,((C4*12)*0.135-17640)/(C4*12),IF((C4*12)<=1800000,((C4*12)*0.16-35640)/(C4*12),0.165))))))-Premissas!$B$7-Premissas!$B$11-Premissas!$B$12)-Premissas!$B$13-Premissas!$B$8-Premissas!$B$17)-C4*0.015 | E4: =(C4*(1-(IF((C4*12)<=0,0.06,IF((C4*12)<=180000,0.06,IF((C4*12)<=360000,((C4*12)*0.112-9360)/(C4*12),IF((C4*12)<=720000,((C4*12)*0.135-17640)/(C4*12),IF((C4*12)<=1800000,((C4*12)*0.16-35640)/(C4*12),0.165))))))-Premissas!$B$7-Premissas!$B$11-Premissas!$B$12)-Premissas!$B$13-Premissas!$B$8-Premissas!$B$18)-C4*0.015 | F4: =(C4*(1-(IF((C4*12)<=0,0.06,IF((C4*12)<=180000,0.06,IF((C4*12)<=360000,((C4*12)*0.112-9360)/(C4*12),IF((C4*12)<=720000,((C4*12)*0.135-17640)/(C4*12),IF((C4*12)<=1800000,((C4*12)*0.16-35640)/(C4*12),0.165))))))-Premissas!$B$7-Premissas!$B$11-Premissas!$B$12)-Premissas!$B$13-Premissas!$B$8-Premissas!$B$19)-C4*0.015
A5: 2 | B5: =IF(A5<=3,0.35,IF(A5<=6,0.55,IF(A5<=9,0.75,IF(A5<=12,0.88,1)))) | C5: =Premissas!$B$6*B5 | D5: =(C5*(1-(IF((C5*12)<=0,0.06,IF((C5*12)<=180000,0.06,IF((C5*12)<=360000,((C5*12)*0.112-9360)/(C5*12),IF((C5*12)<=720000,((C5*12)*0.135-17640)/(C5*12),IF((C5*12)<=1800000,((C5*12)*0.16-35640)/(C5*12),0.165))))))-Premissas!$B$7-Premissas!$B$11-Premissas!$B$12)-Premissas!$B$13-Premissas!$B$8-Premissas!$B$17)-C5*0.015 | E5: =(C5*(1-(IF((C5*12)<=0,0.06,IF((C5*12)<=180000,0.06,IF((C5*12)<=360000,((C5*12)*0.112-9360)/(C5*12),IF((C5*12)<=720000,((C5*12)*0.135-17640)/(C5*12),IF((C5*12)<=1800000,((C5*12)*0.16-35640)/(C5*12),0.165))))))-Premissas!$B$7-Premissas!$B$11-Premissas!$B$12)-Premissas!$B$13-Premissas!$B$8-Premissas!$B$18)-C5*0.015 | F5: =(C5*(1-(IF((C5*12)<=0,0.06,IF((C5*12)<=180000,0.06,IF((C5*12)<=360000,((C5*12)*0.112-9360)/(C5*12),IF((C5*12)<=720000,((C5*12)*0.135-17640)/(C5*12),IF((C5*12)<=1800000,((C5*12)*0.16-35640)/(C5*12),0.165))))))-Premissas!$B$7-Premissas!$B$11-Premissas!$B$12)-Premissas!$B$13-Premissas!$B$8-Premissas!$B$19)-C5*0.015
A6: 3 | B6: =IF(A6<=3,0.35,IF(A6<=6,0.55,IF(A6<=9,0.75,IF(A6<=12,0.88,1)))) | C6: =Premissas!$B$6*B6 | D6: =(C6*(1-(IF((C6*12)<=0,0.06,IF((C6*12)<=180000,0.06,IF((C6*12)<=360000,((C6*12)*0.112-9360)/(C6*12),IF((C6*12)<=720000,((C6*12)*0.135-17640)/(C6*12),IF((C6*12)<=1800000,((C6*12)*0.16-35640)/(C6*12),0.165))))))-Premissas!$B$7-Premissas!$B$11-Premissas!$B$12)-Premissas!$B$13-Premissas!$B$8-Premissas!$B$17)-C6*0.015 | E6: =(C6*(1-(IF((C6*12)<=0,0.06,IF((C6*12)<=180000,0.06,IF((C6*12)<=360000,((C6*12)*0.112-9360)/(C6*12),IF((C6*12)<=720000,((C6*12)*0.135-17640)/(C6*12),IF((C6*12)<=1800000,((C6*12)*0.16-35640)/(C6*12),0.165))))))-Premissas!$B$7-Premissas!$B$11-Premissas!$B$12)-Premissas!$B$13-Premissas!$B$8-Premissas!$B$18)-C6*0.015 | F6: =(C6*(1-(IF((C6*12)<=0,0.06,IF((C6*12)<=180000,0.06,IF((C6*12)<=360000,((C6*12)*0.112-9360)/(C6*12),IF((C6*12)<=720000,((C6*12)*0.135-17640)/(C6*12),IF((C6*12)<=1800000,((C6*12)*0.16-35640)/(C6*12),0.165))))))-Premissas!$B$7-Premissas!$B$11-Premissas!$B$12)-Premissas!$B$13-Premissas!$B$8-Premissas!$B$19)-C6*0.015
A7: 4 | B7: =IF(A7<=3,0.35,IF(A7<=6,0.55,IF(A7<=9,0.75,IF(A7<=12,0.88,1)))) | C7: =Premissas!$B$6*B7 | D7: =(C7*(1-(IF((C7*12)<=0,0.06,IF((C7*12)<=180000,0.06,IF((C7*12)<=360000,((C7*12)*0.112-9360)/(C7*12),IF((C7*12)<=720000,((C7*12)*0.135-17640)/(C7*12),IF((C7*12)<=1800000,((C7*12)*0.16-35640)/(C7*12),0.165))))))-Premissas!$B$7-Premissas!$B$11-Premissas!$B$12)-Premissas!$B$13-Premissas!$B$8-Premissas!$B$17)-C7*0.015 | E7: =(C7*(1-(IF((C7*12)<=0,0.06,IF((C7*12)<=180000,0.06,IF((C7*12)<=360000,((C7*12)*0.112-9360)/(C7*12),IF((C7*12)<=720000,((C7*12)*0.135-17640)/(C7*12),IF((C7*12)<=1800000,((C7*12)*0.16-35640)/(C7*12),0.165))))))-Premissas!$B$7-Premissas!$B$11-Premissas!$B$12)-Premissas!$B$13-Premissas!$B$8-Premissas!$B$18)-C7*0.015 | F7: =(C7*(1-(IF((C7*12)<=0,0.06,IF((C7*12)<=180000,0.06,IF((C7*12)<=360000,((C7*12)*0.112-9360)/(C7*12),IF((C7*12)<=720000,((C7*12)*0.135-17640)/(C7*12),IF((C7*12)<=1800000,((C7*12)*0.16-35640)/(C7*12),0.165))))))-Premissas!$B$7-Premissas!$B$11-Premissas!$B$12)-Premissas!$B$13-Premissas!$B$8-Premissas!$B$19)-C7*0.015
A8: 5 | B8: =IF(A8<=3,0.35,IF(A8<=6,0.55,IF(A8<=9,0.75,IF(A8<=12,0.88,1)))) | C8: =Premissas!$B$6*B8 | D8: =(C8*(1-(IF((C8*12)<=0,0.06,IF((C8*12)<=180000,0.06,IF((C8*12)<=360000,((C8*12)*0.112-9360)/(C8*12),IF((C8*12)<=720000,((C8*12)*0.135-17640)/(C8*12),IF((C8*12)<=1800000,((C8*12)*0.16-35640)/(C8*12),0.165))))))-Premissas!$B$7-Premissas!$B$11-Premissas!$B$12)-Premissas!$B$13-Premissas!$B$8-Premissas!$B$17)-C8*0.015 | E8: =(C8*(1-(IF((C8*12)<=0,0.06,IF((C8*12)<=180000,0.06,IF((C8*12)<=360000,((C8*12)*0.112-9360)/(C8*12),IF((C8*12)<=720000,((C8*12)*0.135-17640)/(C8*12),IF((C8*12)<=1800000,((C8*12)*0.16-35640)/(C8*12),0.165))))))-Premissas!$B$7-Premissas!$B$11-Premissas!$B$12)-Premissas!$B$13-Premissas!$B$8-Premissas!$B$18)-C8*0.015 | F8: =(C8*(1-(IF((C8*12)<=0,0.06,IF((C8*12)<=180000,0.06,IF((C8*12)<=360000,((C8*12)*0.112-9360)/(C8*12),IF((C8*12)<=720000,((C8*12)*0.135-17640)/(C8*12),IF((C8*12)<=1800000,((C8*12)*0.16-35640)/(C8*12),0.165))))))-Premissas!$B$7-Premissas!$B$11-Premissas!$B$12)-Premissas!$B$13-Premissas!$B$8-Premissas!$B$19)-C8*0.015
A9: 6 | B9: =IF(A9<=3,0.35,IF(A9<=6,0.55,IF(A9<=9,0.75,IF(A9<=12,0.88,1)))) | C9: =Premissas!$B$6*B9 | D9: =(C9*(1-(IF((C9*12)<=0,0.06,IF((C9*12)<=180000,0.06,IF((C9*12)<=360000,((C9*12)*0.112-9360)/(C9*12),IF((C9*12)<=720000,((C9*12)*0.135-17640)/(C9*12),IF((C9*12)<=1800000,((C9*12)*0.16-35640)/(C9*12),0.165))))))-Premissas!$B$7-Premissas!$B$11-Premissas!$B$12)-Premissas!$B$13-Premissas!$B$8-Premissas!$B$17)-C9*0.015 | E9: =(C9*(1-(IF((C9*12)<=0,0.06,IF((C9*12)<=180000,0.06,IF((C9*12)<=360000,((C9*12)*0.112-9360)/(C9*12),IF((C9*12)<=720000,((C9*12)*0.135-17640)/(C9*12),IF((C9*12)<=1800000,((C9*12)*0.16-35640)/(C9*12),0.165))))))-Premissas!$B$7-Premissas!$B$11-Premissas!$B$12)-Premissas!$B$13-Premissas!$B$8-Premissas!$B$18)-C9*0.015 | F9: =(C9*(1-(IF((C9*12)<=0,0.06,IF((C9*12)<=180000,0.06,IF((C9*12)<=360000,((C9*12)*0.112-9360)/(C9*12),IF((C9*12)<=720000,((C9*12)*0.135-17640)/(C9*12),IF((C9*12)<=1800000,((C9*12)*0.16-35640)/(C9*12),0.165))))))-Premissas!$B$7-Premissas!$B$11-Premissas!$B$12)-Premissas!$B$13-Premissas!$B$8-Premissas!$B$19)-C9*0.015
A10: 7 | B10: =IF(A10<=3,0.35,IF(A10<=6,0.55,IF(A10<=9,0.75,IF(A10<=12,0.88,1)))) | C10: =Premissas!$B$6*B10 | D10: =(C10*(1-(IF((C10*12)<=0,0.06,IF((C10*12)<=180000,0.06,IF((C10*12)<=360000,((C10*12)*0.112-9360)/(C10*12),IF((C10*12)<=720000,((C10*12)*0.135-17640)/(C10*12),IF((C10*12)<=1800000,((C10*12)*0.16-35640)/(C10*12),0.165))))))-Premissas!$B$7-Premissas!$B$11-Premissas!$B$12)-Premissas!$B$13-Premissas!$B$8-Premissas!$B$17)-C10*0.015 | E10: =(C10*(1-(IF((C10*12)<=0,0.06,IF((C10*12)<=180000,0.06,IF((C10*12)<=360000,((C10*12)*0.112-9360)/(C10*12),IF((C10*12)<=720000,((C10*12)*0.135-17640)/(C10*12),IF((C10*12)<=1800000,((C10*12)*0.16-35640)/(C10*12),0.165))))))-Premissas!$B$7-Premissas!$B$11-Premissas!$B$12)-Premissas!$B$13-Premissas!$B$8-Premissas!$B$18)-C10*0.015 | F10: =(C10*(1-(IF((C10*12)<=0,0.06,IF((C10*12)<=180000,0.06,IF((C10*12)<=360000,((C10*12)*0.112-9360)/(C10*12),IF((C10*12)<=720000,((C10*12)*0.135-17640)/(C10*12),IF((C10*12)<=1800000,((C10*12)*0.16-35640)/(C10*12),0.165))))))-Premissas!$B$7-Premissas!$B$11-Premissas!$B$12)-Premissas!$B$13-Premissas!$B$8-Premissas!$B$19)-C10*0.015
A11: 8 | B11: =IF(A11<=3,0.35,IF(A11<=6,0.55,IF(A11<=9,0.75,IF(A11<=12,0.88,1)))) | C11: =Premissas!$B$6*B11 | D11: =(C11*(1-(IF((C11*12)<=0,0.06,IF((C11*12)<=180000,0.06,IF((C11*12)<=360000,((C11*12)*0.112-9360)/(C11*12),IF((C11*12)<=720000,((C11*12)*0.135-17640)/(C11*12),IF((C11*12)<=1800000,((C11*12)*0.16-35640)/(C11*12),0.165))))))-Premissas!$B$7-Premissas!$B$11-Premissas!$B$12)-Premissas!$B$13-Premissas!$B$8-Premissas!$B$17)-C11*0.015 | E11: =(C11*(1-(IF((C11*12)<=0,0.06,IF((C11*12)<=180000,0.06,IF((C11*12)<=360000,((C11*12)*0.112-9360)/(C11*12),IF((C11*12)<=720000,((C11*12)*0.135-17640)/(C11*12),IF((C11*12)<=1800000,((C11*12)*0.16-35640)/(C11*12),0.165))))))-Premissas!$B$7-Premissas!$B$11-Premissas!$B$12)-Premissas!$B$13-Premissas!$B$8-Premissas!$B$18)-C11*0.015 | F11: =(C11*(1-(IF((C11*12)<=0,0.06,IF((C11*12)<=180000,0.06,IF((C11*12)<=360000,((C11*12)*0.112-9360)/(C11*12),IF((C11*12)<=720000,((C11*12)*0.135-17640)/(C11*12),IF((C11*12)<=1800000,((C11*12)*0.16-35640)/(C11*12),0.165))))))-Premissas!$B$7-Premissas!$B$11-Premissas!$B$12)-Premissas!$B$13-Premissas!$B$8-Premissas!$B$19)-C11*0.015
A12: 9 | B12: =IF(A12<=3,0.35,IF(A12<=6,0.55,IF(A12<=9,0.75,IF(A12<=12,0.88,1)))) | C12: =Premissas!$B$6*B12 | D12: =(C12*(1-(IF((C12*12)<=0,0.06,IF((C12*12)<=180000,0.06,IF((C12*12)<=360000,((C12*12)*0.112-9360)/(C12*12),IF((C12*12)<=720000,((C12*12)*0.135-17640)/(C12*12),IF((C12*12)<=1800000,((C12*12)*0.16-35640)/(C12*12),0.165))))))-Premissas!$B$7-Premissas!$B$11-Premissas!$B$12)-Premissas!$B$13-Premissas!$B$8-Premissas!$B$17)-C12*0.015 | E12: =(C12*(1-(IF((C12*12)<=0,0.06,IF((C12*12)<=180000,0.06,IF((C12*12)<=360000,((C12*12)*0.112-9360)/(C12*12),IF((C12*12)<=720000,((C12*12)*0.135-17640)/(C12*12),IF((C12*12)<=1800000,((C12*12)*0.16-35640)/(C12*12),0.165))))))-Premissas!$B$7-Premissas!$B$11-Premissas!$B$12)-Premissas!$B$13-Premissas!$B$8-Premissas!$B$18)-C12*0.015 | F12: =(C12*(1-(IF((C12*12)<=0,0.06,IF((C12*12)<=180000,0.06,IF((C12*12)<=360000,((C12*12)*0.112-9360)/(C12*12),IF((C12*12)<=720000,((C12*12)*0.135-17640)/(C12*12),IF((C12*12)<=1800000,((C12*12)*0.16-35640)/(C12*12),0.165))))))-Premissas!$B$7-Premissas!$B$11-Premissas!$B$12)-Premissas!$B$13-Premissas!$B$8-Premissas!$B$19)-C12*0.015
A13: 10 | B13: =IF(A13<=3,0.35,IF(A13<=6,0.55,IF(A13<=9,0.75,IF(A13<=12,0.88,1)))) | C13: =Premissas!$B$6*B13 | D13: =(C13*(1-(IF((C13*12)<=0,0.06,IF((C13*12)<=180000,0.06,IF((C13*12)<=360000,((C13*12)*0.112-9360)/(C13*12),IF((C13*12)<=720000,((C13*12)*0.135-17640)/(C13*12),IF((C13*12)<=1800000,((C13*12)*0.16-35640)/(C13*12),0.165))))))-Premissas!$B$7-Premissas!$B$11-Premissas!$B$12)-Premissas!$B$13-Premissas!$B$8-Premissas!$B$17)-C13*0.015 | E13: =(C13*(1-(IF((C13*12)<=0,0.06,IF((C13*12)<=180000,0.06,IF((C13*12)<=360000,((C13*12)*0.112-9360)/(C13*12),IF((C13*12)<=720000,((C13*12)*0.135-17640)/(C13*12),IF((C13*12)<=1800000,((C13*12)*0.16-35640)/(C13*12),0.165))))))-Premissas!$B$7-Premissas!$B$11-Premissas!$B$12)-Premissas!$B$13-Premissas!$B$8-Premissas!$B$18)-C13*0.015 | F13: =(C13*(1-(IF((C13*12)<=0,0.06,IF((C13*12)<=180000,0.06,IF((C13*12)<=360000,((C13*12)*0.112-9360)/(C13*12),IF((C13*12)<=720000,((C13*12)*0.135-17640)/(C13*12),IF((C13*12)<=1800000,((C13*12)*0.16-35640)/(C13*12),0.165))))))-Premissas!$B$7-Premissas!$B$11-Premissas!$B$12)-Premissas!$B$13-Premissas!$B$8-Premissas!$B$19)-C13*0.015
A14: 11 | B14: =IF(A14<=3,0.35,IF(A14<=6,0.55,IF(A14<=9,0.75,IF(A14<=12,0.88,1)))) | C14: =Premissas!$B$6*B14 | D14: =(C14*(1-(IF((C14*12)<=0,0.06,IF((C14*12)<=180000,0.06,IF((C14*12)<=360000,((C14*12)*0.112-9360)/(C14*12),IF((C14*12)<=720000,((C14*12)*0.135-17640)/(C14*12),IF((C14*12)<=1800000,((C14*12)*0.16-35640)/(C14*12),0.165))))))-Premissas!$B$7-Premissas!$B$11-Premissas!$B$12)-Premissas!$B$13-Premissas!$B$8-Premissas!$B$17)-C14*0.015 | E14: =(C14*(1-(IF((C14*12)<=0,0.06,IF((C14*12)<=180000,0.06,IF((C14*12)<=360000,((C14*12)*0.112-9360)/(C14*12),IF((C14*12)<=720000,((C14*12)*0.135-17640)/(C14*12),IF((C14*12)<=1800000,((C14*12)*0.16-35640)/(C14*12),0.165))))))-Premissas!$B$7-Premissas!$B$11-Premissas!$B$12)-Premissas!$B$13-Premissas!$B$8-Premissas!$B$18)-C14*0.015 | F14: =(C14*(1-(IF((C14*12)<=0,0.06,IF((C14*12)<=180000,0.06,IF((C14*12)<=360000,((C14*12)*0.112-9360)/(C14*12),IF((C14*12)<=720000,((C14*12)*0.135-17640)/(C14*12),IF((C14*12)<=1800000,((C14*12)*0.16-35640)/(C14*12),0.165))))))-Premissas!$B$7-Premissas!$B$11-Premissas!$B$12)-Premissas!$B$13-Premissas!$B$8-Premissas!$B$19)-C14*0.015
A15: 12 | B15: =IF(A15<=3,0.35,IF(A15<=6,0.55,IF(A15<=9,0.75,IF(A15<=12,0.88,1)))) | C15: =Premissas!$B$6*B15 | D15: =(C15*(1-(IF((C15*12)<=0,0.06,IF((C15*12)<=180000,0.06,IF((C15*12)<=360000,((C15*12)*0.112-9360)/(C15*12),IF((C15*12)<=720000,((C15*12)*0.135-17640)/(C15*12),IF((C15*12)<=1800000,((C15*12)*0.16-35640)/(C15*12),0.165))))))-Premissas!$B$7-Premissas!$B$11-Premissas!$B$12)-Premissas!$B$13-Premissas!$B$8-Premissas!$B$17)-C15*0.015 | E15: =(C15*(1-(IF((C15*12)<=0,0.06,IF((C15*12)<=180000,0.06,IF((C15*12)<=360000,((C15*12)*0.112-9360)/(C15*12),IF((C15*12)<=720000,((C15*12)*0.135-17640)/(C15*12),IF((C15*12)<=1800000,((C15*12)*0.16-35640)/(C15*12),0.165))))))-Premissas!$B$7-Premissas!$B$11-Premissas!$B$12)-Premissas!$B$13-Premissas!$B$8-Premissas!$B$18)-C15*0.015 | F15: =(C15*(1-(IF((C15*12)<=0,0.06,IF((C15*12)<=180000,0.06,IF((C15*12)<=360000,((C15*12)*0.112-9360)/(C15*12),IF((C15*12)<=720000,((C15*12)*0.135-17640)/(C15*12),IF((C15*12)<=1800000,((C15*12)*0.16-35640)/(C15*12),0.165))))))-Premissas!$B$7-Premissas!$B$11-Premissas!$B$12)-Premissas!$B$13-Premissas!$B$8-Premissas!$B$19)-C15*0.015
... A62: 59 | B62: =IF(A62<=3,0.35,IF(A62<=6,0.55,IF(A62<=9,0.75,IF(A62<=12,0.88,1)))) | C62: =Premissas!$B$6*B62 | D62: =(C62*(1-(IF((C62*12)<=0,0.06,IF((C62*12)<=180000,0.06,IF((C62*12)<=360000,((C62*12)*0.112-9360)/(C62*12),IF((C62*12)<=720000,((C62*12)*0.135-17640)/(C62*12),IF((C62*12)<=1800000,((C62*12)*0.16-35640)/(C62*12),0.165))))))-Premissas!$B$7-Premissas!$B$11-Premissas!$B$12)-Premissas!$B$13-Premissas!$B$8-Premissas!$B$17)-C62*0.015 | E62: =(C62*(1-(IF((C62*12)<=0,0.06,IF((C62*12)<=180000,0.06,IF((C62*12)<=360000,((C62*12)*0.112-9360)/(C62*12),IF((C62*12)<=720000,((C62*12)*0.135-17640)/(C62*12),IF((C62*12)<=1800000,((C62*12)*0.16-35640)/(C62*12),0.165))))))-Premissas!$B$7-Premissas!$B$11-Premissas!$B$12)-Premissas!$B$13-Premissas!$B$8-Premissas!$B$18)-C62*0.015 | F62: =(C62*(1-(IF((C62*12)<=0,0.06,IF((C62*12)<=180000,0.06,IF((C62*12)<=360000,((C62*12)*0.112-9360)/(C62*12),IF((C62*12)<=720000,((C62*12)*0.135-17640)/(C62*12),IF((C62*12)<=1800000,((C62*12)*0.16-35640)/(C62*12),0.165))))))-Premissas!$B$7-Premissas!$B$11-Premissas!$B$12)-Premissas!$B$13-Premissas!$B$8-Premissas!$B$19)-C62*0.015
A63: 60 | B63: =IF(A63<=3,0.35,IF(A63<=6,0.55,IF(A63<=9,0.75,IF(A63<=12,0.88,1)))) | C63: =Premissas!$B$6*B63 | D63: =(C63*(1-(IF((C63*12)<=0,0.06,IF((C63*12)<=180000,0.06,IF((C63*12)<=360000,((C63*12)*0.112-9360)/(C63*12),IF((C63*12)<=720000,((C63*12)*0.135-17640)/(C63*12),IF((C63*12)<=1800000,((C63*12)*0.16-35640)/(C63*12),0.165))))))-Premissas!$B$7-Premissas!$B$11-Premissas!$B$12)-Premissas!$B$13-Premissas!$B$8-Premissas!$B$17)-C63*0.015+Premissas!$B$28*Premissas!$B$30 | E63: =(C63*(1-(IF((C63*12)<=0,0.06,IF((C63*12)<=180000,0.06,IF((C63*12)<=360000,((C63*12)*0.112-9360)/(C63*12),IF((C63*12)<=720000,((C63*12)*0.135-17640)/(C63*12),IF((C63*12)<=1800000,((C63*12)*0.16-35640)/(C63*12),0.165))))))-Premissas!$B$7-Premissas!$B$11-Premissas!$B$12)-Premissas!$B$13-Premissas!$B$8-Premissas!$B$18)-C63*0.015+Premissas!$B$29*Premissas!$B$30 | F63: =(C63*(1-(IF((C63*12)<=0,0.06,IF((C63*12)<=180000,0.06,IF((C63*12)<=360000,((C63*12)*0.112-9360)/(C63*12),IF((C63*12)<=720000,((C63*12)*0.135-17640)/(C63*12),IF((C63*12)<=1800000,((C63*12)*0.16-35640)/(C63*12),0.165))))))-Premissas!$B$7-Premissas!$B$11-Premissas!$B$12)-Premissas!$B$13-Premissas!$B$8-Premissas!$B$19)-C63*0.015+Premissas!$B$29*Premissas!$B$30
A66: RESULTADO
A67: Investimento do franqueado | D67: =Premissas!$B$26 | E67: =Premissas!$B$27 | F67: =Premissas!$B$27
A68: Aluguel que ele paga | D68: =Premissas!$B$17 | E68: =Premissas!$B$18 | F68: =Premissas!$B$19
A69: EBITDA maduro/mes | D69: =D63-Premissas!$B$28*Premissas!$B$30+C63*0.015 | E69: =E63-Premissas!$B$29*Premissas!$B$30+C63*0.015 | F69: =F63-Premissas!$B$29*Premissas!$B$30+C63*0.015
A70: Margem EBITDA | D70: =IF(C63=0,0,D69/C63) | E70: =IF(C63=0,0,E69/C63) | F70: =IF(C63=0,0,F69/C63)
A71: TIR anual | D71: =IFERROR((1+IRR(D77:D137,0.02))^12-1,"nao converge") | E71: =IFERROR((1+IRR(E77:E137,0.02))^12-1,"nao converge") | F71: =IFERROR((1+IRR(F77:F137,0.02))^12-1,"nao converge")
A72: VPL na TMA | D72: =NPV((1+Premissas!$B$35)^(1/12)-1,D78:D137)+D77 | E72: =NPV((1+Premissas!$B$35)^(1/12)-1,E78:E137)+E77 | F72: =NPV((1+Premissas!$B$35)^(1/12)-1,F78:F137)+F77
A73: Payback (meses) | D73: =IFERROR(MATCH(TRUE,INDEX(H78:H137>=0,0),0),"nao paga") | E73: =IFERROR(MATCH(TRUE,INDEX(I78:I137>=0,0),0),"nao paga") | F73: =IFERROR(MATCH(TRUE,INDEX(J78:J137>=0,0),0),"nao paga")
A75: Fluxo com o mes 0 (para IRR / NPV / payback)
A76: Mes | D76: A | E76: B1 | F76: B2 | H76: Caixa acumulado A | I76: B1 | J76: B2
A77: 0 | D77: =-Premissas!$B$26 | E77: =-Premissas!$B$27 | F77: =-Premissas!$B$27 | H77: =D77 | I77: =E77 | J77: =F77
A78: 1 | D78: =D4 | E78: =E4 | F78: =F4 | H78: =H77+D78 | I78: =I77+E78 | J78: =J77+F78
A79: 2 | D79: =D5 | E79: =E5 | F79: =F5 | H79: =H78+D79 | I79: =I78+E79 | J79: =J78+F79
A80: 3 | D80: =D6 | E80: =E6 | F80: =F6 | H80: =H79+D80 | I80: =I79+E80 | J80: =J79+F80
A81: 4 | D81: =D7 | E81: =E7 | F81: =F7 | H81: =H80+D81 | I81: =I80+E81 | J81: =J80+F81
A82: 5 | D82: =D8 | E82: =E8 | F82: =F8 | H82: =H81+D82 | I82: =I81+E82 | J82: =J81+F82
A83: 6 | D83: =D9 | E83: =E9 | F83: =F9 | H83: =H82+D83 | I83: =I82+E83 | J83: =J82+F83
A84: 7 | D84: =D10 | E84: =E10 | F84: =F10 | H84: =H83+D84 | I84: =I83+E84 | J84: =J83+F84
A85: 8 | D85: =D11 | E85: =E11 | F85: =F11 | H85: =H84+D85 | I85: =I84+E85 | J85: =J84+F85
A86: 9 | D86: =D12 | E86: =E12 | F86: =F12 | H86: =H85+D86 | I86: =I85+E86 | J86: =J85+F86
A87: 10 | D87: =D13 | E87: =E13 | F87: =F13 | H87: =H86+D87 | I87: =I86+E87 | J87: =J86+F87
A88: 11 | D88: =D14 | E88: =E14 | F88: =F14 | H88: =H87+D88 | I88: =I87+E88 | J88: =J87+F88
A89: 12 | D89: =D15 | E89: =E15 | F89: =F15 | H89: =H88+D89 | I89: =I88+E89 | J89: =J88+F89
... A137: 60 | D137: =D63 | E137: =E63 | F137: =F63 | H137: =H136+D137 | I137: =I136+E137 | J137: =J136+F137

Sheet Franqueadora
A1: A FRANQUEADORA | 120 meses | escolha a estrutura em B4
A3: Estrutura do ponto (A, B1 ou B2):
A4: A | B4: A = asset-light (capital zero no imovel) B1 = compramos terreno e construimos B2 = alugamos longo e sublocamos
A6: Mes | B6: Ano | C6: Unidades ativas | D6: Receita da rede | E6: Royalty | F6: Tecnologia | G6: Aluguel recebido | H6: Receita bruta | I6: Tributos | J6: Estrutura | K6: Custo do imovel | L6: Aluguel pago | M6: EBITDA | N6: Capex do ponto | O6: Taxa de franquia | P6: Fluxo livre | Q6: Caixa acumulado
A7: 1 | B7: =ROUNDUP(A7/12,0) | C7: =COUNTIF(Cronograma!$B$4:$B$68,"<="&A7) | D7: =Premissas!$B$6*(COUNTIFS(Cronograma!$B$4:$B$68,">="&A7-2,Cronograma!$B$4:$B$68,"<="&A7)*0.35+COUNTIFS(Cronograma!$B$4:$B$68,">="&A7-5,Cronograma!$B$4:$B$68,"<="&A7-3)*0.55+COUNTIFS(Cronograma!$B$4:$B$68,">="&A7-8,Cronograma!$B$4:$B$68,"<="&A7-6)*0.75+COUNTIFS(Cronograma!$B$4:$B$68,">="&A7-11,Cronograma!$B$4:$B$68,"<="&A7-9)*0.88+COUNTIF(Cronograma!$B$4:$B$68,"<="&A7-12)*1) | E7: =D7*Premissas!$B$11 | F7: =C7*Premissas!$B$13 | G7: =IF($A$4="B1",C7*Premissas!$B$18,IF($A$4="B2",C7*Premissas!$B$19,0)) | H7: =E7+F7+G7 | I7: =(E7+F7)*Premissas!$B$33+G7*Premissas!$B$34 | J7: =INDEX(Premissas!$B$37:$B$46,MIN(10,B7)) | K7: =IF($A$4="B1",C7*Premissas!$B$22,IF($A$4="B2",C7*Premissas!$B$23,0)) | L7: =IF($A$4="B2",C7*Premissas!$B$17,0) | M7: =H7-I7-J7-K7-L7 | N7: =COUNTIF(Cronograma!$B$4:$B$68,"="&A7+Premissas!$B$36)*IF($A$4="B1",Premissas!$B$20+Premissas!$B$21,IF($A$4="B2",Premissas!$B$21,0)) | O7: =COUNTIF(Cronograma!$B$4:$B$68,"="&A7+3)*Premissas!$B$14*(1-Premissas!$B$33) | P7: =M7-N7+O7 | Q7: =P7
A8: 2 | B8: =ROUNDUP(A8/12,0) | C8: =COUNTIF(Cronograma!$B$4:$B$68,"<="&A8) | D8: =Premissas!$B$6*(COUNTIFS(Cronograma!$B$4:$B$68,">="&A8-2,Cronograma!$B$4:$B$68,"<="&A8)*0.35+COUNTIFS(Cronograma!$B$4:$B$68,">="&A8-5,Cronograma!$B$4:$B$68,"<="&A8-3)*0.55+COUNTIFS(Cronograma!$B$4:$B$68,">="&A8-8,Cronograma!$B$4:$B$68,"<="&A8-6)*0.75+COUNTIFS(Cronograma!$B$4:$B$68,">="&A8-11,Cronograma!$B$4:$B$68,"<="&A8-9)*0.88+COUNTIF(Cronograma!$B$4:$B$68,"<="&A8-12)*1) | E8: =D8*Premissas!$B$11 | F8: =C8*Premissas!$B$13 | G8: =IF($A$4="B1",C8*Premissas!$B$18,IF($A$4="B2",C8*Premissas!$B$19,0)) | H8: =E8+F8+G8 | I8: =(E8+F8)*Premissas!$B$33+G8*Premissas!$B$34 | J8: =INDEX(Premissas!$B$37:$B$46,MIN(10,B8)) | K8: =IF($A$4="B1",C8*Premissas!$B$22,IF($A$4="B2",C8*Premissas!$B$23,0)) | L8: =IF($A$4="B2",C8*Premissas!$B$17,0) | M8: =H8-I8-J8-K8-L8 | N8: =COUNTIF(Cronograma!$B$4:$B$68,"="&A8+Premissas!$B$36)*IF($A$4="B1",Premissas!$B$20+Premissas!$B$21,IF($A$4="B2",Premissas!$B$21,0)) | O8: =COUNTIF(Cronograma!$B$4:$B$68,"="&A8+3)*Premissas!$B$14*(1-Premissas!$B$33) | P8: =M8-N8+O8 | Q8: =Q7+P8
A9: 3 | B9: =ROUNDUP(A9/12,0) | C9: =COUNTIF(Cronograma!$B$4:$B$68,"<="&A9) | D9: =Premissas!$B$6*(COUNTIFS(Cronograma!$B$4:$B$68,">="&A9-2,Cronograma!$B$4:$B$68,"<="&A9)*0.35+COUNTIFS(Cronograma!$B$4:$B$68,">="&A9-5,Cronograma!$B$4:$B$68,"<="&A9-3)*0.55+COUNTIFS(Cronograma!$B$4:$B$68,">="&A9-8,Cronograma!$B$4:$B$68,"<="&A9-6)*0.75+COUNTIFS(Cronograma!$B$4:$B$68,">="&A9-11,Cronograma!$B$4:$B$68,"<="&A9-9)*0.88+COUNTIF(Cronograma!$B$4:$B$68,"<="&A9-12)*1) | E9: =D9*Premissas!$B$11 | F9: =C9*Premissas!$B$13 | G9: =IF($A$4="B1",C9*Premissas!$B$18,IF($A$4="B2",C9*Premissas!$B$19,0)) | H9: =E9+F9+G9 | I9: =(E9+F9)*Premissas!$B$33+G9*Premissas!$B$34 | J9: =INDEX(Premissas!$B$37:$B$46,MIN(10,B9)) | K9: =IF($A$4="B1",C9*Premissas!$B$22,IF($A$4="B2",C9*Premissas!$B$23,0)) | L9: =IF($A$4="B2",C9*Premissas!$B$17,0) | M9: =H9-I9-J9-K9-L9 | N9: =COUNTIF(Cronograma!$B$4:$B$68,"="&A9+Premissas!$B$36)*IF($A$4="B1",Premissas!$B$20+Premissas!$B$21,IF($A$4="B2",Premissas!$B$21,0)) | O9: =COUNTIF(Cronograma!$B$4:$B$68,"="&A9+3)*Premissas!$B$14*(1-Premissas!$B$33) | P9: =M9-N9+O9 | Q9: =Q8+P9
A10: 4 | B10: =ROUNDUP(A10/12,0) | C10: =COUNTIF(Cronograma!$B$4:$B$68,"<="&A10) | D10: =Premissas!$B$6*(COUNTIFS(Cronograma!$B$4:$B$68,">="&A10-2,Cronograma!$B$4:$B$68,"<="&A10)*0.35+COUNTIFS(Cronograma!$B$4:$B$68,">="&A10-5,Cronograma!$B$4:$B$68,"<="&A10-3)*0.55+COUNTIFS(Cronograma!$B$4:$B$68,">="&A10-8,Cronograma!$B$4:$B$68,"<="&A10-6)*0.75+COUNTIFS(Cronograma!$B$4:$B$68,">="&A10-11,Cronograma!$B$4:$B$68,"<="&A10-9)*0.88+COUNTIF(Cronograma!$B$4:$B$68,"<="&A10-12)*1) | E10: =D10*Premissas!$B$11 | F10: =C10*Premissas!$B$13 | G10: =IF($A$4="B1",C10*Premissas!$B$18,IF($A$4="B2",C10*Premissas!$B$19,0)) | H10: =E10+F10+G10 | I10: =(E10+F10)*Premissas!$B$33+G10*Premissas!$B$34 | J10: =INDEX(Premissas!$B$37:$B$46,MIN(10,B10)) | K10: =IF($A$4="B1",C10*Premissas!$B$22,IF($A$4="B2",C10*Premissas!$B$23,0)) | L10: =IF($A$4="B2",C10*Premissas!$B$17,0) | M10: =H10-I10-J10-K10-L10 | N10: =COUNTIF(Cronograma!$B$4:$B$68,"="&A10+Premissas!$B$36)*IF($A$4="B1",Premissas!$B$20+Premissas!$B$21,IF($A$4="B2",Premissas!$B$21,0)) | O10: =COUNTIF(Cronograma!$B$4:$B$68,"="&A10+3)*Premissas!$B$14*(1-Premissas!$B$33) | P10: =M10-N10+O10 | Q10: =Q9+P10
A11: 5 | B11: =ROUNDUP(A11/12,0) | C11: =COUNTIF(Cronograma!$B$4:$B$68,"<="&A11) | D11: =Premissas!$B$6*(COUNTIFS(Cronograma!$B$4:$B$68,">="&A11-2,Cronograma!$B$4:$B$68,"<="&A11)*0.35+COUNTIFS(Cronograma!$B$4:$B$68,">="&A11-5,Cronograma!$B$4:$B$68,"<="&A11-3)*0.55+COUNTIFS(Cronograma!$B$4:$B$68,">="&A11-8,Cronograma!$B$4:$B$68,"<="&A11-6)*0.75+COUNTIFS(Cronograma!$B$4:$B$68,">="&A11-11,Cronograma!$B$4:$B$68,"<="&A11-9)*0.88+COUNTIF(Cronograma!$B$4:$B$68,"<="&A11-12)*1) | E11: =D11*Premissas!$B$11 | F11: =C11*Premissas!$B$13 | G11: =IF($A$4="B1",C11*Premissas!$B$18,IF($A$4="B2",C11*Premissas!$B$19,0)) | H11: =E11+F11+G11 | I11: =(E11+F11)*Premissas!$B$33+G11*Premissas!$B$34 | J11: =INDEX(Premissas!$B$37:$B$46,MIN(10,B11)) | K11: =IF($A$4="B1",C11*Premissas!$B$22,IF($A$4="B2",C11*Premissas!$B$23,0)) | L11: =IF($A$4="B2",C11*Premissas!$B$17,0) | M11: =H11-I11-J11-K11-L11 | N11: =COUNTIF(Cronograma!$B$4:$B$68,"="&A11+Premissas!$B$36)*IF($A$4="B1",Premissas!$B$20+Premissas!$B$21,IF($A$4="B2",Premissas!$B$21,0)) | O11: =COUNTIF(Cronograma!$B$4:$B$68,"="&A11+3)*Premissas!$B$14*(1-Premissas!$B$33) | P11: =M11-N11+O11 | Q11: =Q10+P11
A12: 6 | B12: =ROUNDUP(A12/12,0) | C12: =COUNTIF(Cronograma!$B$4:$B$68,"<="&A12) | D12: =Premissas!$B$6*(COUNTIFS(Cronograma!$B$4:$B$68,">="&A12-2,Cronograma!$B$4:$B$68,"<="&A12)*0.35+COUNTIFS(Cronograma!$B$4:$B$68,">="&A12-5,Cronograma!$B$4:$B$68,"<="&A12-3)*0.55+COUNTIFS(Cronograma!$B$4:$B$68,">="&A12-8,Cronograma!$B$4:$B$68,"<="&A12-6)*0.75+COUNTIFS(Cronograma!$B$4:$B$68,">="&A12-11,Cronograma!$B$4:$B$68,"<="&A12-9)*0.88+COUNTIF(Cronograma!$B$4:$B$68,"<="&A12-12)*1) | E12: =D12*Premissas!$B$11 | F12: =C12*Premissas!$B$13 | G12: =IF($A$4="B1",C12*Premissas!$B$18,IF($A$4="B2",C12*Premissas!$B$19,0)) | H12: =E12+F12+G12 | I12: =(E12+F12)*Premissas!$B$33+G12*Premissas!$B$34 | J12: =INDEX(Premissas!$B$37:$B$46,MIN(10,B12)) | K12: =IF($A$4="B1",C12*Premissas!$B$22,IF($A$4="B2",C12*Premissas!$B$23,0)) | L12: =IF($A$4="B2",C12*Premissas!$B$17,0) | M12: =H12-I12-J12-K12-L12 | N12: =COUNTIF(Cronograma!$B$4:$B$68,"="&A12+Premissas!$B$36)*IF($A$4="B1",Premissas!$B$20+Premissas!$B$21,IF($A$4="B2",Premissas!$B$21,0)) | O12: =COUNTIF(Cronograma!$B$4:$B$68,"="&A12+3)*Premissas!$B$14*(1-Premissas!$B$33) | P12: =M12-N12+O12 | Q12: =Q11+P12
A13: 7 | B13: =ROUNDUP(A13/12,0) | C13: =COUNTIF(Cronograma!$B$4:$B$68,"<="&A13) | D13: =Premissas!$B$6*(COUNTIFS(Cronograma!$B$4:$B$68,">="&A13-2,Cronograma!$B$4:$B$68,"<="&A13)*0.35+COUNTIFS(Cronograma!$B$4:$B$68,">="&A13-5,Cronograma!$B$4:$B$68,"<="&A13-3)*0.55+COUNTIFS(Cronograma!$B$4:$B$68,">="&A13-8,Cronograma!$B$4:$B$68,"<="&A13-6)*0.75+COUNTIFS(Cronograma!$B$4:$B$68,">="&A13-11,Cronograma!$B$4:$B$68,"<="&A13-9)*0.88+COUNTIF(Cronograma!$B$4:$B$68,"<="&A13-12)*1) | E13: =D13*Premissas!$B$11 | F13: =C13*Premissas!$B$13 | G13: =IF($A$4="B1",C13*Premissas!$B$18,IF($A$4="B2",C13*Premissas!$B$19,0)) | H13: =E13+F13+G13 | I13: =(E13+F13)*Premissas!$B$33+G13*Premissas!$B$34 | J13: =INDEX(Premissas!$B$37:$B$46,MIN(10,B13)) | K13: =IF($A$4="B1",C13*Premissas!$B$22,IF($A$4="B2",C13*Premissas!$B$23,0)) | L13: =IF($A$4="B2",C13*Premissas!$B$17,0) | M13: =H13-I13-J13-K13-L13 | N13: =COUNTIF(Cronograma!$B$4:$B$68,"="&A13+Premissas!$B$36)*IF($A$4="B1",Premissas!$B$20+Premissas!$B$21,IF($A$4="B2",Premissas!$B$21,0)) | O13: =COUNTIF(Cronograma!$B$4:$B$68,"="&A13+3)*Premissas!$B$14*(1-Premissas!$B$33) | P13: =M13-N13+O13 | Q13: =Q12+P13
A14: 8 | B14: =ROUNDUP(A14/12,0) | C14: =COUNTIF(Cronograma!$B$4:$B$68,"<="&A14) | D14: =Premissas!$B$6*(COUNTIFS(Cronograma!$B$4:$B$68,">="&A14-2,Cronograma!$B$4:$B$68,"<="&A14)*0.35+COUNTIFS(Cronograma!$B$4:$B$68,">="&A14-5,Cronograma!$B$4:$B$68,"<="&A14-3)*0.55+COUNTIFS(Cronograma!$B$4:$B$68,">="&A14-8,Cronograma!$B$4:$B$68,"<="&A14-6)*0.75+COUNTIFS(Cronograma!$B$4:$B$68,">="&A14-11,Cronograma!$B$4:$B$68,"<="&A14-9)*0.88+COUNTIF(Cronograma!$B$4:$B$68,"<="&A14-12)*1) | E14: =D14*Premissas!$B$11 | F14: =C14*Premissas!$B$13 | G14: =IF($A$4="B1",C14*Premissas!$B$18,IF($A$4="B2",C14*Premissas!$B$19,0)) | H14: =E14+F14+G14 | I14: =(E14+F14)*Premissas!$B$33+G14*Premissas!$B$34 | J14: =INDEX(Premissas!$B$37:$B$46,MIN(10,B14)) | K14: =IF($A$4="B1",C14*Premissas!$B$22,IF($A$4="B2",C14*Premissas!$B$23,0)) | L14: =IF($A$4="B2",C14*Premissas!$B$17,0) | M14: =H14-I14-J14-K14-L14 | N14: =COUNTIF(Cronograma!$B$4:$B$68,"="&A14+Premissas!$B$36)*IF($A$4="B1",Premissas!$B$20+Premissas!$B$21,IF($A$4="B2",Premissas!$B$21,0)) | O14: =COUNTIF(Cronograma!$B$4:$B$68,"="&A14+3)*Premissas!$B$14*(1-Premissas!$B$33) | P14: =M14-N14+O14 | Q14: =Q13+P14
A15: 9 | B15: =ROUNDUP(A15/12,0) | C15: =COUNTIF(Cronograma!$B$4:$B$68,"<="&A15) | D15: =Premissas!$B$6*(COUNTIFS(Cronograma!$B$4:$B$68,">="&A15-2,Cronograma!$B$4:$B$68,"<="&A15)*0.35+COUNTIFS(Cronograma!$B$4:$B$68,">="&A15-5,Cronograma!$B$4:$B$68,"<="&A15-3)*0.55+COUNTIFS(Cronograma!$B$4:$B$68,">="&A15-8,Cronograma!$B$4:$B$68,"<="&A15-6)*0.75+COUNTIFS(Cronograma!$B$4:$B$68,">="&A15-11,Cronograma!$B$4:$B$68,"<="&A15-9)*0.88+COUNTIF(Cronograma!$B$4:$B$68,"<="&A15-12)*1) | E15: =D15*Premissas!$B$11 | F15: =C15*Premissas!$B$13 | G15: =IF($A$4="B1",C15*Premissas!$B$18,IF($A$4="B2",C15*Premissas!$B$19,0)) | H15: =E15+F15+G15 | I15: =(E15+F15)*Premissas!$B$33+G15*Premissas!$B$34 | J15: =INDEX(Premissas!$B$37:$B$46,MIN(10,B15)) | K15: =IF($A$4="B1",C15*Premissas!$B$22,IF($A$4="B2",C15*Premissas!$B$23,0)) | L15: =IF($A$4="B2",C15*Premissas!$B$17,0) | M15: =H15-I15-J15-K15-L15 | N15: =COUNTIF(Cronograma!$B$4:$B$68,"="&A15+Premissas!$B$36)*IF($A$4="B1",Premissas!$B$20+Premissas!$B$21,IF($A$4="B2",Premissas!$B$21,0)) | O15: =COUNTIF(Cronograma!$B$4:$B$68,"="&A15+3)*Premissas!$B$14*(1-Premissas!$B$33) | P15: =M15-N15+O15 | Q15: =Q14+P15
A16: 10 | B16: =ROUNDUP(A16/12,0) | C16: =COUNTIF(Cronograma!$B$4:$B$68,"<="&A16) | D16: =Premissas!$B$6*(COUNTIFS(Cronograma!$B$4:$B$68,">="&A16-2,Cronograma!$B$4:$B$68,"<="&A16)*0.35+COUNTIFS(Cronograma!$B$4:$B$68,">="&A16-5,Cronograma!$B$4:$B$68,"<="&A16-3)*0.55+COUNTIFS(Cronograma!$B$4:$B$68,">="&A16-8,Cronograma!$B$4:$B$68,"<="&A16-6)*0.75+COUNTIFS(Cronograma!$B$4:$B$68,">="&A16-11,Cronograma!$B$4:$B$68,"<="&A16-9)*0.88+COUNTIF(Cronograma!$B$4:$B$68,"<="&A16-12)*1) | E16: =D16*Premissas!$B$11 | F16: =C16*Premissas!$B$13 | G16: =IF($A$4="B1",C16*Premissas!$B$18,IF($A$4="B2",C16*Premissas!$B$19,0)) | H16: =E16+F16+G16 | I16: =(E16+F16)*Premissas!$B$33+G16*Premissas!$B$34 | J16: =INDEX(Premissas!$B$37:$B$46,MIN(10,B16)) | K16: =IF($A$4="B1",C16*Premissas!$B$22,IF($A$4="B2",C16*Premissas!$B$23,0)) | L16: =IF($A$4="B2",C16*Premissas!$B$17,0) | M16: =H16-I16-J16-K16-L16 | N16: =COUNTIF(Cronograma!$B$4:$B$68,"="&A16+Premissas!$B$36)*IF($A$4="B1",Premissas!$B$20+Premissas!$B$21,IF($A$4="B2",Premissas!$B$21,0)) | O16: =COUNTIF(Cronograma!$B$4:$B$68,"="&A16+3)*Premissas!$B$14*(1-Premissas!$B$33) | P16: =M16-N16+O16 | Q16: =Q15+P16
A17: 11 | B17: =ROUNDUP(A17/12,0) | C17: =COUNTIF(Cronograma!$B$4:$B$68,"<="&A17) | D17: =Premissas!$B$6*(COUNTIFS(Cronograma!$B$4:$B$68,">="&A17-2,Cronograma!$B$4:$B$68,"<="&A17)*0.35+COUNTIFS(Cronograma!$B$4:$B$68,">="&A17-5,Cronograma!$B$4:$B$68,"<="&A17-3)*0.55+COUNTIFS(Cronograma!$B$4:$B$68,">="&A17-8,Cronograma!$B$4:$B$68,"<="&A17-6)*0.75+COUNTIFS(Cronograma!$B$4:$B$68,">="&A17-11,Cronograma!$B$4:$B$68,"<="&A17-9)*0.88+COUNTIF(Cronograma!$B$4:$B$68,"<="&A17-12)*1) | E17: =D17*Premissas!$B$11 | F17: =C17*Premissas!$B$13 | G17: =IF($A$4="B1",C17*Premissas!$B$18,IF($A$4="B2",C17*Premissas!$B$19,0)) | H17: =E17+F17+G17 | I17: =(E17+F17)*Premissas!$B$33+G17*Premissas!$B$34 | J17: =INDEX(Premissas!$B$37:$B$46,MIN(10,B17)) | K17: =IF($A$4="B1",C17*Premissas!$B$22,IF($A$4="B2",C17*Premissas!$B$23,0)) | L17: =IF($A$4="B2",C17*Premissas!$B$17,0) | M17: =H17-I17-J17-K17-L17 | N17: =COUNTIF(Cronograma!$B$4:$B$68,"="&A17+Premissas!$B$36)*IF($A$4="B1",Premissas!$B$20+Premissas!$B$21,IF($A$4="B2",Premissas!$B$21,0)) | O17: =COUNTIF(Cronograma!$B$4:$B$68,"="&A17+3)*Premissas!$B$14*(1-Premissas!$B$33) | P17: =M17-N17+O17 | Q17: =Q16+P17
A18: 12 | B18: =ROUNDUP(A18/12,0) | C18: =COUNTIF(Cronograma!$B$4:$B$68,"<="&A18) | D18: =Premissas!$B$6*(COUNTIFS(Cronograma!$B$4:$B$68,">="&A18-2,Cronograma!$B$4:$B$68,"<="&A18)*0.35+COUNTIFS(Cronograma!$B$4:$B$68,">="&A18-5,Cronograma!$B$4:$B$68,"<="&A18-3)*0.55+COUNTIFS(Cronograma!$B$4:$B$68,">="&A18-8,Cronograma!$B$4:$B$68,"<="&A18-6)*0.75+COUNTIFS(Cronograma!$B$4:$B$68,">="&A18-11,Cronograma!$B$4:$B$68,"<="&A18-9)*0.88+COUNTIF(Cronograma!$B$4:$B$68,"<="&A18-12)*1) | E18: =D18*Premissas!$B$11 | F18: =C18*Premissas!$B$13 | G18: =IF($A$4="B1",C18*Premissas!$B$18,IF($A$4="B2",C18*Premissas!$B$19,0)) | H18: =E18+F18+G18 | I18: =(E18+F18)*Premissas!$B$33+G18*Premissas!$B$34 | J18: =INDEX(Premissas!$B$37:$B$46,MIN(10,B18)) | K18: =IF($A$4="B1",C18*Premissas!$B$22,IF($A$4="B2",C18*Premissas!$B$23,0)) | L18: =IF($A$4="B2",C18*Premissas!$B$17,0) | M18: =H18-I18-J18-K18-L18 | N18: =COUNTIF(Cronograma!$B$4:$B$68,"="&A18+Premissas!$B$36)*IF($A$4="B1",Premissas!$B$20+Premissas!$B$21,IF($A$4="B2",Premissas!$B$21,0)) | O18: =COUNTIF(Cronograma!$B$4:$B$68,"="&A18+3)*Premissas!$B$14*(1-Premissas!$B$33) | P18: =M18-N18+O18 | Q18: =Q17+P18
A19: 13 | B19: =ROUNDUP(A19/12,0) | C19: =COUNTIF(Cronograma!$B$4:$B$68,"<="&A19) | D19: =Premissas!$B$6*(COUNTIFS(Cronograma!$B$4:$B$68,">="&A19-2,Cronograma!$B$4:$B$68,"<="&A19)*0.35+COUNTIFS(Cronograma!$B$4:$B$68,">="&A19-5,Cronograma!$B$4:$B$68,"<="&A19-3)*0.55+COUNTIFS(Cronograma!$B$4:$B$68,">="&A19-8,Cronograma!$B$4:$B$68,"<="&A19-6)*0.75+COUNTIFS(Cronograma!$B$4:$B$68,">="&A19-11,Cronograma!$B$4:$B$68,"<="&A19-9)*0.88+COUNTIF(Cronograma!$B$4:$B$68,"<="&A19-12)*1) | E19: =D19*Premissas!$B$11 | F19: =C19*Premissas!$B$13 | G19: =IF($A$4="B1",C19*Premissas!$B$18,IF($A$4="B2",C19*Premissas!$B$19,0)) | H19: =E19+F19+G19 | I19: =(E19+F19)*Premissas!$B$33+G19*Premissas!$B$34 | J19: =INDEX(Premissas!$B$37:$B$46,MIN(10,B19)) | K19: =IF($A$4="B1",C19*Premissas!$B$22,IF($A$4="B2",C19*Premissas!$B$23,0)) | L19: =IF($A$4="B2",C19*Premissas!$B$17,0) | M19: =H19-I19-J19-K19-L19 | N19: =COUNTIF(Cronograma!$B$4:$B$68,"="&A19+Premissas!$B$36)*IF($A$4="B1",Premissas!$B$20+Premissas!$B$21,IF($A$4="B2",Premissas!$B$21,0)) | O19: =COUNTIF(Cronograma!$B$4:$B$68,"="&A19+3)*Premissas!$B$14*(1-Premissas!$B$33) | P19: =M19-N19+O19 | Q19: =Q18+P19
... A126: 120 | B126: =ROUNDUP(A126/12,0) | C126: =COUNTIF(Cronograma!$B$4:$B$68,"<="&A126) | D126: =Premissas!$B$6*(COUNTIFS(Cronograma!$B$4:$B$68,">="&A126-2,Cronograma!$B$4:$B$68,"<="&A126)*0.35+COUNTIFS(Cronograma!$B$4:$B$68,">="&A126-5,Cronograma!$B$4:$B$68,"<="&A126-3)*0.55+COUNTIFS(Cronograma!$B$4:$B$68,">="&A126-8,Cronograma!$B$4:$B$68,"<="&A126-6)*0.75+COUNTIFS(Cronograma!$B$4:$B$68,">="&A126-11,Cronograma!$B$4:$B$68,"<="&A126-9)*0.88+COUNTIF(Cronograma!$B$4:$B$68,"<="&A126-12)*1) | E126: =D126*Premissas!$B$11 | F126: =C126*Premissas!$B$13 | G126: =IF($A$4="B1",C126*Premissas!$B$18,IF($A$4="B2",C126*Premissas!$B$19,0)) | H126: =E126+F126+G126 | I126: =(E126+F126)*Premissas!$B$33+G126*Premissas!$B$34 | J126: =INDEX(Premissas!$B$37:$B$46,MIN(10,B126)) | K126: =IF($A$4="B1",C126*Premissas!$B$22,IF($A$4="B2",C126*Premissas!$B$23,0)) | L126: =IF($A$4="B2",C126*Premissas!$B$17,0) | M126: =H126-I126-J126-K126-L126 | N126: =COUNTIF(Cronograma!$B$4:$B$68,"="&A126+Premissas!$B$36)*IF($A$4="B1",Premissas!$B$20+Premissas!$B$21,IF($A$4="B2",Premissas!$B$21,0)) | O126: =COUNTIF(Cronograma!$B$4:$B$68,"="&A126+3)*Premissas!$B$14*(1-Premissas!$B$33) | P126: =M126-N126+O126 | Q126: =Q125+P126
A129: RESULTADO DA FRANQUEADORA (sem valor residual)
A130: Unidades no ano 10 | D130: =C126
A131: Receita bruta no ano 10 | D131: =SUMIF($B$7:$B$126,10,$H$7:$H$126)
A132: EBITDA no ano 10 | D132: =SUMIF($B$7:$B$126,10,$M$7:$M$126)
A133: Capital total no imovel | D133: =SUM(N7:N126)
A134: Pico de caixa | D134: =MIN(Q7:Q126)
A135: Mes do pico | D135: =MATCH(MIN(Q7:Q126),Q7:Q126,0)
A136: Mes em que o caixa zera | D136: =IFERROR(MATCH(TRUE,INDEX(Q7:Q126>=0,0),0),"nao zera")
A137: TIR anual | D137: =IFERROR((1+IRR(P7:P126,0.02))^12-1,"negativa")
A138: VPL na TMA | D138: =NPV((1+Premissas!$B$35)^(1/12)-1,P7:P126)
A141: Nota: estas linhas NAO incluem valor residual (terreno valorizado nem multiplo do negocio de franquia). Ver BP-REDE.md secao 2.

Sheet Cronograma
A1: FASE 2 - mes de inauguracao de cada unidade franqueada
A3: Unidade | B3: Mes de inauguracao | C3: Ano
A4: 1 | B4: 13 | C4: =ROUNDUP(B4/12,0)
A5: 2 | B5: 19 | C5: =ROUNDUP(B5/12,0)
A6: 3 | B6: 25 | C6: =ROUNDUP(B6/12,0)
A7: 4 | B7: 27 | C7: =ROUNDUP(B7/12,0)
A8: 5 | B8: 29 | C8: =ROUNDUP(B8/12,0)
A9: 6 | B9: 32 | C9: =ROUNDUP(B9/12,0)
A10: 7 | B10: 34 | C10: =ROUNDUP(B10/12,0)
A11: 8 | B11: 37 | C11: =ROUNDUP(B11/12,0)
A12: 9 | B12: 39 | C12: =ROUNDUP(B12/12,0)
A13: 10 | B13: 41 | C13: =ROUNDUP(B13/12,0)
A14: 11 | B14: 44 | C14: =ROUNDUP(B14/12,0)
A15: 12 | B15: 46 | C15: =ROUNDUP(B15/12,0)
... A68: 65 | B68: 119 | C68: =ROUNDUP(B68/12,0)
