Workbook

Sheet Premissas
A1: FASE 1 - LOJA MODELO PIUMHI/MG | premissas
A3: As celulas em bege sao as unicas para editar. Tudo o mais e formula.
A5: DEMANDA
A6: Assinantes no estado maduro | B6: 500 | C6: Conservador 380 | Base 500 | Otimista 650
A7: Lavagens avulsas por dia | B7: 8
A8: Receita complementar/mes (box, aspirador) | B8: 2200
A9: Assinantes na abertura (fundadores) | B9: 80
A10: Velocidade da rampa (k) | B10: 0.33 | C10: maior = rampa mais rapida
A11: Mes de meia-rampa | B11: 8
A12: Automoveis em Piumhi (Senatran 2024) | B12: 13652 | C12: CONFIRMAR na planilha do Senatran
A14: PRECOS E MIX
A15: Essencial - preco/mes | B15: 59
A16: Essencial - lavagens/mes | B16: 4
A17: Essencial - participacao no mix | B17: 0.45
A18: Ilimitada - preco/mes | B18: 99
A19: Ilimitada - lavagens/mes por assinante | B19: 6 | C19: a premissa mais sensivel do modelo
A20: Ilimitada - participacao no mix | B20: 0.4
A21: Premium - preco/mes | B21: 139
A22: Premium - lavagens/mes por assinante | B22: 7
A23: Premium - participacao no mix | B23: 0.15
A24: Lavagem avulsa | B24: 35
A26: CUSTO VARIAVEL
A27: Agua por lavagem (litros) | B27: 85
A28: Tarifa de agua + esgoto (R$/m3) | B28: 14 | C28: ESTIMATIVA - minimo de 30 m3 por R$ 93,59 confirmado; falta o excedente e o esgoto
A29: Energia por lavagem (kWh) | B29: 1.6 | C29: calculo proprio; fornecedor declara 0,6-1,2
A30: Tarifa de energia (R$/kWh) | B30: 1.11 | C30: CONFIRMADO out/2026 - CEMIG baixa tensao
A31: Quimicos por lavagem | B31: 2.5
A32: Meios de pagamento (% da receita) | B32: 0.015
A33: CUSTO VARIAVEL POR LAVAGEM | B33: =B27/1000*B28+B29*B30+B31
A35: CUSTO FIXO MENSAL
A36: Aluguel da area | B36: 3000
A37: 1 atendente meio periodo + encargos | B37: 2600
A38: Manutencao preventiva e pecas de desgaste | B38: 1400
A39: Internet, telefonia, gateway, software | B39: 450
A40: Contador | B40: 700
A41: Seguro do equipamento + RC | B41: 400
A42: Energia de base (iluminacao, standby, aspirador) | B42: 600
A43: Limpeza, uniformes, materiais | B43: 350
A44: Marketing recorrente | B44: 1800
A45: IPTU, taxas, alvara (rateio mensal) | B45: 250
A46: Pro-labore do operador | B46: 3500 | C46: um negocio que so fecha com o dono de graca nao fechou
A47: TOTAL FIXO | B47: =SUM(B36:B46)
A49: CAPEX DE IMPLANTACAO
A50: Cambio de planejamento (R$/USD) | B50: 5.3 | C50: Focus fim-2026: 5,20
A51: Maquina JM-70 posta em Piumhi (USD 23.000) | B51: 121900
A52: Interface Modbus/API + kit de pecas 2 anos (USD 2.000) | B52: 10600
A53: Obra civil: portico, baia coberta, piso, patio 300 m2 | B53: 92000
A54: Caixa separadora agua/oleo + hidraulica + reservatorio | B54: 26000
A55: Entrada de energia, quadro, cabeamento, projeto e ART | B55: 24000
A56: Laudo NR-12 com ART | B56: 6000
A57: Totem de pagamento PIX/cartao + camera + CFTV + rede | B57: 26000
A58: 1 box de alta pressao + 2 aspiradores | B58: 18000
A59: Fachada, comunicacao visual, iluminacao | B59: 19000
A60: Software da unidade, integracao e implantacao | B60: 12000
A61: Projeto, licencas, alvaras, bombeiros, taxas | B61: 14000
A62: Subtotal | B62: =SUM(B51:B61)
A63: Contingencia (%) | B63: 0.08
A64: Cortes da versao enxuta | B64: 71060 | C64: boxes e aspiradores no mes 6, patio de 150 m2, fachada simples; zere para o capex cheio
A65: CAPEX TOTAL | B65: =B62*(1+B63)-B64
A66: do qual benfeitoria em imovel de terceiro | B66: =B53+B54+B55 | C66: obra civil + separadora + entrada de energia
A68: CAPITAL DE GIRO
A69: Caucao de 3 alugueis | B69: 9000
A70: Campanha de pre-venda e inauguracao | B70: 22000
A71: Estoque inicial de quimicos | B71: 6000
A72: Colchao de 3 meses de custo fixo | B72: 18000
A73: Cortes no giro (versao enxuta) | B73: 10000 | C73: zere junto com os cortes do capex
A74: TOTAL GIRO | B74: =SUM(B69:B72)-B73
A75: INVESTIMENTO TOTAL | B75: =B65+B74
A77: FINANCEIRO
A78: TMA (a.a.) | B78: 0.18 | C78: Selic em ago/2026: 14% a.a.
A79: Capex de manutencao (% da receita) | B79: 0.015
A80: Valor residual do capex no mes 60 | B80: 0.3
A82: CAPACIDADE
A83: Ciclo + manobra (min) | B83: 6.5
A84: Disponibilidade da maquina | B84: 0.9
A85: Janela diaria de pico (horas) | B85: 13
A86: Lavagens na janela de pico | B86: 0.75

Sheet Resumo
A1: FASE 1 - resumo
A3: Investimento total | B3: =Premissas!$B$75
A4: capex de implantacao | B4: =Premissas!$B$65
A5: capital de giro | B5: =Premissas!$B$74
A6: benfeitoria em imovel de terceiro | B6: =Premissas!$B$66 | C6: fica no terreno do locador se o contrato nao for renovado
A8: Receita madura/mes | B8: =Fluxo!G64
A9: Lavagens/dia no estado maduro | B9: =Fluxo!I64
A10: EBITDA maduro/mes | B10: =Fluxo!O64
A11: Margem EBITDA madura | B11: =Fluxo!P64
A13: TIR anual | B13: =IFERROR((1+IRR(Fluxo!$R$4:$R$64,0.02))^12-1,"nao converge") | C13: TIR mensal capitalizada para o ano
A14: VPL na TMA | B14: =NPV((1+Premissas!$B$78)^(1/12)-1,Fluxo!$R$5:$R$64)+Fluxo!$R$4
A15: Payback (mes em que o caixa zera) | B15: =IFERROR(MATCH(TRUE,INDEX(Fluxo!$S$5:$S$64>=0,0),0),"nao paga")
A16: ROI 5 anos (caixa gerado / investimento) | B16: =SUM(Fluxo!$R$5:$R$64)/Premissas!$B$75
A18: PONTO DE EQUILIBRIO
A19: Custo variavel relativo (maduro) | B19: =Fluxo!M64/Fluxo!G64
A20: Receita de equilibrio/mes | B20: =Premissas!$B$47/(1-Fluxo!K64-Fluxo!M64/Fluxo!G64)
A21: como % da receita madura | B21: =B20/Fluxo!G64
A22: assinantes equivalentes | B22: =B20/Fluxo!G64*Premissas!$B$6
A24: CAPACIDADE DA MAQUINA
A25: Teto pratico (lavagens/dia) | B25: =60/Premissas!$B$83*Premissas!$B$84*Premissas!$B$85/Premissas!$B$86
A26: Uso no estado maduro | B26: =Fluxo!I64/B25 | C26: acima de 85% a fila aparece no horario de pico
A28: A aba Fluxo comeca no mes 0, que carrega o investimento. IRR, NPV e payback incluem esse desembolso.

Sheet Capital
A1: ESTRUTURA DE CAPITAL | divida, pre-venda e divisao entre socios
A3: Celulas em bege sao de entrada. O resto e formula.
A5: DIVIDA
A6: Valor da divida | B6: 120000 | C6: cooperativa de credito local e a fonte mais provavel
A7: Juros (a.a.) | B7: 0.21
A8: Prazo (meses) | B8: 60
A9: Carencia (meses, so juros) | B9: 6 | C9: exija 6 no minimo: os meses 1 a 4 tem EBITDA negativo
A10: Juros mensais | B10: =(1+B7)^(1/12)-1
A11: Parcela apos a carencia | B11: =B6*B10/(1-(1+B10)^-B8)
A12: Juros durante a carencia | B12: =B6*B10
A14: PRE-VENDA ANUAL DOS FUNDADORES
A15: Numero de fundadores | B15: 80
A16: Mensalidade do fundador | B16: 79
A17: Meses pagos a vista | B17: 11 | C17: 12 meses pelo preco de 11
A18: Caixa no mes 0 | B18: =B15*B16*B17
A20: DIVISAO DO EQUITY
A21: Aporte do investidor A | B21: 75000
A22: Fatia do investidor A | B22: 0.24
A23: Aporte do investidor B | B23: 75000
A24: Fatia do investidor B | B24: 0.24
A26: Mes | B26: FCL do projeto | C26: Servico da divida | D26: Ajuste da pre-venda | E26: FCL do equity | F26: Caixa acumulado | G26: Investidor A | H26: Investidor B | I26: Antonio
A27: 0 | B27: =Fluxo!$R$4 | C27: =-Capital!$B$6 | D27: =-Capital!$B$18 | E27: =B27-C27-D27 | F27: =E27 | G27: =-Capital!$B$21 | H27: =-Capital!$B$23 | I27: =-(MIN(F27:F87)*-1-Capital!$B$21-Capital!$B$23)
A28: 1 | B28: =Fluxo!$R$5 | C28: =IF(A28<=Capital!$B$9,Capital!$B$12,IF(A28<=Capital!$B$9+Capital!$B$8,Capital!$B$11,0)) | D28: =IF(A28<=12,Capital!$B$15*87.0*(1-Fluxo!$K$5),0) | E28: =B28-C28-D28 | F28: =F27+E28 | G28: =E28*Capital!$B$22 | H28: =E28*Capital!$B$24 | I28: =E28*(1-Capital!$B$22-Capital!$B$24)
A29: 2 | B29: =Fluxo!$R$6 | C29: =IF(A29<=Capital!$B$9,Capital!$B$12,IF(A29<=Capital!$B$9+Capital!$B$8,Capital!$B$11,0)) | D29: =IF(A29<=12,Capital!$B$15*87.0*(1-Fluxo!$K$6),0) | E29: =B29-C29-D29 | F29: =F28+E29 | G29: =E29*Capital!$B$22 | H29: =E29*Capital!$B$24 | I29: =E29*(1-Capital!$B$22-Capital!$B$24)
A30: 3 | B30: =Fluxo!$R$7 | C30: =IF(A30<=Capital!$B$9,Capital!$B$12,IF(A30<=Capital!$B$9+Capital!$B$8,Capital!$B$11,0)) | D30: =IF(A30<=12,Capital!$B$15*87.0*(1-Fluxo!$K$7),0) | E30: =B30-C30-D30 | F30: =F29+E30 | G30: =E30*Capital!$B$22 | H30: =E30*Capital!$B$24 | I30: =E30*(1-Capital!$B$22-Capital!$B$24)
A31: 4 | B31: =Fluxo!$R$8 | C31: =IF(A31<=Capital!$B$9,Capital!$B$12,IF(A31<=Capital!$B$9+Capital!$B$8,Capital!$B$11,0)) | D31: =IF(A31<=12,Capital!$B$15*87.0*(1-Fluxo!$K$8),0) | E31: =B31-C31-D31 | F31: =F30+E31 | G31: =E31*Capital!$B$22 | H31: =E31*Capital!$B$24 | I31: =E31*(1-Capital!$B$22-Capital!$B$24)
A32: 5 | B32: =Fluxo!$R$9 | C32: =IF(A32<=Capital!$B$9,Capital!$B$12,IF(A32<=Capital!$B$9+Capital!$B$8,Capital!$B$11,0)) | D32: =IF(A32<=12,Capital!$B$15*87.0*(1-Fluxo!$K$9),0) | E32: =B32-C32-D32 | F32: =F31+E32 | G32: =E32*Capital!$B$22 | H32: =E32*Capital!$B$24 | I32: =E32*(1-Capital!$B$22-Capital!$B$24)
A33: 6 | B33: =Fluxo!$R$10 | C33: =IF(A33<=Capital!$B$9,Capital!$B$12,IF(A33<=Capital!$B$9+Capital!$B$8,Capital!$B$11,0)) | D33: =IF(A33<=12,Capital!$B$15*87.0*(1-Fluxo!$K$10),0) | E33: =B33-C33-D33 | F33: =F32+E33 | G33: =E33*Capital!$B$22 | H33: =E33*Capital!$B$24 | I33: =E33*(1-Capital!$B$22-Capital!$B$24)
A34: 7 | B34: =Fluxo!$R$11 | C34: =IF(A34<=Capital!$B$9,Capital!$B$12,IF(A34<=Capital!$B$9+Capital!$B$8,Capital!$B$11,0)) | D34: =IF(A34<=12,Capital!$B$15*87.0*(1-Fluxo!$K$11),0) | E34: =B34-C34-D34 | F34: =F33+E34 | G34: =E34*Capital!$B$22 | H34: =E34*Capital!$B$24 | I34: =E34*(1-Capital!$B$22-Capital!$B$24)
A35: 8 | B35: =Fluxo!$R$12 | C35: =IF(A35<=Capital!$B$9,Capital!$B$12,IF(A35<=Capital!$B$9+Capital!$B$8,Capital!$B$11,0)) | D35: =IF(A35<=12,Capital!$B$15*87.0*(1-Fluxo!$K$12),0) | E35: =B35-C35-D35 | F35: =F34+E35 | G35: =E35*Capital!$B$22 | H35: =E35*Capital!$B$24 | I35: =E35*(1-Capital!$B$22-Capital!$B$24)
A36: 9 | B36: =Fluxo!$R$13 | C36: =IF(A36<=Capital!$B$9,Capital!$B$12,IF(A36<=Capital!$B$9+Capital!$B$8,Capital!$B$11,0)) | D36: =IF(A36<=12,Capital!$B$15*87.0*(1-Fluxo!$K$13),0) | E36: =B36-C36-D36 | F36: =F35+E36 | G36: =E36*Capital!$B$22 | H36: =E36*Capital!$B$24 | I36: =E36*(1-Capital!$B$22-Capital!$B$24)
A37: 10 | B37: =Fluxo!$R$14 | C37: =IF(A37<=Capital!$B$9,Capital!$B$12,IF(A37<=Capital!$B$9+Capital!$B$8,Capital!$B$11,0)) | D37: =IF(A37<=12,Capital!$B$15*87.0*(1-Fluxo!$K$14),0) | E37: =B37-C37-D37 | F37: =F36+E37 | G37: =E37*Capital!$B$22 | H37: =E37*Capital!$B$24 | I37: =E37*(1-Capital!$B$22-Capital!$B$24)
A38: 11 | B38: =Fluxo!$R$15 | C38: =IF(A38<=Capital!$B$9,Capital!$B$12,IF(A38<=Capital!$B$9+Capital!$B$8,Capital!$B$11,0)) | D38: =IF(A38<=12,Capital!$B$15*87.0*(1-Fluxo!$K$15),0) | E38: =B38-C38-D38 | F38: =F37+E38 | G38: =E38*Capital!$B$22 | H38: =E38*Capital!$B$24 | I38: =E38*(1-Capital!$B$22-Capital!$B$24)
A39: 12 | B39: =Fluxo!$R$16 | C39: =IF(A39<=Capital!$B$9,Capital!$B$12,IF(A39<=Capital!$B$9+Capital!$B$8,Capital!$B$11,0)) | D39: =IF(A39<=12,Capital!$B$15*87.0*(1-Fluxo!$K$16),0) | E39: =B39-C39-D39 | F39: =F38+E39 | G39: =E39*Capital!$B$22 | H39: =E39*Capital!$B$24 | I39: =E39*(1-Capital!$B$22-Capital!$B$24)
A40: 13 | B40: =Fluxo!$R$17 | C40: =IF(A40<=Capital!$B$9,Capital!$B$12,IF(A40<=Capital!$B$9+Capital!$B$8,Capital!$B$11,0)) | D40: =IF(A40<=12,Capital!$B$15*87.0*(1-Fluxo!$K$17),0) | E40: =B40-C40-D40 | F40: =F39+E40 | G40: =E40*Capital!$B$22 | H40: =E40*Capital!$B$24 | I40: =E40*(1-Capital!$B$22-Capital!$B$24)
A41: 14 | B41: =Fluxo!$R$18 | C41: =IF(A41<=Capital!$B$9,Capital!$B$12,IF(A41<=Capital!$B$9+Capital!$B$8,Capital!$B$11,0)) | D41: =IF(A41<=12,Capital!$B$15*87.0*(1-Fluxo!$K$18),0) | E41: =B41-C41-D41 | F41: =F40+E41 | G41: =E41*Capital!$B$22 | H41: =E41*Capital!$B$24 | I41: =E41*(1-Capital!$B$22-Capital!$B$24)
A42: 15 | B42: =Fluxo!$R$19 | C42: =IF(A42<=Capital!$B$9,Capital!$B$12,IF(A42<=Capital!$B$9+Capital!$B$8,Capital!$B$11,0)) | D42: =IF(A42<=12,Capital!$B$15*87.0*(1-Fluxo!$K$19),0) | E42: =B42-C42-D42 | F42: =F41+E42 | G42: =E42*Capital!$B$22 | H42: =E42*Capital!$B$24 | I42: =E42*(1-Capital!$B$22-Capital!$B$24)
A43: 16 | B43: =Fluxo!$R$20 | C43: =IF(A43<=Capital!$B$9,Capital!$B$12,IF(A43<=Capital!$B$9+Capital!$B$8,Capital!$B$11,0)) | D43: =IF(A43<=12,Capital!$B$15*87.0*(1-Fluxo!$K$20),0) | E43: =B43-C43-D43 | F43: =F42+E43 | G43: =E43*Capital!$B$22 | H43: =E43*Capital!$B$24 | I43: =E43*(1-Capital!$B$22-Capital!$B$24)
A44: 17 | B44: =Fluxo!$R$21 | C44: =IF(A44<=Capital!$B$9,Capital!$B$12,IF(A44<=Capital!$B$9+Capital!$B$8,Capital!$B$11,0)) | D44: =IF(A44<=12,Capital!$B$15*87.0*(1-Fluxo!$K$21),0) | E44: =B44-C44-D44 | F44: =F43+E44 | G44: =E44*Capital!$B$22 | H44: =E44*Capital!$B$24 | I44: =E44*(1-Capital!$B$22-Capital!$B$24)
A45: 18 | B45: =Fluxo!$R$22 | C45: =IF(A45<=Capital!$B$9,Capital!$B$12,IF(A45<=Capital!$B$9+Capital!$B$8,Capital!$B$11,0)) | D45: =IF(A45<=12,Capital!$B$15*87.0*(1-Fluxo!$K$22),0) | E45: =B45-C45-D45 | F45: =F44+E45 | G45: =E45*Capital!$B$22 | H45: =E45*Capital!$B$24 | I45: =E45*(1-Capital!$B$22-Capital!$B$24)
A46: 19 | B46: =Fluxo!$R$23 | C46: =IF(A46<=Capital!$B$9,Capital!$B$12,IF(A46<=Capital!$B$9+Capital!$B$8,Capital!$B$11,0)) | D46: =IF(A46<=12,Capital!$B$15*87.0*(1-Fluxo!$K$23),0) | E46: =B46-C46-D46 | F46: =F45+E46 | G46: =E46*Capital!$B$22 | H46: =E46*Capital!$B$24 | I46: =E46*(1-Capital!$B$22-Capital!$B$24)
A47: 20 | B47: =Fluxo!$R$24 | C47: =IF(A47<=Capital!$B$9,Capital!$B$12,IF(A47<=Capital!$B$9+Capital!$B$8,Capital!$B$11,0)) | D47: =IF(A47<=12,Capital!$B$15*87.0*(1-Fluxo!$K$24),0) | E47: =B47-C47-D47 | F47: =F46+E47 | G47: =E47*Capital!$B$22 | H47: =E47*Capital!$B$24 | I47: =E47*(1-Capital!$B$22-Capital!$B$24)
A48: 21 | B48: =Fluxo!$R$25 | C48: =IF(A48<=Capital!$B$9,Capital!$B$12,IF(A48<=Capital!$B$9+Capital!$B$8,Capital!$B$11,0)) | D48: =IF(A48<=12,Capital!$B$15*87.0*(1-Fluxo!$K$25),0) | E48: =B48-C48-D48 | F48: =F47+E48 | G48: =E48*Capital!$B$22 | H48: =E48*Capital!$B$24 | I48: =E48*(1-Capital!$B$22-Capital!$B$24)
A49: 22 | B49: =Fluxo!$R$26 | C49: =IF(A49<=Capital!$B$9,Capital!$B$12,IF(A49<=Capital!$B$9+Capital!$B$8,Capital!$B$11,0)) | D49: =IF(A49<=12,Capital!$B$15*87.0*(1-Fluxo!$K$26),0) | E49: =B49-C49-D49 | F49: =F48+E49 | G49: =E49*Capital!$B$22 | H49: =E49*Capital!$B$24 | I49: =E49*(1-Capital!$B$22-Capital!$B$24)
A50: 23 | B50: =Fluxo!$R$27 | C50: =IF(A50<=Capital!$B$9,Capital!$B$12,IF(A50<=Capital!$B$9+Capital!$B$8,Capital!$B$11,0)) | D50: =IF(A50<=12,Capital!$B$15*87.0*(1-Fluxo!$K$27),0) | E50: =B50-C50-D50 | F50: =F49+E50 | G50: =E50*Capital!$B$22 | H50: =E50*Capital!$B$24 | I50: =E50*(1-Capital!$B$22-Capital!$B$24)
A51: 24 | B51: =Fluxo!$R$28 | C51: =IF(A51<=Capital!$B$9,Capital!$B$12,IF(A51<=Capital!$B$9+Capital!$B$8,Capital!$B$11,0)) | D51: =IF(A51<=12,Capital!$B$15*87.0*(1-Fluxo!$K$28),0) | E51: =B51-C51-D51 | F51: =F50+E51 | G51: =E51*Capital!$B$22 | H51: =E51*Capital!$B$24 | I51: =E51*(1-Capital!$B$22-Capital!$B$24)
A52: 25 | B52: =Fluxo!$R$29 | C52: =IF(A52<=Capital!$B$9,Capital!$B$12,IF(A52<=Capital!$B$9+Capital!$B$8,Capital!$B$11,0)) | D52: =IF(A52<=12,Capital!$B$15*87.0*(1-Fluxo!$K$29),0) | E52: =B52-C52-D52 | F52: =F51+E52 | G52: =E52*Capital!$B$22 | H52: =E52*Capital!$B$24 | I52: =E52*(1-Capital!$B$22-Capital!$B$24)
A53: 26 | B53: =Fluxo!$R$30 | C53: =IF(A53<=Capital!$B$9,Capital!$B$12,IF(A53<=Capital!$B$9+Capital!$B$8,Capital!$B$11,0)) | D53: =IF(A53<=12,Capital!$B$15*87.0*(1-Fluxo!$K$30),0) | E53: =B53-C53-D53 | F53: =F52+E53 | G53: =E53*Capital!$B$22 | H53: =E53*Capital!$B$24 | I53: =E53*(1-Capital!$B$22-Capital!$B$24)
A54: 27 | B54: =Fluxo!$R$31 | C54: =IF(A54<=Capital!$B$9,Capital!$B$12,IF(A54<=Capital!$B$9+Capital!$B$8,Capital!$B$11,0)) | D54: =IF(A54<=12,Capital!$B$15*87.0*(1-Fluxo!$K$31),0) | E54: =B54-C54-D54 | F54: =F53+E54 | G54: =E54*Capital!$B$22 | H54: =E54*Capital!$B$24 | I54: =E54*(1-Capital!$B$22-Capital!$B$24)
A55: 28 | B55: =Fluxo!$R$32 | C55: =IF(A55<=Capital!$B$9,Capital!$B$12,IF(A55<=Capital!$B$9+Capital!$B$8,Capital!$B$11,0)) | D55: =IF(A55<=12,Capital!$B$15*87.0*(1-Fluxo!$K$32),0) | E55: =B55-C55-D55 | F55: =F54+E55 | G55: =E55*Capital!$B$22 | H55: =E55*Capital!$B$24 | I55: =E55*(1-Capital!$B$22-Capital!$B$24)
A56: 29 | B56: =Fluxo!$R$33 | C56: =IF(A56<=Capital!$B$9,Capital!$B$12,IF(A56<=Capital!$B$9+Capital!$B$8,Capital!$B$11,0)) | D56: =IF(A56<=12,Capital!$B$15*87.0*(1-Fluxo!$K$33),0) | E56: =B56-C56-D56 | F56: =F55+E56 | G56: =E56*Capital!$B$22 | H56: =E56*Capital!$B$24 | I56: =E56*(1-Capital!$B$22-Capital!$B$24)
A57: 30 | B57: =Fluxo!$R$34 | C57: =IF(A57<=Capital!$B$9,Capital!$B$12,IF(A57<=Capital!$B$9+Capital!$B$8,Capital!$B$11,0)) | D57: =IF(A57<=12,Capital!$B$15*87.0*(1-Fluxo!$K$34),0) | E57: =B57-C57-D57 | F57: =F56+E57 | G57: =E57*Capital!$B$22 | H57: =E57*Capital!$B$24 | I57: =E57*(1-Capital!$B$22-Capital!$B$24)
A58: 31 | B58: =Fluxo!$R$35 | C58: =IF(A58<=Capital!$B$9,Capital!$B$12,IF(A58<=Capital!$B$9+Capital!$B$8,Capital!$B$11,0)) | D58: =IF(A58<=12,Capital!$B$15*87.0*(1-Fluxo!$K$35),0) | E58: =B58-C58-D58 | F58: =F57+E58 | G58: =E58*Capital!$B$22 | H58: =E58*Capital!$B$24 | I58: =E58*(1-Capital!$B$22-Capital!$B$24)
A59: 32 | B59: =Fluxo!$R$36 | C59: =IF(A59<=Capital!$B$9,Capital!$B$12,IF(A59<=Capital!$B$9+Capital!$B$8,Capital!$B$11,0)) | D59: =IF(A59<=12,Capital!$B$15*87.0*(1-Fluxo!$K$36),0) | E59: =B59-C59-D59 | F59: =F58+E59 | G59: =E59*Capital!$B$22 | H59: =E59*Capital!$B$24 | I59: =E59*(1-Capital!$B$22-Capital!$B$24)
A60: 33 | B60: =Fluxo!$R$37 | C60: =IF(A60<=Capital!$B$9,Capital!$B$12,IF(A60<=Capital!$B$9+Capital!$B$8,Capital!$B$11,0)) | D60: =IF(A60<=12,Capital!$B$15*87.0*(1-Fluxo!$K$37),0) | E60: =B60-C60-D60 | F60: =F59+E60 | G60: =E60*Capital!$B$22 | H60: =E60*Capital!$B$24 | I60: =E60*(1-Capital!$B$22-Capital!$B$24)
A61: 34 | B61: =Fluxo!$R$38 | C61: =IF(A61<=Capital!$B$9,Capital!$B$12,IF(A61<=Capital!$B$9+Capital!$B$8,Capital!$B$11,0)) | D61: =IF(A61<=12,Capital!$B$15*87.0*(1-Fluxo!$K$38),0) | E61: =B61-C61-D61 | F61: =F60+E61 | G61: =E61*Capital!$B$22 | H61: =E61*Capital!$B$24 | I61: =E61*(1-Capital!$B$22-Capital!$B$24)
A62: 35 | B62: =Fluxo!$R$39 | C62: =IF(A62<=Capital!$B$9,Capital!$B$12,IF(A62<=Capital!$B$9+Capital!$B$8,Capital!$B$11,0)) | D62: =IF(A62<=12,Capital!$B$15*87.0*(1-Fluxo!$K$39),0) | E62: =B62-C62-D62 | F62: =F61+E62 | G62: =E62*Capital!$B$22 | H62: =E62*Capital!$B$24 | I62: =E62*(1-Capital!$B$22-Capital!$B$24)
A63: 36 | B63: =Fluxo!$R$40 | C63: =IF(A63<=Capital!$B$9,Capital!$B$12,IF(A63<=Capital!$B$9+Capital!$B$8,Capital!$B$11,0)) | D63: =IF(A63<=12,Capital!$B$15*87.0*(1-Fluxo!$K$40),0) | E63: =B63-C63-D63 | F63: =F62+E63 | G63: =E63*Capital!$B$22 | H63: =E63*Capital!$B$24 | I63: =E63*(1-Capital!$B$22-Capital!$B$24)
A64: 37 | B64: =Fluxo!$R$41 | C64: =IF(A64<=Capital!$B$9,Capital!$B$12,IF(A64<=Capital!$B$9+Capital!$B$8,Capital!$B$11,0)) | D64: =IF(A64<=12,Capital!$B$15*87.0*(1-Fluxo!$K$41),0) | E64: =B64-C64-D64 | F64: =F63+E64 | G64: =E64*Capital!$B$22 | H64: =E64*Capital!$B$24 | I64: =E64*(1-Capital!$B$22-Capital!$B$24)
A65: 38 | B65: =Fluxo!$R$42 | C65: =IF(A65<=Capital!$B$9,Capital!$B$12,IF(A65<=Capital!$B$9+Capital!$B$8,Capital!$B$11,0)) | D65: =IF(A65<=12,Capital!$B$15*87.0*(1-Fluxo!$K$42),0) | E65: =B65-C65-D65 | F65: =F64+E65 | G65: =E65*Capital!$B$22 | H65: =E65*Capital!$B$24 | I65: =E65*(1-Capital!$B$22-Capital!$B$24)
A66: 39 | B66: =Fluxo!$R$43 | C66: =IF(A66<=Capital!$B$9,Capital!$B$12,IF(A66<=Capital!$B$9+Capital!$B$8,Capital!$B$11,0)) | D66: =IF(A66<=12,Capital!$B$15*87.0*(1-Fluxo!$K$43),0) | E66: =B66-C66-D66 | F66: =F65+E66 | G66: =E66*Capital!$B$22 | H66: =E66*Capital!$B$24 | I66: =E66*(1-Capital!$B$22-Capital!$B$24)
A67: 40 | B67: =Fluxo!$R$44 | C67: =IF(A67<=Capital!$B$9,Capital!$B$12,IF(A67<=Capital!$B$9+Capital!$B$8,Capital!$B$11,0)) | D67: =IF(A67<=12,Capital!$B$15*87.0*(1-Fluxo!$K$44),0) | E67: =B67-C67-D67 | F67: =F66+E67 | G67: =E67*Capital!$B$22 | H67: =E67*Capital!$B$24 | I67: =E67*(1-Capital!$B$22-Capital!$B$24)
A68: 41 | B68: =Fluxo!$R$45 | C68: =IF(A68<=Capital!$B$9,Capital!$B$12,IF(A68<=Capital!$B$9+Capital!$B$8,Capital!$B$11,0)) | D68: =IF(A68<=12,Capital!$B$15*87.0*(1-Fluxo!$K$45),0) | E68: =B68-C68-D68 | F68: =F67+E68 | G68: =E68*Capital!$B$22 | H68: =E68*Capital!$B$24 | I68: =E68*(1-Capital!$B$22-Capital!$B$24)
A69: 42 | B69: =Fluxo!$R$46 | C69: =IF(A69<=Capital!$B$9,Capital!$B$12,IF(A69<=Capital!$B$9+Capital!$B$8,Capital!$B$11,0)) | D69: =IF(A69<=12,Capital!$B$15*87.0*(1-Fluxo!$K$46),0) | E69: =B69-C69-D69 | F69: =F68+E69 | G69: =E69*Capital!$B$22 | H69: =E69*Capital!$B$24 | I69: =E69*(1-Capital!$B$22-Capital!$B$24)
A70: 43 | B70: =Fluxo!$R$47 | C70: =IF(A70<=Capital!$B$9,Capital!$B$12,IF(A70<=Capital!$B$9+Capital!$B$8,Capital!$B$11,0)) | D70: =IF(A70<=12,Capital!$B$15*87.0*(1-Fluxo!$K$47),0) | E70: =B70-C70-D70 | F70: =F69+E70 | G70: =E70*Capital!$B$22 | H70: =E70*Capital!$B$24 | I70: =E70*(1-Capital!$B$22-Capital!$B$24)
A71: 44 | B71: =Fluxo!$R$48 | C71: =IF(A71<=Capital!$B$9,Capital!$B$12,IF(A71<=Capital!$B$9+Capital!$B$8,Capital!$B$11,0)) | D71: =IF(A71<=12,Capital!$B$15*87.0*(1-Fluxo!$K$48),0) | E71: =B71-C71-D71 | F71: =F70+E71 | G71: =E71*Capital!$B$22 | H71: =E71*Capital!$B$24 | I71: =E71*(1-Capital!$B$22-Capital!$B$24)
A72: 45 | B72: =Fluxo!$R$49 | C72: =IF(A72<=Capital!$B$9,Capital!$B$12,IF(A72<=Capital!$B$9+Capital!$B$8,Capital!$B$11,0)) | D72: =IF(A72<=12,Capital!$B$15*87.0*(1-Fluxo!$K$49),0) | E72: =B72-C72-D72 | F72: =F71+E72 | G72: =E72*Capital!$B$22 | H72: =E72*Capital!$B$24 | I72: =E72*(1-Capital!$B$22-Capital!$B$24)
A73: 46 | B73: =Fluxo!$R$50 | C73: =IF(A73<=Capital!$B$9,Capital!$B$12,IF(A73<=Capital!$B$9+Capital!$B$8,Capital!$B$11,0)) | D73: =IF(A73<=12,Capital!$B$15*87.0*(1-Fluxo!$K$50),0) | E73: =B73-C73-D73 | F73: =F72+E73 | G73: =E73*Capital!$B$22 | H73: =E73*Capital!$B$24 | I73: =E73*(1-Capital!$B$22-Capital!$B$24)
A74: 47 | B74: =Fluxo!$R$51 | C74: =IF(A74<=Capital!$B$9,Capital!$B$12,IF(A74<=Capital!$B$9+Capital!$B$8,Capital!$B$11,0)) | D74: =IF(A74<=12,Capital!$B$15*87.0*(1-Fluxo!$K$51),0) | E74: =B74-C74-D74 | F74: =F73+E74 | G74: =E74*Capital!$B$22 | H74: =E74*Capital!$B$24 | I74: =E74*(1-Capital!$B$22-Capital!$B$24)
A75: 48 | B75: =Fluxo!$R$52 | C75: =IF(A75<=Capital!$B$9,Capital!$B$12,IF(A75<=Capital!$B$9+Capital!$B$8,Capital!$B$11,0)) | D75: =IF(A75<=12,Capital!$B$15*87.0*(1-Fluxo!$K$52),0) | E75: =B75-C75-D75 | F75: =F74+E75 | G75: =E75*Capital!$B$22 | H75: =E75*Capital!$B$24 | I75: =E75*(1-Capital!$B$22-Capital!$B$24)
A76: 49 | B76: =Fluxo!$R$53 | C76: =IF(A76<=Capital!$B$9,Capital!$B$12,IF(A76<=Capital!$B$9+Capital!$B$8,Capital!$B$11,0)) | D76: =IF(A76<=12,Capital!$B$15*87.0*(1-Fluxo!$K$53),0) | E76: =B76-C76-D76 | F76: =F75+E76 | G76: =E76*Capital!$B$22 | H76: =E76*Capital!$B$24 | I76: =E76*(1-Capital!$B$22-Capital!$B$24)
A77: 50 | B77: =Fluxo!$R$54 | C77: =IF(A77<=Capital!$B$9,Capital!$B$12,IF(A77<=Capital!$B$9+Capital!$B$8,Capital!$B$11,0)) | D77: =IF(A77<=12,Capital!$B$15*87.0*(1-Fluxo!$K$54),0) | E77: =B77-C77-D77 | F77: =F76+E77 | G77: =E77*Capital!$B$22 | H77: =E77*Capital!$B$24 | I77: =E77*(1-Capital!$B$22-Capital!$B$24)
A78: 51 | B78: =Fluxo!$R$55 | C78: =IF(A78<=Capital!$B$9,Capital!$B$12,IF(A78<=Capital!$B$9+Capital!$B$8,Capital!$B$11,0)) | D78: =IF(A78<=12,Capital!$B$15*87.0*(1-Fluxo!$K$55),0) | E78: =B78-C78-D78 | F78: =F77+E78 | G78: =E78*Capital!$B$22 | H78: =E78*Capital!$B$24 | I78: =E78*(1-Capital!$B$22-Capital!$B$24)
A79: 52 | B79: =Fluxo!$R$56 | C79: =IF(A79<=Capital!$B$9,Capital!$B$12,IF(A79<=Capital!$B$9+Capital!$B$8,Capital!$B$11,0)) | D79: =IF(A79<=12,Capital!$B$15*87.0*(1-Fluxo!$K$56),0) | E79: =B79-C79-D79 | F79: =F78+E79 | G79: =E79*Capital!$B$22 | H79: =E79*Capital!$B$24 | I79: =E79*(1-Capital!$B$22-Capital!$B$24)
A80: 53 | B80: =Fluxo!$R$57 | C80: =IF(A80<=Capital!$B$9,Capital!$B$12,IF(A80<=Capital!$B$9+Capital!$B$8,Capital!$B$11,0)) | D80: =IF(A80<=12,Capital!$B$15*87.0*(1-Fluxo!$K$57),0) | E80: =B80-C80-D80 | F80: =F79+E80 | G80: =E80*Capital!$B$22 | H80: =E80*Capital!$B$24 | I80: =E80*(1-Capital!$B$22-Capital!$B$24)
A81: 54 | B81: =Fluxo!$R$58 | C81: =IF(A81<=Capital!$B$9,Capital!$B$12,IF(A81<=Capital!$B$9+Capital!$B$8,Capital!$B$11,0)) | D81: =IF(A81<=12,Capital!$B$15*87.0*(1-Fluxo!$K$58),0) | E81: =B81-C81-D81 | F81: =F80+E81 | G81: =E81*Capital!$B$22 | H81: =E81*Capital!$B$24 | I81: =E81*(1-Capital!$B$22-Capital!$B$24)
A82: 55 | B82: =Fluxo!$R$59 | C82: =IF(A82<=Capital!$B$9,Capital!$B$12,IF(A82<=Capital!$B$9+Capital!$B$8,Capital!$B$11,0)) | D82: =IF(A82<=12,Capital!$B$15*87.0*(1-Fluxo!$K$59),0) | E82: =B82-C82-D82 | F82: =F81+E82 | G82: =E82*Capital!$B$22 | H82: =E82*Capital!$B$24 | I82: =E82*(1-Capital!$B$22-Capital!$B$24)
A83: 56 | B83: =Fluxo!$R$60 | C83: =IF(A83<=Capital!$B$9,Capital!$B$12,IF(A83<=Capital!$B$9+Capital!$B$8,Capital!$B$11,0)) | D83: =IF(A83<=12,Capital!$B$15*87.0*(1-Fluxo!$K$60),0) | E83: =B83-C83-D83 | F83: =F82+E83 | G83: =E83*Capital!$B$22 | H83: =E83*Capital!$B$24 | I83: =E83*(1-Capital!$B$22-Capital!$B$24)
A84: 57 | B84: =Fluxo!$R$61 | C84: =IF(A84<=Capital!$B$9,Capital!$B$12,IF(A84<=Capital!$B$9+Capital!$B$8,Capital!$B$11,0)) | D84: =IF(A84<=12,Capital!$B$15*87.0*(1-Fluxo!$K$61),0) | E84: =B84-C84-D84 | F84: =F83+E84 | G84: =E84*Capital!$B$22 | H84: =E84*Capital!$B$24 | I84: =E84*(1-Capital!$B$22-Capital!$B$24)
A85: 58 | B85: =Fluxo!$R$62 | C85: =IF(A85<=Capital!$B$9,Capital!$B$12,IF(A85<=Capital!$B$9+Capital!$B$8,Capital!$B$11,0)) | D85: =IF(A85<=12,Capital!$B$15*87.0*(1-Fluxo!$K$62),0) | E85: =B85-C85-D85 | F85: =F84+E85 | G85: =E85*Capital!$B$22 | H85: =E85*Capital!$B$24 | I85: =E85*(1-Capital!$B$22-Capital!$B$24)
A86: 59 | B86: =Fluxo!$R$63 | C86: =IF(A86<=Capital!$B$9,Capital!$B$12,IF(A86<=Capital!$B$9+Capital!$B$8,Capital!$B$11,0)) | D86: =IF(A86<=12,Capital!$B$15*87.0*(1-Fluxo!$K$63),0) | E86: =B86-C86-D86 | F86: =F85+E86 | G86: =E86*Capital!$B$22 | H86: =E86*Capital!$B$24 | I86: =E86*(1-Capital!$B$22-Capital!$B$24)
A87: 60 | B87: =Fluxo!$R$64 | C87: =IF(A87<=Capital!$B$9,Capital!$B$12,IF(A87<=Capital!$B$9+Capital!$B$8,Capital!$B$11,0))+Capital!$B$11*(1-(1+Capital!$B$10)^-MAX(0,Capital!$B$8-(60-Capital!$B$9)))/Capital!$B$10 | D87: =IF(A87<=12,Capital!$B$15*87.0*(1-Fluxo!$K$64),0) | E87: =B87-C87-D87 | F87: =F86+E87 | G87: =E87*Capital!$B$22 | H87: =E87*Capital!$B$24 | I87: =E87*(1-Capital!$B$22-Capital!$B$24)
A90: RESULTADO
A91: CAPITAL A RESERVAR (pico de caixa) | B91: =-MIN(F27:F87) | C91: e isto, nao a 1a tranche, que precisa estar comprometido
A92: 1a tranche, na assinatura | B92: =-E27
A93: a chamar durante a rampa | B93: =-MIN(F27:F87)+E27
A94: Mes do pico | B94: =MATCH(MIN(F27:F87),F27:F87,0)-1
A95: TIR do equity (a.a.) | B95: =IFERROR((1+IRR(E27:E87,0.02))^12-1,"n/d")
A96: VPL do equity na TMA | B96: =NPV((1+Premissas!$B$78)^(1/12)-1,E28:E87)+E27
A97: TIR do investidor A | B97: =IFERROR((1+IRR(G27:G87,0.02))^12-1,"n/d") | C97: o que ele compara com o CDI
A98: TIR do investidor B | B98: =IFERROR((1+IRR(H27:H87,0.02))^12-1,"n/d")
A99: TIR do Antonio | B99: =IFERROR((1+IRR(I27:I87,0.02))^12-1,"n/d") | C99: mais o pro-labore e 100% da franqueadora
A100: Aporte do Antonio | B100: =-I27
A101: Fatia do Antonio | B101: =1-Capital!$B$22-Capital!$B$24 | C101: FIQUE ACIMA DE 50%: e a unidade padrao da rede
A104: O aporte do Antonio e o residual: capital a reservar menos os aportes dos investidores.
A105: As colunas dos socios lancam o compromisso inteiro no mes 0. Na pratica ele e chamado em tranches,
A106: o que melhora a TIR deles - logo as TIRs aqui sao conservadoras.
A107: A pre-venda e antecipacao de receita: entra no mes 0 e sai da receita dos 12 meses seguintes.

Sheet Fluxo
A1: FASE 1 - fluxo de caixa mensal, 60 meses
A3: Mes | B3: Assinantes | C3: % da frota | D3: Receita assin. | E3: Receita avulsa | F3: Complementar | G3: Receita total | H3: Lavagens/mes | I3: Lavagens/dia | J3: RBT12 | K3: Aliq. Simples | L3: Imposto | M3: Custo variavel | N3: Custo fixo | O3: EBITDA | P3: Margem | Q3: Capex manut. | R3: Fluxo livre | S3: Caixa acumulado
A4: 0 | R4: =-Premissas!$B$75 | S4: =R4
A5: 1 | B5: =MIN(Premissas!$B$6,MAX(Premissas!$B$9,Premissas!$B$6/(1+EXP(-Premissas!$B$10*(A5-Premissas!$B$11))))) | C5: =B5/Premissas!$B$12 | D5: =B5*(Premissas!$B$17*Premissas!$B$15+Premissas!$B$20*Premissas!$B$18+Premissas!$B$23*Premissas!$B$21) | E5: =Premissas!$B$7*30*Premissas!$B$24*MIN(1,0.45+0.55*A5/12) | F5: =Premissas!$B$8*MIN(1,0.45+0.55*A5/12) | G5: =D5+E5+F5 | H5: =B5*(Premissas!$B$17*Premissas!$B$16+Premissas!$B$20*Premissas!$B$19+Premissas!$B$23*Premissas!$B$22)+Premissas!$B$7*30*MIN(1,0.45+0.55*A5/12) | I5: =H5/30 | J5: =SUM(G5:G5)*12/1 | K5: =IF((J5)<=0,0.06,IF((J5)<=180000,0.06,IF((J5)<=360000,((J5)*0.112-9360)/(J5),IF((J5)<=720000,((J5)*0.135-17640)/(J5),IF((J5)<=1800000,((J5)*0.16-35640)/(J5),0.165))))) | L5: =G5*K5 | M5: =H5*Premissas!$B$33+G5*Premissas!$B$32 | N5: =Premissas!$B$47 | O5: =G5-L5-M5-N5 | P5: =IF(G5=0,0,O5/G5) | Q5: =G5*Premissas!$B$79 | R5: =O5-Q5 | S5: =S4+R5
A6: 2 | B6: =MIN(Premissas!$B$6,MAX(Premissas!$B$9,Premissas!$B$6/(1+EXP(-Premissas!$B$10*(A6-Premissas!$B$11))))) | C6: =B6/Premissas!$B$12 | D6: =B6*(Premissas!$B$17*Premissas!$B$15+Premissas!$B$20*Premissas!$B$18+Premissas!$B$23*Premissas!$B$21) | E6: =Premissas!$B$7*30*Premissas!$B$24*MIN(1,0.45+0.55*A6/12) | F6: =Premissas!$B$8*MIN(1,0.45+0.55*A6/12) | G6: =D6+E6+F6 | H6: =B6*(Premissas!$B$17*Premissas!$B$16+Premissas!$B$20*Premissas!$B$19+Premissas!$B$23*Premissas!$B$22)+Premissas!$B$7*30*MIN(1,0.45+0.55*A6/12) | I6: =H6/30 | J6: =SUM(G5:G6)*12/2 | K6: =IF((J6)<=0,0.06,IF((J6)<=180000,0.06,IF((J6)<=360000,((J6)*0.112-9360)/(J6),IF((J6)<=720000,((J6)*0.135-17640)/(J6),IF((J6)<=1800000,((J6)*0.16-35640)/(J6),0.165))))) | L6: =G6*K6 | M6: =H6*Premissas!$B$33+G6*Premissas!$B$32 | N6: =Premissas!$B$47 | O6: =G6-L6-M6-N6 | P6: =IF(G6=0,0,O6/G6) | Q6: =G6*Premissas!$B$79 | R6: =O6-Q6 | S6: =S5+R6
A7: 3 | B7: =MIN(Premissas!$B$6,MAX(Premissas!$B$9,Premissas!$B$6/(1+EXP(-Premissas!$B$10*(A7-Premissas!$B$11))))) | C7: =B7/Premissas!$B$12 | D7: =B7*(Premissas!$B$17*Premissas!$B$15+Premissas!$B$20*Premissas!$B$18+Premissas!$B$23*Premissas!$B$21) | E7: =Premissas!$B$7*30*Premissas!$B$24*MIN(1,0.45+0.55*A7/12) | F7: =Premissas!$B$8*MIN(1,0.45+0.55*A7/12) | G7: =D7+E7+F7 | H7: =B7*(Premissas!$B$17*Premissas!$B$16+Premissas!$B$20*Premissas!$B$19+Premissas!$B$23*Premissas!$B$22)+Premissas!$B$7*30*MIN(1,0.45+0.55*A7/12) | I7: =H7/30 | J7: =SUM(G5:G7)*12/3 | K7: =IF((J7)<=0,0.06,IF((J7)<=180000,0.06,IF((J7)<=360000,((J7)*0.112-9360)/(J7),IF((J7)<=720000,((J7)*0.135-17640)/(J7),IF((J7)<=1800000,((J7)*0.16-35640)/(J7),0.165))))) | L7: =G7*K7 | M7: =H7*Premissas!$B$33+G7*Premissas!$B$32 | N7: =Premissas!$B$47 | O7: =G7-L7-M7-N7 | P7: =IF(G7=0,0,O7/G7) | Q7: =G7*Premissas!$B$79 | R7: =O7-Q7 | S7: =S6+R7
A8: 4 | B8: =MIN(Premissas!$B$6,MAX(Premissas!$B$9,Premissas!$B$6/(1+EXP(-Premissas!$B$10*(A8-Premissas!$B$11))))) | C8: =B8/Premissas!$B$12 | D8: =B8*(Premissas!$B$17*Premissas!$B$15+Premissas!$B$20*Premissas!$B$18+Premissas!$B$23*Premissas!$B$21) | E8: =Premissas!$B$7*30*Premissas!$B$24*MIN(1,0.45+0.55*A8/12) | F8: =Premissas!$B$8*MIN(1,0.45+0.55*A8/12) | G8: =D8+E8+F8 | H8: =B8*(Premissas!$B$17*Premissas!$B$16+Premissas!$B$20*Premissas!$B$19+Premissas!$B$23*Premissas!$B$22)+Premissas!$B$7*30*MIN(1,0.45+0.55*A8/12) | I8: =H8/30 | J8: =SUM(G5:G8)*12/4 | K8: =IF((J8)<=0,0.06,IF((J8)<=180000,0.06,IF((J8)<=360000,((J8)*0.112-9360)/(J8),IF((J8)<=720000,((J8)*0.135-17640)/(J8),IF((J8)<=1800000,((J8)*0.16-35640)/(J8),0.165))))) | L8: =G8*K8 | M8: =H8*Premissas!$B$33+G8*Premissas!$B$32 | N8: =Premissas!$B$47 | O8: =G8-L8-M8-N8 | P8: =IF(G8=0,0,O8/G8) | Q8: =G8*Premissas!$B$79 | R8: =O8-Q8 | S8: =S7+R8
A9: 5 | B9: =MIN(Premissas!$B$6,MAX(Premissas!$B$9,Premissas!$B$6/(1+EXP(-Premissas!$B$10*(A9-Premissas!$B$11))))) | C9: =B9/Premissas!$B$12 | D9: =B9*(Premissas!$B$17*Premissas!$B$15+Premissas!$B$20*Premissas!$B$18+Premissas!$B$23*Premissas!$B$21) | E9: =Premissas!$B$7*30*Premissas!$B$24*MIN(1,0.45+0.55*A9/12) | F9: =Premissas!$B$8*MIN(1,0.45+0.55*A9/12) | G9: =D9+E9+F9 | H9: =B9*(Premissas!$B$17*Premissas!$B$16+Premissas!$B$20*Premissas!$B$19+Premissas!$B$23*Premissas!$B$22)+Premissas!$B$7*30*MIN(1,0.45+0.55*A9/12) | I9: =H9/30 | J9: =SUM(G5:G9)*12/5 | K9: =IF((J9)<=0,0.06,IF((J9)<=180000,0.06,IF((J9)<=360000,((J9)*0.112-9360)/(J9),IF((J9)<=720000,((J9)*0.135-17640)/(J9),IF((J9)<=1800000,((J9)*0.16-35640)/(J9),0.165))))) | L9: =G9*K9 | M9: =H9*Premissas!$B$33+G9*Premissas!$B$32 | N9: =Premissas!$B$47 | O9: =G9-L9-M9-N9 | P9: =IF(G9=0,0,O9/G9) | Q9: =G9*Premissas!$B$79 | R9: =O9-Q9 | S9: =S8+R9
A10: 6 | B10: =MIN(Premissas!$B$6,MAX(Premissas!$B$9,Premissas!$B$6/(1+EXP(-Premissas!$B$10*(A10-Premissas!$B$11))))) | C10: =B10/Premissas!$B$12 | D10: =B10*(Premissas!$B$17*Premissas!$B$15+Premissas!$B$20*Premissas!$B$18+Premissas!$B$23*Premissas!$B$21) | E10: =Premissas!$B$7*30*Premissas!$B$24*MIN(1,0.45+0.55*A10/12) | F10: =Premissas!$B$8*MIN(1,0.45+0.55*A10/12) | G10: =D10+E10+F10 | H10: =B10*(Premissas!$B$17*Premissas!$B$16+Premissas!$B$20*Premissas!$B$19+Premissas!$B$23*Premissas!$B$22)+Premissas!$B$7*30*MIN(1,0.45+0.55*A10/12) | I10: =H10/30 | J10: =SUM(G5:G10)*12/6 | K10: =IF((J10)<=0,0.06,IF((J10)<=180000,0.06,IF((J10)<=360000,((J10)*0.112-9360)/(J10),IF((J10)<=720000,((J10)*0.135-17640)/(J10),IF((J10)<=1800000,((J10)*0.16-35640)/(J10),0.165))))) | L10: =G10*K10 | M10: =H10*Premissas!$B$33+G10*Premissas!$B$32 | N10: =Premissas!$B$47 | O10: =G10-L10-M10-N10 | P10: =IF(G10=0,0,O10/G10) | Q10: =G10*Premissas!$B$79 | R10: =O10-Q10 | S10: =S9+R10
A11: 7 | B11: =MIN(Premissas!$B$6,MAX(Premissas!$B$9,Premissas!$B$6/(1+EXP(-Premissas!$B$10*(A11-Premissas!$B$11))))) | C11: =B11/Premissas!$B$12 | D11: =B11*(Premissas!$B$17*Premissas!$B$15+Premissas!$B$20*Premissas!$B$18+Premissas!$B$23*Premissas!$B$21) | E11: =Premissas!$B$7*30*Premissas!$B$24*MIN(1,0.45+0.55*A11/12) | F11: =Premissas!$B$8*MIN(1,0.45+0.55*A11/12) | G11: =D11+E11+F11 | H11: =B11*(Premissas!$B$17*Premissas!$B$16+Premissas!$B$20*Premissas!$B$19+Premissas!$B$23*Premissas!$B$22)+Premissas!$B$7*30*MIN(1,0.45+0.55*A11/12) | I11: =H11/30 | J11: =SUM(G5:G11)*12/7 | K11: =IF((J11)<=0,0.06,IF((J11)<=180000,0.06,IF((J11)<=360000,((J11)*0.112-9360)/(J11),IF((J11)<=720000,((J11)*0.135-17640)/(J11),IF((J11)<=1800000,((J11)*0.16-35640)/(J11),0.165))))) | L11: =G11*K11 | M11: =H11*Premissas!$B$33+G11*Premissas!$B$32 | N11: =Premissas!$B$47 | O11: =G11-L11-M11-N11 | P11: =IF(G11=0,0,O11/G11) | Q11: =G11*Premissas!$B$79 | R11: =O11-Q11 | S11: =S10+R11
A12: 8 | B12: =MIN(Premissas!$B$6,MAX(Premissas!$B$9,Premissas!$B$6/(1+EXP(-Premissas!$B$10*(A12-Premissas!$B$11))))) | C12: =B12/Premissas!$B$12 | D12: =B12*(Premissas!$B$17*Premissas!$B$15+Premissas!$B$20*Premissas!$B$18+Premissas!$B$23*Premissas!$B$21) | E12: =Premissas!$B$7*30*Premissas!$B$24*MIN(1,0.45+0.55*A12/12) | F12: =Premissas!$B$8*MIN(1,0.45+0.55*A12/12) | G12: =D12+E12+F12 | H12: =B12*(Premissas!$B$17*Premissas!$B$16+Premissas!$B$20*Premissas!$B$19+Premissas!$B$23*Premissas!$B$22)+Premissas!$B$7*30*MIN(1,0.45+0.55*A12/12) | I12: =H12/30 | J12: =SUM(G5:G12)*12/8 | K12: =IF((J12)<=0,0.06,IF((J12)<=180000,0.06,IF((J12)<=360000,((J12)*0.112-9360)/(J12),IF((J12)<=720000,((J12)*0.135-17640)/(J12),IF((J12)<=1800000,((J12)*0.16-35640)/(J12),0.165))))) | L12: =G12*K12 | M12: =H12*Premissas!$B$33+G12*Premissas!$B$32 | N12: =Premissas!$B$47 | O12: =G12-L12-M12-N12 | P12: =IF(G12=0,0,O12/G12) | Q12: =G12*Premissas!$B$79 | R12: =O12-Q12 | S12: =S11+R12
A13: 9 | B13: =MIN(Premissas!$B$6,MAX(Premissas!$B$9,Premissas!$B$6/(1+EXP(-Premissas!$B$10*(A13-Premissas!$B$11))))) | C13: =B13/Premissas!$B$12 | D13: =B13*(Premissas!$B$17*Premissas!$B$15+Premissas!$B$20*Premissas!$B$18+Premissas!$B$23*Premissas!$B$21) | E13: =Premissas!$B$7*30*Premissas!$B$24*MIN(1,0.45+0.55*A13/12) | F13: =Premissas!$B$8*MIN(1,0.45+0.55*A13/12) | G13: =D13+E13+F13 | H13: =B13*(Premissas!$B$17*Premissas!$B$16+Premissas!$B$20*Premissas!$B$19+Premissas!$B$23*Premissas!$B$22)+Premissas!$B$7*30*MIN(1,0.45+0.55*A13/12) | I13: =H13/30 | J13: =SUM(G5:G13)*12/9 | K13: =IF((J13)<=0,0.06,IF((J13)<=180000,0.06,IF((J13)<=360000,((J13)*0.112-9360)/(J13),IF((J13)<=720000,((J13)*0.135-17640)/(J13),IF((J13)<=1800000,((J13)*0.16-35640)/(J13),0.165))))) | L13: =G13*K13 | M13: =H13*Premissas!$B$33+G13*Premissas!$B$32 | N13: =Premissas!$B$47 | O13: =G13-L13-M13-N13 | P13: =IF(G13=0,0,O13/G13) | Q13: =G13*Premissas!$B$79 | R13: =O13-Q13 | S13: =S12+R13
A14: 10 | B14: =MIN(Premissas!$B$6,MAX(Premissas!$B$9,Premissas!$B$6/(1+EXP(-Premissas!$B$10*(A14-Premissas!$B$11))))) | C14: =B14/Premissas!$B$12 | D14: =B14*(Premissas!$B$17*Premissas!$B$15+Premissas!$B$20*Premissas!$B$18+Premissas!$B$23*Premissas!$B$21) | E14: =Premissas!$B$7*30*Premissas!$B$24*MIN(1,0.45+0.55*A14/12) | F14: =Premissas!$B$8*MIN(1,0.45+0.55*A14/12) | G14: =D14+E14+F14 | H14: =B14*(Premissas!$B$17*Premissas!$B$16+Premissas!$B$20*Premissas!$B$19+Premissas!$B$23*Premissas!$B$22)+Premissas!$B$7*30*MIN(1,0.45+0.55*A14/12) | I14: =H14/30 | J14: =SUM(G5:G14)*12/10 | K14: =IF((J14)<=0,0.06,IF((J14)<=180000,0.06,IF((J14)<=360000,((J14)*0.112-9360)/(J14),IF((J14)<=720000,((J14)*0.135-17640)/(J14),IF((J14)<=1800000,((J14)*0.16-35640)/(J14),0.165))))) | L14: =G14*K14 | M14: =H14*Premissas!$B$33+G14*Premissas!$B$32 | N14: =Premissas!$B$47 | O14: =G14-L14-M14-N14 | P14: =IF(G14=0,0,O14/G14) | Q14: =G14*Premissas!$B$79 | R14: =O14-Q14 | S14: =S13+R14
A15: 11 | B15: =MIN(Premissas!$B$6,MAX(Premissas!$B$9,Premissas!$B$6/(1+EXP(-Premissas!$B$10*(A15-Premissas!$B$11))))) | C15: =B15/Premissas!$B$12 | D15: =B15*(Premissas!$B$17*Premissas!$B$15+Premissas!$B$20*Premissas!$B$18+Premissas!$B$23*Premissas!$B$21) | E15: =Premissas!$B$7*30*Premissas!$B$24*MIN(1,0.45+0.55*A15/12) | F15: =Premissas!$B$8*MIN(1,0.45+0.55*A15/12) | G15: =D15+E15+F15 | H15: =B15*(Premissas!$B$17*Premissas!$B$16+Premissas!$B$20*Premissas!$B$19+Premissas!$B$23*Premissas!$B$22)+Premissas!$B$7*30*MIN(1,0.45+0.55*A15/12) | I15: =H15/30 | J15: =SUM(G5:G15)*12/11 | K15: =IF((J15)<=0,0.06,IF((J15)<=180000,0.06,IF((J15)<=360000,((J15)*0.112-9360)/(J15),IF((J15)<=720000,((J15)*0.135-17640)/(J15),IF((J15)<=1800000,((J15)*0.16-35640)/(J15),0.165))))) | L15: =G15*K15 | M15: =H15*Premissas!$B$33+G15*Premissas!$B$32 | N15: =Premissas!$B$47 | O15: =G15-L15-M15-N15 | P15: =IF(G15=0,0,O15/G15) | Q15: =G15*Premissas!$B$79 | R15: =O15-Q15 | S15: =S14+R15
A16: 12 | B16: =MIN(Premissas!$B$6,MAX(Premissas!$B$9,Premissas!$B$6/(1+EXP(-Premissas!$B$10*(A16-Premissas!$B$11))))) | C16: =B16/Premissas!$B$12 | D16: =B16*(Premissas!$B$17*Premissas!$B$15+Premissas!$B$20*Premissas!$B$18+Premissas!$B$23*Premissas!$B$21) | E16: =Premissas!$B$7*30*Premissas!$B$24*MIN(1,0.45+0.55*A16/12) | F16: =Premissas!$B$8*MIN(1,0.45+0.55*A16/12) | G16: =D16+E16+F16 | H16: =B16*(Premissas!$B$17*Premissas!$B$16+Premissas!$B$20*Premissas!$B$19+Premissas!$B$23*Premissas!$B$22)+Premissas!$B$7*30*MIN(1,0.45+0.55*A16/12) | I16: =H16/30 | J16: =SUM(G5:G16)*12/12 | K16: =IF((J16)<=0,0.06,IF((J16)<=180000,0.06,IF((J16)<=360000,((J16)*0.112-9360)/(J16),IF((J16)<=720000,((J16)*0.135-17640)/(J16),IF((J16)<=1800000,((J16)*0.16-35640)/(J16),0.165))))) | L16: =G16*K16 | M16: =H16*Premissas!$B$33+G16*Premissas!$B$32 | N16: =Premissas!$B$47 | O16: =G16-L16-M16-N16 | P16: =IF(G16=0,0,O16/G16) | Q16: =G16*Premissas!$B$79 | R16: =O16-Q16 | S16: =S15+R16
A17: 13 | B17: =MIN(Premissas!$B$6,MAX(Premissas!$B$9,Premissas!$B$6/(1+EXP(-Premissas!$B$10*(A17-Premissas!$B$11))))) | C17: =B17/Premissas!$B$12 | D17: =B17*(Premissas!$B$17*Premissas!$B$15+Premissas!$B$20*Premissas!$B$18+Premissas!$B$23*Premissas!$B$21) | E17: =Premissas!$B$7*30*Premissas!$B$24*MIN(1,0.45+0.55*A17/12) | F17: =Premissas!$B$8*MIN(1,0.45+0.55*A17/12) | G17: =D17+E17+F17 | H17: =B17*(Premissas!$B$17*Premissas!$B$16+Premissas!$B$20*Premissas!$B$19+Premissas!$B$23*Premissas!$B$22)+Premissas!$B$7*30*MIN(1,0.45+0.55*A17/12) | I17: =H17/30 | J17: =SUM(G6:G17)*12/12 | K17: =IF((J17)<=0,0.06,IF((J17)<=180000,0.06,IF((J17)<=360000,((J17)*0.112-9360)/(J17),IF((J17)<=720000,((J17)*0.135-17640)/(J17),IF((J17)<=1800000,((J17)*0.16-35640)/(J17),0.165))))) | L17: =G17*K17 | M17: =H17*Premissas!$B$33+G17*Premissas!$B$32 | N17: =Premissas!$B$47 | O17: =G17-L17-M17-N17 | P17: =IF(G17=0,0,O17/G17) | Q17: =G17*Premissas!$B$79 | R17: =O17-Q17 | S17: =S16+R17
A18: 14 | B18: =MIN(Premissas!$B$6,MAX(Premissas!$B$9,Premissas!$B$6/(1+EXP(-Premissas!$B$10*(A18-Premissas!$B$11))))) | C18: =B18/Premissas!$B$12 | D18: =B18*(Premissas!$B$17*Premissas!$B$15+Premissas!$B$20*Premissas!$B$18+Premissas!$B$23*Premissas!$B$21) | E18: =Premissas!$B$7*30*Premissas!$B$24*MIN(1,0.45+0.55*A18/12) | F18: =Premissas!$B$8*MIN(1,0.45+0.55*A18/12) | G18: =D18+E18+F18 | H18: =B18*(Premissas!$B$17*Premissas!$B$16+Premissas!$B$20*Premissas!$B$19+Premissas!$B$23*Premissas!$B$22)+Premissas!$B$7*30*MIN(1,0.45+0.55*A18/12) | I18: =H18/30 | J18: =SUM(G7:G18)*12/12 | K18: =IF((J18)<=0,0.06,IF((J18)<=180000,0.06,IF((J18)<=360000,((J18)*0.112-9360)/(J18),IF((J18)<=720000,((J18)*0.135-17640)/(J18),IF((J18)<=1800000,((J18)*0.16-35640)/(J18),0.165))))) | L18: =G18*K18 | M18: =H18*Premissas!$B$33+G18*Premissas!$B$32 | N18: =Premissas!$B$47 | O18: =G18-L18-M18-N18 | P18: =IF(G18=0,0,O18/G18) | Q18: =G18*Premissas!$B$79 | R18: =O18-Q18 | S18: =S17+R18
A19: 15 | B19: =MIN(Premissas!$B$6,MAX(Premissas!$B$9,Premissas!$B$6/(1+EXP(-Premissas!$B$10*(A19-Premissas!$B$11))))) | C19: =B19/Premissas!$B$12 | D19: =B19*(Premissas!$B$17*Premissas!$B$15+Premissas!$B$20*Premissas!$B$18+Premissas!$B$23*Premissas!$B$21) | E19: =Premissas!$B$7*30*Premissas!$B$24*MIN(1,0.45+0.55*A19/12) | F19: =Premissas!$B$8*MIN(1,0.45+0.55*A19/12) | G19: =D19+E19+F19 | H19: =B19*(Premissas!$B$17*Premissas!$B$16+Premissas!$B$20*Premissas!$B$19+Premissas!$B$23*Premissas!$B$22)+Premissas!$B$7*30*MIN(1,0.45+0.55*A19/12) | I19: =H19/30 | J19: =SUM(G8:G19)*12/12 | K19: =IF((J19)<=0,0.06,IF((J19)<=180000,0.06,IF((J19)<=360000,((J19)*0.112-9360)/(J19),IF((J19)<=720000,((J19)*0.135-17640)/(J19),IF((J19)<=1800000,((J19)*0.16-35640)/(J19),0.165))))) | L19: =G19*K19 | M19: =H19*Premissas!$B$33+G19*Premissas!$B$32 | N19: =Premissas!$B$47 | O19: =G19-L19-M19-N19 | P19: =IF(G19=0,0,O19/G19) | Q19: =G19*Premissas!$B$79 | R19: =O19-Q19 | S19: =S18+R19
A20: 16 | B20: =MIN(Premissas!$B$6,MAX(Premissas!$B$9,Premissas!$B$6/(1+EXP(-Premissas!$B$10*(A20-Premissas!$B$11))))) | C20: =B20/Premissas!$B$12 | D20: =B20*(Premissas!$B$17*Premissas!$B$15+Premissas!$B$20*Premissas!$B$18+Premissas!$B$23*Premissas!$B$21) | E20: =Premissas!$B$7*30*Premissas!$B$24*MIN(1,0.45+0.55*A20/12) | F20: =Premissas!$B$8*MIN(1,0.45+0.55*A20/12) | G20: =D20+E20+F20 | H20: =B20*(Premissas!$B$17*Premissas!$B$16+Premissas!$B$20*Premissas!$B$19+Premissas!$B$23*Premissas!$B$22)+Premissas!$B$7*30*MIN(1,0.45+0.55*A20/12) | I20: =H20/30 | J20: =SUM(G9:G20)*12/12 | K20: =IF((J20)<=0,0.06,IF((J20)<=180000,0.06,IF((J20)<=360000,((J20)*0.112-9360)/(J20),IF((J20)<=720000,((J20)*0.135-17640)/(J20),IF((J20)<=1800000,((J20)*0.16-35640)/(J20),0.165))))) | L20: =G20*K20 | M20: =H20*Premissas!$B$33+G20*Premissas!$B$32 | N20: =Premissas!$B$47 | O20: =G20-L20-M20-N20 | P20: =IF(G20=0,0,O20/G20) | Q20: =G20*Premissas!$B$79 | R20: =O20-Q20 | S20: =S19+R20
A21: 17 | B21: =MIN(Premissas!$B$6,MAX(Premissas!$B$9,Premissas!$B$6/(1+EXP(-Premissas!$B$10*(A21-Premissas!$B$11))))) | C21: =B21/Premissas!$B$12 | D21: =B21*(Premissas!$B$17*Premissas!$B$15+Premissas!$B$20*Premissas!$B$18+Premissas!$B$23*Premissas!$B$21) | E21: =Premissas!$B$7*30*Premissas!$B$24*MIN(1,0.45+0.55*A21/12) | F21: =Premissas!$B$8*MIN(1,0.45+0.55*A21/12) | G21: =D21+E21+F21 | H21: =B21*(Premissas!$B$17*Premissas!$B$16+Premissas!$B$20*Premissas!$B$19+Premissas!$B$23*Premissas!$B$22)+Premissas!$B$7*30*MIN(1,0.45+0.55*A21/12) | I21: =H21/30 | J21: =SUM(G10:G21)*12/12 | K21: =IF((J21)<=0,0.06,IF((J21)<=180000,0.06,IF((J21)<=360000,((J21)*0.112-9360)/(J21),IF((J21)<=720000,((J21)*0.135-17640)/(J21),IF((J21)<=1800000,((J21)*0.16-35640)/(J21),0.165))))) | L21: =G21*K21 | M21: =H21*Premissas!$B$33+G21*Premissas!$B$32 | N21: =Premissas!$B$47 | O21: =G21-L21-M21-N21 | P21: =IF(G21=0,0,O21/G21) | Q21: =G21*Premissas!$B$79 | R21: =O21-Q21 | S21: =S20+R21
A22: 18 | B22: =MIN(Premissas!$B$6,MAX(Premissas!$B$9,Premissas!$B$6/(1+EXP(-Premissas!$B$10*(A22-Premissas!$B$11))))) | C22: =B22/Premissas!$B$12 | D22: =B22*(Premissas!$B$17*Premissas!$B$15+Premissas!$B$20*Premissas!$B$18+Premissas!$B$23*Premissas!$B$21) | E22: =Premissas!$B$7*30*Premissas!$B$24*MIN(1,0.45+0.55*A22/12) | F22: =Premissas!$B$8*MIN(1,0.45+0.55*A22/12) | G22: =D22+E22+F22 | H22: =B22*(Premissas!$B$17*Premissas!$B$16+Premissas!$B$20*Premissas!$B$19+Premissas!$B$23*Premissas!$B$22)+Premissas!$B$7*30*MIN(1,0.45+0.55*A22/12) | I22: =H22/30 | J22: =SUM(G11:G22)*12/12 | K22: =IF((J22)<=0,0.06,IF((J22)<=180000,0.06,IF((J22)<=360000,((J22)*0.112-9360)/(J22),IF((J22)<=720000,((J22)*0.135-17640)/(J22),IF((J22)<=1800000,((J22)*0.16-35640)/(J22),0.165))))) | L22: =G22*K22 | M22: =H22*Premissas!$B$33+G22*Premissas!$B$32 | N22: =Premissas!$B$47 | O22: =G22-L22-M22-N22 | P22: =IF(G22=0,0,O22/G22) | Q22: =G22*Premissas!$B$79 | R22: =O22-Q22 | S22: =S21+R22
A23: 19 | B23: =MIN(Premissas!$B$6,MAX(Premissas!$B$9,Premissas!$B$6/(1+EXP(-Premissas!$B$10*(A23-Premissas!$B$11))))) | C23: =B23/Premissas!$B$12 | D23: =B23*(Premissas!$B$17*Premissas!$B$15+Premissas!$B$20*Premissas!$B$18+Premissas!$B$23*Premissas!$B$21) | E23: =Premissas!$B$7*30*Premissas!$B$24*MIN(1,0.45+0.55*A23/12) | F23: =Premissas!$B$8*MIN(1,0.45+0.55*A23/12) | G23: =D23+E23+F23 | H23: =B23*(Premissas!$B$17*Premissas!$B$16+Premissas!$B$20*Premissas!$B$19+Premissas!$B$23*Premissas!$B$22)+Premissas!$B$7*30*MIN(1,0.45+0.55*A23/12) | I23: =H23/30 | J23: =SUM(G12:G23)*12/12 | K23: =IF((J23)<=0,0.06,IF((J23)<=180000,0.06,IF((J23)<=360000,((J23)*0.112-9360)/(J23),IF((J23)<=720000,((J23)*0.135-17640)/(J23),IF((J23)<=1800000,((J23)*0.16-35640)/(J23),0.165))))) | L23: =G23*K23 | M23: =H23*Premissas!$B$33+G23*Premissas!$B$32 | N23: =Premissas!$B$47 | O23: =G23-L23-M23-N23 | P23: =IF(G23=0,0,O23/G23) | Q23: =G23*Premissas!$B$79 | R23: =O23-Q23 | S23: =S22+R23
A24: 20 | B24: =MIN(Premissas!$B$6,MAX(Premissas!$B$9,Premissas!$B$6/(1+EXP(-Premissas!$B$10*(A24-Premissas!$B$11))))) | C24: =B24/Premissas!$B$12 | D24: =B24*(Premissas!$B$17*Premissas!$B$15+Premissas!$B$20*Premissas!$B$18+Premissas!$B$23*Premissas!$B$21) | E24: =Premissas!$B$7*30*Premissas!$B$24*MIN(1,0.45+0.55*A24/12) | F24: =Premissas!$B$8*MIN(1,0.45+0.55*A24/12) | G24: =D24+E24+F24 | H24: =B24*(Premissas!$B$17*Premissas!$B$16+Premissas!$B$20*Premissas!$B$19+Premissas!$B$23*Premissas!$B$22)+Premissas!$B$7*30*MIN(1,0.45+0.55*A24/12) | I24: =H24/30 | J24: =SUM(G13:G24)*12/12 | K24: =IF((J24)<=0,0.06,IF((J24)<=180000,0.06,IF((J24)<=360000,((J24)*0.112-9360)/(J24),IF((J24)<=720000,((J24)*0.135-17640)/(J24),IF((J24)<=1800000,((J24)*0.16-35640)/(J24),0.165))))) | L24: =G24*K24 | M24: =H24*Premissas!$B$33+G24*Premissas!$B$32 | N24: =Premissas!$B$47 | O24: =G24-L24-M24-N24 | P24: =IF(G24=0,0,O24/G24) | Q24: =G24*Premissas!$B$79 | R24: =O24-Q24 | S24: =S23+R24
A25: 21 | B25: =MIN(Premissas!$B$6,MAX(Premissas!$B$9,Premissas!$B$6/(1+EXP(-Premissas!$B$10*(A25-Premissas!$B$11))))) | C25: =B25/Premissas!$B$12 | D25: =B25*(Premissas!$B$17*Premissas!$B$15+Premissas!$B$20*Premissas!$B$18+Premissas!$B$23*Premissas!$B$21) | E25: =Premissas!$B$7*30*Premissas!$B$24*MIN(1,0.45+0.55*A25/12) | F25: =Premissas!$B$8*MIN(1,0.45+0.55*A25/12) | G25: =D25+E25+F25 | H25: =B25*(Premissas!$B$17*Premissas!$B$16+Premissas!$B$20*Premissas!$B$19+Premissas!$B$23*Premissas!$B$22)+Premissas!$B$7*30*MIN(1,0.45+0.55*A25/12) | I25: =H25/30 | J25: =SUM(G14:G25)*12/12 | K25: =IF((J25)<=0,0.06,IF((J25)<=180000,0.06,IF((J25)<=360000,((J25)*0.112-9360)/(J25),IF((J25)<=720000,((J25)*0.135-17640)/(J25),IF((J25)<=1800000,((J25)*0.16-35640)/(J25),0.165))))) | L25: =G25*K25 | M25: =H25*Premissas!$B$33+G25*Premissas!$B$32 | N25: =Premissas!$B$47 | O25: =G25-L25-M25-N25 | P25: =IF(G25=0,0,O25/G25) | Q25: =G25*Premissas!$B$79 | R25: =O25-Q25 | S25: =S24+R25
A26: 22 | B26: =MIN(Premissas!$B$6,MAX(Premissas!$B$9,Premissas!$B$6/(1+EXP(-Premissas!$B$10*(A26-Premissas!$B$11))))) | C26: =B26/Premissas!$B$12 | D26: =B26*(Premissas!$B$17*Premissas!$B$15+Premissas!$B$20*Premissas!$B$18+Premissas!$B$23*Premissas!$B$21) | E26: =Premissas!$B$7*30*Premissas!$B$24*MIN(1,0.45+0.55*A26/12) | F26: =Premissas!$B$8*MIN(1,0.45+0.55*A26/12) | G26: =D26+E26+F26 | H26: =B26*(Premissas!$B$17*Premissas!$B$16+Premissas!$B$20*Premissas!$B$19+Premissas!$B$23*Premissas!$B$22)+Premissas!$B$7*30*MIN(1,0.45+0.55*A26/12) | I26: =H26/30 | J26: =SUM(G15:G26)*12/12 | K26: =IF((J26)<=0,0.06,IF((J26)<=180000,0.06,IF((J26)<=360000,((J26)*0.112-9360)/(J26),IF((J26)<=720000,((J26)*0.135-17640)/(J26),IF((J26)<=1800000,((J26)*0.16-35640)/(J26),0.165))))) | L26: =G26*K26 | M26: =H26*Premissas!$B$33+G26*Premissas!$B$32 | N26: =Premissas!$B$47 | O26: =G26-L26-M26-N26 | P26: =IF(G26=0,0,O26/G26) | Q26: =G26*Premissas!$B$79 | R26: =O26-Q26 | S26: =S25+R26
A27: 23 | B27: =MIN(Premissas!$B$6,MAX(Premissas!$B$9,Premissas!$B$6/(1+EXP(-Premissas!$B$10*(A27-Premissas!$B$11))))) | C27: =B27/Premissas!$B$12 | D27: =B27*(Premissas!$B$17*Premissas!$B$15+Premissas!$B$20*Premissas!$B$18+Premissas!$B$23*Premissas!$B$21) | E27: =Premissas!$B$7*30*Premissas!$B$24*MIN(1,0.45+0.55*A27/12) | F27: =Premissas!$B$8*MIN(1,0.45+0.55*A27/12) | G27: =D27+E27+F27 | H27: =B27*(Premissas!$B$17*Premissas!$B$16+Premissas!$B$20*Premissas!$B$19+Premissas!$B$23*Premissas!$B$22)+Premissas!$B$7*30*MIN(1,0.45+0.55*A27/12) | I27: =H27/30 | J27: =SUM(G16:G27)*12/12 | K27: =IF((J27)<=0,0.06,IF((J27)<=180000,0.06,IF((J27)<=360000,((J27)*0.112-9360)/(J27),IF((J27)<=720000,((J27)*0.135-17640)/(J27),IF((J27)<=1800000,((J27)*0.16-35640)/(J27),0.165))))) | L27: =G27*K27 | M27: =H27*Premissas!$B$33+G27*Premissas!$B$32 | N27: =Premissas!$B$47 | O27: =G27-L27-M27-N27 | P27: =IF(G27=0,0,O27/G27) | Q27: =G27*Premissas!$B$79 | R27: =O27-Q27 | S27: =S26+R27
... A63: 59 | B63: =MIN(Premissas!$B$6,MAX(Premissas!$B$9,Premissas!$B$6/(1+EXP(-Premissas!$B$10*(A63-Premissas!$B$11))))) | C63: =B63/Premissas!$B$12 | D63: =B63*(Premissas!$B$17*Premissas!$B$15+Premissas!$B$20*Premissas!$B$18+Premissas!$B$23*Premissas!$B$21) | E63: =Premissas!$B$7*30*Premissas!$B$24*MIN(1,0.45+0.55*A63/12) | F63: =Premissas!$B$8*MIN(1,0.45+0.55*A63/12) | G63: =D63+E63+F63 | H63: =B63*(Premissas!$B$17*Premissas!$B$16+Premissas!$B$20*Premissas!$B$19+Premissas!$B$23*Premissas!$B$22)+Premissas!$B$7*30*MIN(1,0.45+0.55*A63/12) | I63: =H63/30 | J63: =SUM(G52:G63)*12/12 | K63: =IF((J63)<=0,0.06,IF((J63)<=180000,0.06,IF((J63)<=360000,((J63)*0.112-9360)/(J63),IF((J63)<=720000,((J63)*0.135-17640)/(J63),IF((J63)<=1800000,((J63)*0.16-35640)/(J63),0.165))))) | L63: =G63*K63 | M63: =H63*Premissas!$B$33+G63*Premissas!$B$32 | N63: =Premissas!$B$47 | O63: =G63-L63-M63-N63 | P63: =IF(G63=0,0,O63/G63) | Q63: =G63*Premissas!$B$79 | R63: =O63-Q63 | S63: =S62+R63
A64: 60 | B64: =MIN(Premissas!$B$6,MAX(Premissas!$B$9,Premissas!$B$6/(1+EXP(-Premissas!$B$10*(A64-Premissas!$B$11))))) | C64: =B64/Premissas!$B$12 | D64: =B64*(Premissas!$B$17*Premissas!$B$15+Premissas!$B$20*Premissas!$B$18+Premissas!$B$23*Premissas!$B$21) | E64: =Premissas!$B$7*30*Premissas!$B$24*MIN(1,0.45+0.55*A64/12) | F64: =Premissas!$B$8*MIN(1,0.45+0.55*A64/12) | G64: =D64+E64+F64 | H64: =B64*(Premissas!$B$17*Premissas!$B$16+Premissas!$B$20*Premissas!$B$19+Premissas!$B$23*Premissas!$B$22)+Premissas!$B$7*30*MIN(1,0.45+0.55*A64/12) | I64: =H64/30 | J64: =SUM(G53:G64)*12/12 | K64: =IF((J64)<=0,0.06,IF((J64)<=180000,0.06,IF((J64)<=360000,((J64)*0.112-9360)/(J64),IF((J64)<=720000,((J64)*0.135-17640)/(J64),IF((J64)<=1800000,((J64)*0.16-35640)/(J64),0.165))))) | L64: =G64*K64 | M64: =H64*Premissas!$B$33+G64*Premissas!$B$32 | N64: =Premissas!$B$47 | O64: =G64-L64-M64-N64 | P64: =IF(G64=0,0,O64/G64) | Q64: =G64*Premissas!$B$79 | R64: =O64-Q64+Premissas!$B$65*Premissas!$B$80 | S64: =S63+R64
