Workbook

Sheet Premissas
A1: MODELO ECONÔMICO — REDE DE LAVAGEM AUTOMATIZADA POR ASSINATURA
A2: Reconstrução a partir dos números-resumo do Plano de Franquia (set/2026). O Excel original não foi fornecido.
A3: Células azuis são premissas editáveis. Tudo o mais é fórmula.
A5: PREMISSAS COMUNS
A6: Taxa mínima de atratividade (a.a.) | B6: 0.18
A7: Imposto sobre receita da unidade (Simples, efetivo) | B7: 0.11
A8: Custos variáveis (água, energia, química, gateway) | B8: 0.22
A9: Royalty sobre receita bruta | B9: 0.06
A10: Fundo de marketing sobre receita bruta | B10: 0.02
A11: Taxa de tecnologia (R$/mês por unidade) | B11: 700
A12: Capex de manutenção (% da receita) | B12: 0.015
A13: Valor residual no mês 60 (% do capex) | B13: 0.35
A14: Imposto sobre receita da franqueadora | B14: 0.16
A15: Rebate do fabricante por unidade instalada | B15: 25000
A17: PREMISSAS POR FORMATO
B18: BOX | C18: EXPRESS | D18: PRIME
A19: Taxa de franquia | B19: 35000 | C19: 50000 | D19: 60000
A20: Capex de instalação | B20: 155000 | C20: 326000 | D20: 600000
A21: Capital de giro | B21: 25000 | C21: 40000 | D21: 60000
A22: Receita madura (R$/mês) | B22: 19000 | C22: 48000 | D22: 75000
A23: EBITDA maduro informado no plano | B23: 5000 | C23: 15600 | D23: 24800
A24: Investimento total (taxa + capex + giro) | B24: =B19+B20+B21 | C24: =C19+C20+C21 | D24: =D19+D20+D21
A25: Custo fixo mensal (calibrado para reproduzir o EBITDA) | B25: =B22*(1-Premissas!$B$7-Premissas!$B$8-Premissas!$B$9-Premissas!$B$10)-Premissas!$B$11-B23 | C25: =C22*(1-Premissas!$B$7-Premissas!$B$8-Premissas!$B$9-Premissas!$B$10)-Premissas!$B$11-C23 | D25: =D22*(1-Premissas!$B$7-Premissas!$B$8-Premissas!$B$9-Premissas!$B$10)-Premissas!$B$11-D23
A27: CURVA DE MATURAÇÃO (% da receita madura)
A28: Meses 1–3 | B28: 0.35
A29: Meses 4–6 | B29: 0.55
A30: Meses 7–9 | B30: 0.75
A31: Meses 10–12 | B31: 0.88
A32: Mês 13 em diante | B32: 1

Sheet Resumo
A1: RESUMO EXECUTIVO
A2: Todos os valores vêm das abas de cálculo. Mude as premissas e tudo se move.
A4: FRANQUEADO
B5: BOX | C5: EXPRESS | D5: PRIME
A6: Investimento total | B6: =Box!B71 | C6: =Express!B71 | D6: =Prime!B71
A7: EBITDA maduro (R$/mês) | B7: =Box!B72 | C7: =Express!B72 | D7: =Prime!B72
A8: Margem EBITDA | B8: =Box!B73 | C8: =Express!B73 | D8: =Prime!B73
A9: Payback (meses) | B9: =Box!B74 | C9: =Express!B74 | D9: =Prime!B74
A10: TIR (a.a.) | B10: =Box!B76 | C10: =Express!B76 | D10: =Prime!B76
A11: VPL @ TMA | B11: =Box!B77 | C11: =Express!B77 | D11: =Prime!B77
A12: ROI 5 anos | B12: =Box!B78 | C12: =Express!B78 | D12: =Prime!B78
A14: LEITURA
A15: O formato BOX rende abaixo da TMA: VPL negativo. A recomendação do BP é retirá-lo da oferta.
A16: EXPRESS é o produto principal; PRIME só depois de validado em praça turística.

Sheet Box
A1: UNIDADE BOX — FLUXO MENSAL (60 MESES)
A3: Mês | B3: % rampa | C3: Receita | D3: Impostos | E3: Variáveis | F3: Royalty | G3: Fundo | H3: Tecnologia | I3: Fixos | J3: EBITDA | K3: Fluxo livre | L3: Acumulado
A4: 0 | K4: =-Premissas!B24 | L4: =-Premissas!B24
A5: 1 | B5: =IF(A5<=3,Premissas!$B$28,IF(A5<=6,Premissas!$B$29,IF(A5<=9,Premissas!$B$30,IF(A5<=12,Premissas!$B$31,Premissas!$B$32)))) | C5: =Premissas!B22*B5 | D5: =-C5*Premissas!$B$7 | E5: =-C5*Premissas!$B$8 | F5: =-C5*Premissas!$B$9 | G5: =-C5*Premissas!$B$10 | H5: =-Premissas!$B$11 | I5: =-Premissas!B25 | J5: =SUM(C5:I5) | K5: =J5-C5*Premissas!$B$12 | L5: =L4+K5
A6: 2 | B6: =IF(A6<=3,Premissas!$B$28,IF(A6<=6,Premissas!$B$29,IF(A6<=9,Premissas!$B$30,IF(A6<=12,Premissas!$B$31,Premissas!$B$32)))) | C6: =Premissas!B22*B6 | D6: =-C6*Premissas!$B$7 | E6: =-C6*Premissas!$B$8 | F6: =-C6*Premissas!$B$9 | G6: =-C6*Premissas!$B$10 | H6: =-Premissas!$B$11 | I6: =-Premissas!B25 | J6: =SUM(C6:I6) | K6: =J6-C6*Premissas!$B$12 | L6: =L5+K6
A7: 3 | B7: =IF(A7<=3,Premissas!$B$28,IF(A7<=6,Premissas!$B$29,IF(A7<=9,Premissas!$B$30,IF(A7<=12,Premissas!$B$31,Premissas!$B$32)))) | C7: =Premissas!B22*B7 | D7: =-C7*Premissas!$B$7 | E7: =-C7*Premissas!$B$8 | F7: =-C7*Premissas!$B$9 | G7: =-C7*Premissas!$B$10 | H7: =-Premissas!$B$11 | I7: =-Premissas!B25 | J7: =SUM(C7:I7) | K7: =J7-C7*Premissas!$B$12 | L7: =L6+K7
A8: 4 | B8: =IF(A8<=3,Premissas!$B$28,IF(A8<=6,Premissas!$B$29,IF(A8<=9,Premissas!$B$30,IF(A8<=12,Premissas!$B$31,Premissas!$B$32)))) | C8: =Premissas!B22*B8 | D8: =-C8*Premissas!$B$7 | E8: =-C8*Premissas!$B$8 | F8: =-C8*Premissas!$B$9 | G8: =-C8*Premissas!$B$10 | H8: =-Premissas!$B$11 | I8: =-Premissas!B25 | J8: =SUM(C8:I8) | K8: =J8-C8*Premissas!$B$12 | L8: =L7+K8
A9: 5 | B9: =IF(A9<=3,Premissas!$B$28,IF(A9<=6,Premissas!$B$29,IF(A9<=9,Premissas!$B$30,IF(A9<=12,Premissas!$B$31,Premissas!$B$32)))) | C9: =Premissas!B22*B9 | D9: =-C9*Premissas!$B$7 | E9: =-C9*Premissas!$B$8 | F9: =-C9*Premissas!$B$9 | G9: =-C9*Premissas!$B$10 | H9: =-Premissas!$B$11 | I9: =-Premissas!B25 | J9: =SUM(C9:I9) | K9: =J9-C9*Premissas!$B$12 | L9: =L8+K9
A10: 6 | B10: =IF(A10<=3,Premissas!$B$28,IF(A10<=6,Premissas!$B$29,IF(A10<=9,Premissas!$B$30,IF(A10<=12,Premissas!$B$31,Premissas!$B$32)))) | C10: =Premissas!B22*B10 | D10: =-C10*Premissas!$B$7 | E10: =-C10*Premissas!$B$8 | F10: =-C10*Premissas!$B$9 | G10: =-C10*Premissas!$B$10 | H10: =-Premissas!$B$11 | I10: =-Premissas!B25 | J10: =SUM(C10:I10) | K10: =J10-C10*Premissas!$B$12 | L10: =L9+K10
A11: 7 | B11: =IF(A11<=3,Premissas!$B$28,IF(A11<=6,Premissas!$B$29,IF(A11<=9,Premissas!$B$30,IF(A11<=12,Premissas!$B$31,Premissas!$B$32)))) | C11: =Premissas!B22*B11 | D11: =-C11*Premissas!$B$7 | E11: =-C11*Premissas!$B$8 | F11: =-C11*Premissas!$B$9 | G11: =-C11*Premissas!$B$10 | H11: =-Premissas!$B$11 | I11: =-Premissas!B25 | J11: =SUM(C11:I11) | K11: =J11-C11*Premissas!$B$12 | L11: =L10+K11
A12: 8 | B12: =IF(A12<=3,Premissas!$B$28,IF(A12<=6,Premissas!$B$29,IF(A12<=9,Premissas!$B$30,IF(A12<=12,Premissas!$B$31,Premissas!$B$32)))) | C12: =Premissas!B22*B12 | D12: =-C12*Premissas!$B$7 | E12: =-C12*Premissas!$B$8 | F12: =-C12*Premissas!$B$9 | G12: =-C12*Premissas!$B$10 | H12: =-Premissas!$B$11 | I12: =-Premissas!B25 | J12: =SUM(C12:I12) | K12: =J12-C12*Premissas!$B$12 | L12: =L11+K12
A13: 9 | B13: =IF(A13<=3,Premissas!$B$28,IF(A13<=6,Premissas!$B$29,IF(A13<=9,Premissas!$B$30,IF(A13<=12,Premissas!$B$31,Premissas!$B$32)))) | C13: =Premissas!B22*B13 | D13: =-C13*Premissas!$B$7 | E13: =-C13*Premissas!$B$8 | F13: =-C13*Premissas!$B$9 | G13: =-C13*Premissas!$B$10 | H13: =-Premissas!$B$11 | I13: =-Premissas!B25 | J13: =SUM(C13:I13) | K13: =J13-C13*Premissas!$B$12 | L13: =L12+K13
A14: 10 | B14: =IF(A14<=3,Premissas!$B$28,IF(A14<=6,Premissas!$B$29,IF(A14<=9,Premissas!$B$30,IF(A14<=12,Premissas!$B$31,Premissas!$B$32)))) | C14: =Premissas!B22*B14 | D14: =-C14*Premissas!$B$7 | E14: =-C14*Premissas!$B$8 | F14: =-C14*Premissas!$B$9 | G14: =-C14*Premissas!$B$10 | H14: =-Premissas!$B$11 | I14: =-Premissas!B25 | J14: =SUM(C14:I14) | K14: =J14-C14*Premissas!$B$12 | L14: =L13+K14
A15: 11 | B15: =IF(A15<=3,Premissas!$B$28,IF(A15<=6,Premissas!$B$29,IF(A15<=9,Premissas!$B$30,IF(A15<=12,Premissas!$B$31,Premissas!$B$32)))) | C15: =Premissas!B22*B15 | D15: =-C15*Premissas!$B$7 | E15: =-C15*Premissas!$B$8 | F15: =-C15*Premissas!$B$9 | G15: =-C15*Premissas!$B$10 | H15: =-Premissas!$B$11 | I15: =-Premissas!B25 | J15: =SUM(C15:I15) | K15: =J15-C15*Premissas!$B$12 | L15: =L14+K15
A16: 12 | B16: =IF(A16<=3,Premissas!$B$28,IF(A16<=6,Premissas!$B$29,IF(A16<=9,Premissas!$B$30,IF(A16<=12,Premissas!$B$31,Premissas!$B$32)))) | C16: =Premissas!B22*B16 | D16: =-C16*Premissas!$B$7 | E16: =-C16*Premissas!$B$8 | F16: =-C16*Premissas!$B$9 | G16: =-C16*Premissas!$B$10 | H16: =-Premissas!$B$11 | I16: =-Premissas!B25 | J16: =SUM(C16:I16) | K16: =J16-C16*Premissas!$B$12 | L16: =L15+K16
A17: 13 | B17: =IF(A17<=3,Premissas!$B$28,IF(A17<=6,Premissas!$B$29,IF(A17<=9,Premissas!$B$30,IF(A17<=12,Premissas!$B$31,Premissas!$B$32)))) | C17: =Premissas!B22*B17 | D17: =-C17*Premissas!$B$7 | E17: =-C17*Premissas!$B$8 | F17: =-C17*Premissas!$B$9 | G17: =-C17*Premissas!$B$10 | H17: =-Premissas!$B$11 | I17: =-Premissas!B25 | J17: =SUM(C17:I17) | K17: =J17-C17*Premissas!$B$12 | L17: =L16+K17
A18: 14 | B18: =IF(A18<=3,Premissas!$B$28,IF(A18<=6,Premissas!$B$29,IF(A18<=9,Premissas!$B$30,IF(A18<=12,Premissas!$B$31,Premissas!$B$32)))) | C18: =Premissas!B22*B18 | D18: =-C18*Premissas!$B$7 | E18: =-C18*Premissas!$B$8 | F18: =-C18*Premissas!$B$9 | G18: =-C18*Premissas!$B$10 | H18: =-Premissas!$B$11 | I18: =-Premissas!B25 | J18: =SUM(C18:I18) | K18: =J18-C18*Premissas!$B$12 | L18: =L17+K18
A19: 15 | B19: =IF(A19<=3,Premissas!$B$28,IF(A19<=6,Premissas!$B$29,IF(A19<=9,Premissas!$B$30,IF(A19<=12,Premissas!$B$31,Premissas!$B$32)))) | C19: =Premissas!B22*B19 | D19: =-C19*Premissas!$B$7 | E19: =-C19*Premissas!$B$8 | F19: =-C19*Premissas!$B$9 | G19: =-C19*Premissas!$B$10 | H19: =-Premissas!$B$11 | I19: =-Premissas!B25 | J19: =SUM(C19:I19) | K19: =J19-C19*Premissas!$B$12 | L19: =L18+K19
A20: 16 | B20: =IF(A20<=3,Premissas!$B$28,IF(A20<=6,Premissas!$B$29,IF(A20<=9,Premissas!$B$30,IF(A20<=12,Premissas!$B$31,Premissas!$B$32)))) | C20: =Premissas!B22*B20 | D20: =-C20*Premissas!$B$7 | E20: =-C20*Premissas!$B$8 | F20: =-C20*Premissas!$B$9 | G20: =-C20*Premissas!$B$10 | H20: =-Premissas!$B$11 | I20: =-Premissas!B25 | J20: =SUM(C20:I20) | K20: =J20-C20*Premissas!$B$12 | L20: =L19+K20
A21: 17 | B21: =IF(A21<=3,Premissas!$B$28,IF(A21<=6,Premissas!$B$29,IF(A21<=9,Premissas!$B$30,IF(A21<=12,Premissas!$B$31,Premissas!$B$32)))) | C21: =Premissas!B22*B21 | D21: =-C21*Premissas!$B$7 | E21: =-C21*Premissas!$B$8 | F21: =-C21*Premissas!$B$9 | G21: =-C21*Premissas!$B$10 | H21: =-Premissas!$B$11 | I21: =-Premissas!B25 | J21: =SUM(C21:I21) | K21: =J21-C21*Premissas!$B$12 | L21: =L20+K21
A22: 18 | B22: =IF(A22<=3,Premissas!$B$28,IF(A22<=6,Premissas!$B$29,IF(A22<=9,Premissas!$B$30,IF(A22<=12,Premissas!$B$31,Premissas!$B$32)))) | C22: =Premissas!B22*B22 | D22: =-C22*Premissas!$B$7 | E22: =-C22*Premissas!$B$8 | F22: =-C22*Premissas!$B$9 | G22: =-C22*Premissas!$B$10 | H22: =-Premissas!$B$11 | I22: =-Premissas!B25 | J22: =SUM(C22:I22) | K22: =J22-C22*Premissas!$B$12 | L22: =L21+K22
A23: 19 | B23: =IF(A23<=3,Premissas!$B$28,IF(A23<=6,Premissas!$B$29,IF(A23<=9,Premissas!$B$30,IF(A23<=12,Premissas!$B$31,Premissas!$B$32)))) | C23: =Premissas!B22*B23 | D23: =-C23*Premissas!$B$7 | E23: =-C23*Premissas!$B$8 | F23: =-C23*Premissas!$B$9 | G23: =-C23*Premissas!$B$10 | H23: =-Premissas!$B$11 | I23: =-Premissas!B25 | J23: =SUM(C23:I23) | K23: =J23-C23*Premissas!$B$12 | L23: =L22+K23
A24: 20 | B24: =IF(A24<=3,Premissas!$B$28,IF(A24<=6,Premissas!$B$29,IF(A24<=9,Premissas!$B$30,IF(A24<=12,Premissas!$B$31,Premissas!$B$32)))) | C24: =Premissas!B22*B24 | D24: =-C24*Premissas!$B$7 | E24: =-C24*Premissas!$B$8 | F24: =-C24*Premissas!$B$9 | G24: =-C24*Premissas!$B$10 | H24: =-Premissas!$B$11 | I24: =-Premissas!B25 | J24: =SUM(C24:I24) | K24: =J24-C24*Premissas!$B$12 | L24: =L23+K24
A25: 21 | B25: =IF(A25<=3,Premissas!$B$28,IF(A25<=6,Premissas!$B$29,IF(A25<=9,Premissas!$B$30,IF(A25<=12,Premissas!$B$31,Premissas!$B$32)))) | C25: =Premissas!B22*B25 | D25: =-C25*Premissas!$B$7 | E25: =-C25*Premissas!$B$8 | F25: =-C25*Premissas!$B$9 | G25: =-C25*Premissas!$B$10 | H25: =-Premissas!$B$11 | I25: =-Premissas!B25 | J25: =SUM(C25:I25) | K25: =J25-C25*Premissas!$B$12 | L25: =L24+K25
A26: 22 | B26: =IF(A26<=3,Premissas!$B$28,IF(A26<=6,Premissas!$B$29,IF(A26<=9,Premissas!$B$30,IF(A26<=12,Premissas!$B$31,Premissas!$B$32)))) | C26: =Premissas!B22*B26 | D26: =-C26*Premissas!$B$7 | E26: =-C26*Premissas!$B$8 | F26: =-C26*Premissas!$B$9 | G26: =-C26*Premissas!$B$10 | H26: =-Premissas!$B$11 | I26: =-Premissas!B25 | J26: =SUM(C26:I26) | K26: =J26-C26*Premissas!$B$12 | L26: =L25+K26
A27: 23 | B27: =IF(A27<=3,Premissas!$B$28,IF(A27<=6,Premissas!$B$29,IF(A27<=9,Premissas!$B$30,IF(A27<=12,Premissas!$B$31,Premissas!$B$32)))) | C27: =Premissas!B22*B27 | D27: =-C27*Premissas!$B$7 | E27: =-C27*Premissas!$B$8 | F27: =-C27*Premissas!$B$9 | G27: =-C27*Premissas!$B$10 | H27: =-Premissas!$B$11 | I27: =-Premissas!B25 | J27: =SUM(C27:I27) | K27: =J27-C27*Premissas!$B$12 | L27: =L26+K27
A28: 24 | B28: =IF(A28<=3,Premissas!$B$28,IF(A28<=6,Premissas!$B$29,IF(A28<=9,Premissas!$B$30,IF(A28<=12,Premissas!$B$31,Premissas!$B$32)))) | C28: =Premissas!B22*B28 | D28: =-C28*Premissas!$B$7 | E28: =-C28*Premissas!$B$8 | F28: =-C28*Premissas!$B$9 | G28: =-C28*Premissas!$B$10 | H28: =-Premissas!$B$11 | I28: =-Premissas!B25 | J28: =SUM(C28:I28) | K28: =J28-C28*Premissas!$B$12 | L28: =L27+K28
A29: 25 | B29: =IF(A29<=3,Premissas!$B$28,IF(A29<=6,Premissas!$B$29,IF(A29<=9,Premissas!$B$30,IF(A29<=12,Premissas!$B$31,Premissas!$B$32)))) | C29: =Premissas!B22*B29 | D29: =-C29*Premissas!$B$7 | E29: =-C29*Premissas!$B$8 | F29: =-C29*Premissas!$B$9 | G29: =-C29*Premissas!$B$10 | H29: =-Premissas!$B$11 | I29: =-Premissas!B25 | J29: =SUM(C29:I29) | K29: =J29-C29*Premissas!$B$12 | L29: =L28+K29
A30: 26 | B30: =IF(A30<=3,Premissas!$B$28,IF(A30<=6,Premissas!$B$29,IF(A30<=9,Premissas!$B$30,IF(A30<=12,Premissas!$B$31,Premissas!$B$32)))) | C30: =Premissas!B22*B30 | D30: =-C30*Premissas!$B$7 | E30: =-C30*Premissas!$B$8 | F30: =-C30*Premissas!$B$9 | G30: =-C30*Premissas!$B$10 | H30: =-Premissas!$B$11 | I30: =-Premissas!B25 | J30: =SUM(C30:I30) | K30: =J30-C30*Premissas!$B$12 | L30: =L29+K30
A31: 27 | B31: =IF(A31<=3,Premissas!$B$28,IF(A31<=6,Premissas!$B$29,IF(A31<=9,Premissas!$B$30,IF(A31<=12,Premissas!$B$31,Premissas!$B$32)))) | C31: =Premissas!B22*B31 | D31: =-C31*Premissas!$B$7 | E31: =-C31*Premissas!$B$8 | F31: =-C31*Premissas!$B$9 | G31: =-C31*Premissas!$B$10 | H31: =-Premissas!$B$11 | I31: =-Premissas!B25 | J31: =SUM(C31:I31) | K31: =J31-C31*Premissas!$B$12 | L31: =L30+K31
A32: 28 | B32: =IF(A32<=3,Premissas!$B$28,IF(A32<=6,Premissas!$B$29,IF(A32<=9,Premissas!$B$30,IF(A32<=12,Premissas!$B$31,Premissas!$B$32)))) | C32: =Premissas!B22*B32 | D32: =-C32*Premissas!$B$7 | E32: =-C32*Premissas!$B$8 | F32: =-C32*Premissas!$B$9 | G32: =-C32*Premissas!$B$10 | H32: =-Premissas!$B$11 | I32: =-Premissas!B25 | J32: =SUM(C32:I32) | K32: =J32-C32*Premissas!$B$12 | L32: =L31+K32
A33: 29 | B33: =IF(A33<=3,Premissas!$B$28,IF(A33<=6,Premissas!$B$29,IF(A33<=9,Premissas!$B$30,IF(A33<=12,Premissas!$B$31,Premissas!$B$32)))) | C33: =Premissas!B22*B33 | D33: =-C33*Premissas!$B$7 | E33: =-C33*Premissas!$B$8 | F33: =-C33*Premissas!$B$9 | G33: =-C33*Premissas!$B$10 | H33: =-Premissas!$B$11 | I33: =-Premissas!B25 | J33: =SUM(C33:I33) | K33: =J33-C33*Premissas!$B$12 | L33: =L32+K33
A34: 30 | B34: =IF(A34<=3,Premissas!$B$28,IF(A34<=6,Premissas!$B$29,IF(A34<=9,Premissas!$B$30,IF(A34<=12,Premissas!$B$31,Premissas!$B$32)))) | C34: =Premissas!B22*B34 | D34: =-C34*Premissas!$B$7 | E34: =-C34*Premissas!$B$8 | F34: =-C34*Premissas!$B$9 | G34: =-C34*Premissas!$B$10 | H34: =-Premissas!$B$11 | I34: =-Premissas!B25 | J34: =SUM(C34:I34) | K34: =J34-C34*Premissas!$B$12 | L34: =L33+K34
A35: 31 | B35: =IF(A35<=3,Premissas!$B$28,IF(A35<=6,Premissas!$B$29,IF(A35<=9,Premissas!$B$30,IF(A35<=12,Premissas!$B$31,Premissas!$B$32)))) | C35: =Premissas!B22*B35 | D35: =-C35*Premissas!$B$7 | E35: =-C35*Premissas!$B$8 | F35: =-C35*Premissas!$B$9 | G35: =-C35*Premissas!$B$10 | H35: =-Premissas!$B$11 | I35: =-Premissas!B25 | J35: =SUM(C35:I35) | K35: =J35-C35*Premissas!$B$12 | L35: =L34+K35
A36: 32 | B36: =IF(A36<=3,Premissas!$B$28,IF(A36<=6,Premissas!$B$29,IF(A36<=9,Premissas!$B$30,IF(A36<=12,Premissas!$B$31,Premissas!$B$32)))) | C36: =Premissas!B22*B36 | D36: =-C36*Premissas!$B$7 | E36: =-C36*Premissas!$B$8 | F36: =-C36*Premissas!$B$9 | G36: =-C36*Premissas!$B$10 | H36: =-Premissas!$B$11 | I36: =-Premissas!B25 | J36: =SUM(C36:I36) | K36: =J36-C36*Premissas!$B$12 | L36: =L35+K36
A37: 33 | B37: =IF(A37<=3,Premissas!$B$28,IF(A37<=6,Premissas!$B$29,IF(A37<=9,Premissas!$B$30,IF(A37<=12,Premissas!$B$31,Premissas!$B$32)))) | C37: =Premissas!B22*B37 | D37: =-C37*Premissas!$B$7 | E37: =-C37*Premissas!$B$8 | F37: =-C37*Premissas!$B$9 | G37: =-C37*Premissas!$B$10 | H37: =-Premissas!$B$11 | I37: =-Premissas!B25 | J37: =SUM(C37:I37) | K37: =J37-C37*Premissas!$B$12 | L37: =L36+K37
A38: 34 | B38: =IF(A38<=3,Premissas!$B$28,IF(A38<=6,Premissas!$B$29,IF(A38<=9,Premissas!$B$30,IF(A38<=12,Premissas!$B$31,Premissas!$B$32)))) | C38: =Premissas!B22*B38 | D38: =-C38*Premissas!$B$7 | E38: =-C38*Premissas!$B$8 | F38: =-C38*Premissas!$B$9 | G38: =-C38*Premissas!$B$10 | H38: =-Premissas!$B$11 | I38: =-Premissas!B25 | J38: =SUM(C38:I38) | K38: =J38-C38*Premissas!$B$12 | L38: =L37+K38
A39: 35 | B39: =IF(A39<=3,Premissas!$B$28,IF(A39<=6,Premissas!$B$29,IF(A39<=9,Premissas!$B$30,IF(A39<=12,Premissas!$B$31,Premissas!$B$32)))) | C39: =Premissas!B22*B39 | D39: =-C39*Premissas!$B$7 | E39: =-C39*Premissas!$B$8 | F39: =-C39*Premissas!$B$9 | G39: =-C39*Premissas!$B$10 | H39: =-Premissas!$B$11 | I39: =-Premissas!B25 | J39: =SUM(C39:I39) | K39: =J39-C39*Premissas!$B$12 | L39: =L38+K39
A40: 36 | B40: =IF(A40<=3,Premissas!$B$28,IF(A40<=6,Premissas!$B$29,IF(A40<=9,Premissas!$B$30,IF(A40<=12,Premissas!$B$31,Premissas!$B$32)))) | C40: =Premissas!B22*B40 | D40: =-C40*Premissas!$B$7 | E40: =-C40*Premissas!$B$8 | F40: =-C40*Premissas!$B$9 | G40: =-C40*Premissas!$B$10 | H40: =-Premissas!$B$11 | I40: =-Premissas!B25 | J40: =SUM(C40:I40) | K40: =J40-C40*Premissas!$B$12 | L40: =L39+K40
A41: 37 | B41: =IF(A41<=3,Premissas!$B$28,IF(A41<=6,Premissas!$B$29,IF(A41<=9,Premissas!$B$30,IF(A41<=12,Premissas!$B$31,Premissas!$B$32)))) | C41: =Premissas!B22*B41 | D41: =-C41*Premissas!$B$7 | E41: =-C41*Premissas!$B$8 | F41: =-C41*Premissas!$B$9 | G41: =-C41*Premissas!$B$10 | H41: =-Premissas!$B$11 | I41: =-Premissas!B25 | J41: =SUM(C41:I41) | K41: =J41-C41*Premissas!$B$12 | L41: =L40+K41
A42: 38 | B42: =IF(A42<=3,Premissas!$B$28,IF(A42<=6,Premissas!$B$29,IF(A42<=9,Premissas!$B$30,IF(A42<=12,Premissas!$B$31,Premissas!$B$32)))) | C42: =Premissas!B22*B42 | D42: =-C42*Premissas!$B$7 | E42: =-C42*Premissas!$B$8 | F42: =-C42*Premissas!$B$9 | G42: =-C42*Premissas!$B$10 | H42: =-Premissas!$B$11 | I42: =-Premissas!B25 | J42: =SUM(C42:I42) | K42: =J42-C42*Premissas!$B$12 | L42: =L41+K42
A43: 39 | B43: =IF(A43<=3,Premissas!$B$28,IF(A43<=6,Premissas!$B$29,IF(A43<=9,Premissas!$B$30,IF(A43<=12,Premissas!$B$31,Premissas!$B$32)))) | C43: =Premissas!B22*B43 | D43: =-C43*Premissas!$B$7 | E43: =-C43*Premissas!$B$8 | F43: =-C43*Premissas!$B$9 | G43: =-C43*Premissas!$B$10 | H43: =-Premissas!$B$11 | I43: =-Premissas!B25 | J43: =SUM(C43:I43) | K43: =J43-C43*Premissas!$B$12 | L43: =L42+K43
A44: 40 | B44: =IF(A44<=3,Premissas!$B$28,IF(A44<=6,Premissas!$B$29,IF(A44<=9,Premissas!$B$30,IF(A44<=12,Premissas!$B$31,Premissas!$B$32)))) | C44: =Premissas!B22*B44 | D44: =-C44*Premissas!$B$7 | E44: =-C44*Premissas!$B$8 | F44: =-C44*Premissas!$B$9 | G44: =-C44*Premissas!$B$10 | H44: =-Premissas!$B$11 | I44: =-Premissas!B25 | J44: =SUM(C44:I44) | K44: =J44-C44*Premissas!$B$12 | L44: =L43+K44
A45: 41 | B45: =IF(A45<=3,Premissas!$B$28,IF(A45<=6,Premissas!$B$29,IF(A45<=9,Premissas!$B$30,IF(A45<=12,Premissas!$B$31,Premissas!$B$32)))) | C45: =Premissas!B22*B45 | D45: =-C45*Premissas!$B$7 | E45: =-C45*Premissas!$B$8 | F45: =-C45*Premissas!$B$9 | G45: =-C45*Premissas!$B$10 | H45: =-Premissas!$B$11 | I45: =-Premissas!B25 | J45: =SUM(C45:I45) | K45: =J45-C45*Premissas!$B$12 | L45: =L44+K45
A46: 42 | B46: =IF(A46<=3,Premissas!$B$28,IF(A46<=6,Premissas!$B$29,IF(A46<=9,Premissas!$B$30,IF(A46<=12,Premissas!$B$31,Premissas!$B$32)))) | C46: =Premissas!B22*B46 | D46: =-C46*Premissas!$B$7 | E46: =-C46*Premissas!$B$8 | F46: =-C46*Premissas!$B$9 | G46: =-C46*Premissas!$B$10 | H46: =-Premissas!$B$11 | I46: =-Premissas!B25 | J46: =SUM(C46:I46) | K46: =J46-C46*Premissas!$B$12 | L46: =L45+K46
A47: 43 | B47: =IF(A47<=3,Premissas!$B$28,IF(A47<=6,Premissas!$B$29,IF(A47<=9,Premissas!$B$30,IF(A47<=12,Premissas!$B$31,Premissas!$B$32)))) | C47: =Premissas!B22*B47 | D47: =-C47*Premissas!$B$7 | E47: =-C47*Premissas!$B$8 | F47: =-C47*Premissas!$B$9 | G47: =-C47*Premissas!$B$10 | H47: =-Premissas!$B$11 | I47: =-Premissas!B25 | J47: =SUM(C47:I47) | K47: =J47-C47*Premissas!$B$12 | L47: =L46+K47
A48: 44 | B48: =IF(A48<=3,Premissas!$B$28,IF(A48<=6,Premissas!$B$29,IF(A48<=9,Premissas!$B$30,IF(A48<=12,Premissas!$B$31,Premissas!$B$32)))) | C48: =Premissas!B22*B48 | D48: =-C48*Premissas!$B$7 | E48: =-C48*Premissas!$B$8 | F48: =-C48*Premissas!$B$9 | G48: =-C48*Premissas!$B$10 | H48: =-Premissas!$B$11 | I48: =-Premissas!B25 | J48: =SUM(C48:I48) | K48: =J48-C48*Premissas!$B$12 | L48: =L47+K48
A49: 45 | B49: =IF(A49<=3,Premissas!$B$28,IF(A49<=6,Premissas!$B$29,IF(A49<=9,Premissas!$B$30,IF(A49<=12,Premissas!$B$31,Premissas!$B$32)))) | C49: =Premissas!B22*B49 | D49: =-C49*Premissas!$B$7 | E49: =-C49*Premissas!$B$8 | F49: =-C49*Premissas!$B$9 | G49: =-C49*Premissas!$B$10 | H49: =-Premissas!$B$11 | I49: =-Premissas!B25 | J49: =SUM(C49:I49) | K49: =J49-C49*Premissas!$B$12 | L49: =L48+K49
A50: 46 | B50: =IF(A50<=3,Premissas!$B$28,IF(A50<=6,Premissas!$B$29,IF(A50<=9,Premissas!$B$30,IF(A50<=12,Premissas!$B$31,Premissas!$B$32)))) | C50: =Premissas!B22*B50 | D50: =-C50*Premissas!$B$7 | E50: =-C50*Premissas!$B$8 | F50: =-C50*Premissas!$B$9 | G50: =-C50*Premissas!$B$10 | H50: =-Premissas!$B$11 | I50: =-Premissas!B25 | J50: =SUM(C50:I50) | K50: =J50-C50*Premissas!$B$12 | L50: =L49+K50
A51: 47 | B51: =IF(A51<=3,Premissas!$B$28,IF(A51<=6,Premissas!$B$29,IF(A51<=9,Premissas!$B$30,IF(A51<=12,Premissas!$B$31,Premissas!$B$32)))) | C51: =Premissas!B22*B51 | D51: =-C51*Premissas!$B$7 | E51: =-C51*Premissas!$B$8 | F51: =-C51*Premissas!$B$9 | G51: =-C51*Premissas!$B$10 | H51: =-Premissas!$B$11 | I51: =-Premissas!B25 | J51: =SUM(C51:I51) | K51: =J51-C51*Premissas!$B$12 | L51: =L50+K51
A52: 48 | B52: =IF(A52<=3,Premissas!$B$28,IF(A52<=6,Premissas!$B$29,IF(A52<=9,Premissas!$B$30,IF(A52<=12,Premissas!$B$31,Premissas!$B$32)))) | C52: =Premissas!B22*B52 | D52: =-C52*Premissas!$B$7 | E52: =-C52*Premissas!$B$8 | F52: =-C52*Premissas!$B$9 | G52: =-C52*Premissas!$B$10 | H52: =-Premissas!$B$11 | I52: =-Premissas!B25 | J52: =SUM(C52:I52) | K52: =J52-C52*Premissas!$B$12 | L52: =L51+K52
A53: 49 | B53: =IF(A53<=3,Premissas!$B$28,IF(A53<=6,Premissas!$B$29,IF(A53<=9,Premissas!$B$30,IF(A53<=12,Premissas!$B$31,Premissas!$B$32)))) | C53: =Premissas!B22*B53 | D53: =-C53*Premissas!$B$7 | E53: =-C53*Premissas!$B$8 | F53: =-C53*Premissas!$B$9 | G53: =-C53*Premissas!$B$10 | H53: =-Premissas!$B$11 | I53: =-Premissas!B25 | J53: =SUM(C53:I53) | K53: =J53-C53*Premissas!$B$12 | L53: =L52+K53
A54: 50 | B54: =IF(A54<=3,Premissas!$B$28,IF(A54<=6,Premissas!$B$29,IF(A54<=9,Premissas!$B$30,IF(A54<=12,Premissas!$B$31,Premissas!$B$32)))) | C54: =Premissas!B22*B54 | D54: =-C54*Premissas!$B$7 | E54: =-C54*Premissas!$B$8 | F54: =-C54*Premissas!$B$9 | G54: =-C54*Premissas!$B$10 | H54: =-Premissas!$B$11 | I54: =-Premissas!B25 | J54: =SUM(C54:I54) | K54: =J54-C54*Premissas!$B$12 | L54: =L53+K54
A55: 51 | B55: =IF(A55<=3,Premissas!$B$28,IF(A55<=6,Premissas!$B$29,IF(A55<=9,Premissas!$B$30,IF(A55<=12,Premissas!$B$31,Premissas!$B$32)))) | C55: =Premissas!B22*B55 | D55: =-C55*Premissas!$B$7 | E55: =-C55*Premissas!$B$8 | F55: =-C55*Premissas!$B$9 | G55: =-C55*Premissas!$B$10 | H55: =-Premissas!$B$11 | I55: =-Premissas!B25 | J55: =SUM(C55:I55) | K55: =J55-C55*Premissas!$B$12 | L55: =L54+K55
A56: 52 | B56: =IF(A56<=3,Premissas!$B$28,IF(A56<=6,Premissas!$B$29,IF(A56<=9,Premissas!$B$30,IF(A56<=12,Premissas!$B$31,Premissas!$B$32)))) | C56: =Premissas!B22*B56 | D56: =-C56*Premissas!$B$7 | E56: =-C56*Premissas!$B$8 | F56: =-C56*Premissas!$B$9 | G56: =-C56*Premissas!$B$10 | H56: =-Premissas!$B$11 | I56: =-Premissas!B25 | J56: =SUM(C56:I56) | K56: =J56-C56*Premissas!$B$12 | L56: =L55+K56
A57: 53 | B57: =IF(A57<=3,Premissas!$B$28,IF(A57<=6,Premissas!$B$29,IF(A57<=9,Premissas!$B$30,IF(A57<=12,Premissas!$B$31,Premissas!$B$32)))) | C57: =Premissas!B22*B57 | D57: =-C57*Premissas!$B$7 | E57: =-C57*Premissas!$B$8 | F57: =-C57*Premissas!$B$9 | G57: =-C57*Premissas!$B$10 | H57: =-Premissas!$B$11 | I57: =-Premissas!B25 | J57: =SUM(C57:I57) | K57: =J57-C57*Premissas!$B$12 | L57: =L56+K57
A58: 54 | B58: =IF(A58<=3,Premissas!$B$28,IF(A58<=6,Premissas!$B$29,IF(A58<=9,Premissas!$B$30,IF(A58<=12,Premissas!$B$31,Premissas!$B$32)))) | C58: =Premissas!B22*B58 | D58: =-C58*Premissas!$B$7 | E58: =-C58*Premissas!$B$8 | F58: =-C58*Premissas!$B$9 | G58: =-C58*Premissas!$B$10 | H58: =-Premissas!$B$11 | I58: =-Premissas!B25 | J58: =SUM(C58:I58) | K58: =J58-C58*Premissas!$B$12 | L58: =L57+K58
A59: 55 | B59: =IF(A59<=3,Premissas!$B$28,IF(A59<=6,Premissas!$B$29,IF(A59<=9,Premissas!$B$30,IF(A59<=12,Premissas!$B$31,Premissas!$B$32)))) | C59: =Premissas!B22*B59 | D59: =-C59*Premissas!$B$7 | E59: =-C59*Premissas!$B$8 | F59: =-C59*Premissas!$B$9 | G59: =-C59*Premissas!$B$10 | H59: =-Premissas!$B$11 | I59: =-Premissas!B25 | J59: =SUM(C59:I59) | K59: =J59-C59*Premissas!$B$12 | L59: =L58+K59
A60: 56 | B60: =IF(A60<=3,Premissas!$B$28,IF(A60<=6,Premissas!$B$29,IF(A60<=9,Premissas!$B$30,IF(A60<=12,Premissas!$B$31,Premissas!$B$32)))) | C60: =Premissas!B22*B60 | D60: =-C60*Premissas!$B$7 | E60: =-C60*Premissas!$B$8 | F60: =-C60*Premissas!$B$9 | G60: =-C60*Premissas!$B$10 | H60: =-Premissas!$B$11 | I60: =-Premissas!B25 | J60: =SUM(C60:I60) | K60: =J60-C60*Premissas!$B$12 | L60: =L59+K60
A61: 57 | B61: =IF(A61<=3,Premissas!$B$28,IF(A61<=6,Premissas!$B$29,IF(A61<=9,Premissas!$B$30,IF(A61<=12,Premissas!$B$31,Premissas!$B$32)))) | C61: =Premissas!B22*B61 | D61: =-C61*Premissas!$B$7 | E61: =-C61*Premissas!$B$8 | F61: =-C61*Premissas!$B$9 | G61: =-C61*Premissas!$B$10 | H61: =-Premissas!$B$11 | I61: =-Premissas!B25 | J61: =SUM(C61:I61) | K61: =J61-C61*Premissas!$B$12 | L61: =L60+K61
A62: 58 | B62: =IF(A62<=3,Premissas!$B$28,IF(A62<=6,Premissas!$B$29,IF(A62<=9,Premissas!$B$30,IF(A62<=12,Premissas!$B$31,Premissas!$B$32)))) | C62: =Premissas!B22*B62 | D62: =-C62*Premissas!$B$7 | E62: =-C62*Premissas!$B$8 | F62: =-C62*Premissas!$B$9 | G62: =-C62*Premissas!$B$10 | H62: =-Premissas!$B$11 | I62: =-Premissas!B25 | J62: =SUM(C62:I62) | K62: =J62-C62*Premissas!$B$12 | L62: =L61+K62
A63: 59 | B63: =IF(A63<=3,Premissas!$B$28,IF(A63<=6,Premissas!$B$29,IF(A63<=9,Premissas!$B$30,IF(A63<=12,Premissas!$B$31,Premissas!$B$32)))) | C63: =Premissas!B22*B63 | D63: =-C63*Premissas!$B$7 | E63: =-C63*Premissas!$B$8 | F63: =-C63*Premissas!$B$9 | G63: =-C63*Premissas!$B$10 | H63: =-Premissas!$B$11 | I63: =-Premissas!B25 | J63: =SUM(C63:I63) | K63: =J63-C63*Premissas!$B$12 | L63: =L62+K63
A64: 60 | B64: =IF(A64<=3,Premissas!$B$28,IF(A64<=6,Premissas!$B$29,IF(A64<=9,Premissas!$B$30,IF(A64<=12,Premissas!$B$31,Premissas!$B$32)))) | C64: =Premissas!B22*B64 | D64: =-C64*Premissas!$B$7 | E64: =-C64*Premissas!$B$8 | F64: =-C64*Premissas!$B$9 | G64: =-C64*Premissas!$B$10 | H64: =-Premissas!$B$11 | I64: =-Premissas!B25 | J64: =SUM(C64:I64) | K64: =J64-C64*Premissas!$B$12+Premissas!B20*Premissas!$B$13 | L64: =L63+K64
A70: RESULTADO
A71: Investimento total | B71: =Premissas!B24
A72: EBITDA maduro (mês 60) | B72: =J64
A73: Margem EBITDA madura | B73: =J64/C64
A74: Payback (meses) | B74: =MATCH(TRUE,INDEX(L5:L64>=0,0),0)
A75: TIR mensal | B75: =IRR(K4:K64)
A76: TIR anual | B76: =(1+B74)^12-1
A77: VPL @ TMA | B77: =NPV((1+Premissas!$B$6)^(1/12)-1,K5:K64)+K4
A78: ROI 5 anos (caixa/investimento) | B78: =SUM(K5:K64)/B71

Sheet Express
A1: UNIDADE EXPRESS — FLUXO MENSAL (60 MESES)
A3: Mês | B3: % rampa | C3: Receita | D3: Impostos | E3: Variáveis | F3: Royalty | G3: Fundo | H3: Tecnologia | I3: Fixos | J3: EBITDA | K3: Fluxo livre | L3: Acumulado
A4: 0 | K4: =-Premissas!C24 | L4: =-Premissas!C24
A5: 1 | B5: =IF(A5<=3,Premissas!$B$28,IF(A5<=6,Premissas!$B$29,IF(A5<=9,Premissas!$B$30,IF(A5<=12,Premissas!$B$31,Premissas!$B$32)))) | C5: =Premissas!C22*B5 | D5: =-C5*Premissas!$B$7 | E5: =-C5*Premissas!$B$8 | F5: =-C5*Premissas!$B$9 | G5: =-C5*Premissas!$B$10 | H5: =-Premissas!$B$11 | I5: =-Premissas!C25 | J5: =SUM(C5:I5) | K5: =J5-C5*Premissas!$B$12 | L5: =L4+K5
A6: 2 | B6: =IF(A6<=3,Premissas!$B$28,IF(A6<=6,Premissas!$B$29,IF(A6<=9,Premissas!$B$30,IF(A6<=12,Premissas!$B$31,Premissas!$B$32)))) | C6: =Premissas!C22*B6 | D6: =-C6*Premissas!$B$7 | E6: =-C6*Premissas!$B$8 | F6: =-C6*Premissas!$B$9 | G6: =-C6*Premissas!$B$10 | H6: =-Premissas!$B$11 | I6: =-Premissas!C25 | J6: =SUM(C6:I6) | K6: =J6-C6*Premissas!$B$12 | L6: =L5+K6
A7: 3 | B7: =IF(A7<=3,Premissas!$B$28,IF(A7<=6,Premissas!$B$29,IF(A7<=9,Premissas!$B$30,IF(A7<=12,Premissas!$B$31,Premissas!$B$32)))) | C7: =Premissas!C22*B7 | D7: =-C7*Premissas!$B$7 | E7: =-C7*Premissas!$B$8 | F7: =-C7*Premissas!$B$9 | G7: =-C7*Premissas!$B$10 | H7: =-Premissas!$B$11 | I7: =-Premissas!C25 | J7: =SUM(C7:I7) | K7: =J7-C7*Premissas!$B$12 | L7: =L6+K7
A8: 4 | B8: =IF(A8<=3,Premissas!$B$28,IF(A8<=6,Premissas!$B$29,IF(A8<=9,Premissas!$B$30,IF(A8<=12,Premissas!$B$31,Premissas!$B$32)))) | C8: =Premissas!C22*B8 | D8: =-C8*Premissas!$B$7 | E8: =-C8*Premissas!$B$8 | F8: =-C8*Premissas!$B$9 | G8: =-C8*Premissas!$B$10 | H8: =-Premissas!$B$11 | I8: =-Premissas!C25 | J8: =SUM(C8:I8) | K8: =J8-C8*Premissas!$B$12 | L8: =L7+K8
A9: 5 | B9: =IF(A9<=3,Premissas!$B$28,IF(A9<=6,Premissas!$B$29,IF(A9<=9,Premissas!$B$30,IF(A9<=12,Premissas!$B$31,Premissas!$B$32)))) | C9: =Premissas!C22*B9 | D9: =-C9*Premissas!$B$7 | E9: =-C9*Premissas!$B$8 | F9: =-C9*Premissas!$B$9 | G9: =-C9*Premissas!$B$10 | H9: =-Premissas!$B$11 | I9: =-Premissas!C25 | J9: =SUM(C9:I9) | K9: =J9-C9*Premissas!$B$12 | L9: =L8+K9
A10: 6 | B10: =IF(A10<=3,Premissas!$B$28,IF(A10<=6,Premissas!$B$29,IF(A10<=9,Premissas!$B$30,IF(A10<=12,Premissas!$B$31,Premissas!$B$32)))) | C10: =Premissas!C22*B10 | D10: =-C10*Premissas!$B$7 | E10: =-C10*Premissas!$B$8 | F10: =-C10*Premissas!$B$9 | G10: =-C10*Premissas!$B$10 | H10: =-Premissas!$B$11 | I10: =-Premissas!C25 | J10: =SUM(C10:I10) | K10: =J10-C10*Premissas!$B$12 | L10: =L9+K10
A11: 7 | B11: =IF(A11<=3,Premissas!$B$28,IF(A11<=6,Premissas!$B$29,IF(A11<=9,Premissas!$B$30,IF(A11<=12,Premissas!$B$31,Premissas!$B$32)))) | C11: =Premissas!C22*B11 | D11: =-C11*Premissas!$B$7 | E11: =-C11*Premissas!$B$8 | F11: =-C11*Premissas!$B$9 | G11: =-C11*Premissas!$B$10 | H11: =-Premissas!$B$11 | I11: =-Premissas!C25 | J11: =SUM(C11:I11) | K11: =J11-C11*Premissas!$B$12 | L11: =L10+K11
A12: 8 | B12: =IF(A12<=3,Premissas!$B$28,IF(A12<=6,Premissas!$B$29,IF(A12<=9,Premissas!$B$30,IF(A12<=12,Premissas!$B$31,Premissas!$B$32)))) | C12: =Premissas!C22*B12 | D12: =-C12*Premissas!$B$7 | E12: =-C12*Premissas!$B$8 | F12: =-C12*Premissas!$B$9 | G12: =-C12*Premissas!$B$10 | H12: =-Premissas!$B$11 | I12: =-Premissas!C25 | J12: =SUM(C12:I12) | K12: =J12-C12*Premissas!$B$12 | L12: =L11+K12
A13: 9 | B13: =IF(A13<=3,Premissas!$B$28,IF(A13<=6,Premissas!$B$29,IF(A13<=9,Premissas!$B$30,IF(A13<=12,Premissas!$B$31,Premissas!$B$32)))) | C13: =Premissas!C22*B13 | D13: =-C13*Premissas!$B$7 | E13: =-C13*Premissas!$B$8 | F13: =-C13*Premissas!$B$9 | G13: =-C13*Premissas!$B$10 | H13: =-Premissas!$B$11 | I13: =-Premissas!C25 | J13: =SUM(C13:I13) | K13: =J13-C13*Premissas!$B$12 | L13: =L12+K13
A14: 10 | B14: =IF(A14<=3,Premissas!$B$28,IF(A14<=6,Premissas!$B$29,IF(A14<=9,Premissas!$B$30,IF(A14<=12,Premissas!$B$31,Premissas!$B$32)))) | C14: =Premissas!C22*B14 | D14: =-C14*Premissas!$B$7 | E14: =-C14*Premissas!$B$8 | F14: =-C14*Premissas!$B$9 | G14: =-C14*Premissas!$B$10 | H14: =-Premissas!$B$11 | I14: =-Premissas!C25 | J14: =SUM(C14:I14) | K14: =J14-C14*Premissas!$B$12 | L14: =L13+K14
A15: 11 | B15: =IF(A15<=3,Premissas!$B$28,IF(A15<=6,Premissas!$B$29,IF(A15<=9,Premissas!$B$30,IF(A15<=12,Premissas!$B$31,Premissas!$B$32)))) | C15: =Premissas!C22*B15 | D15: =-C15*Premissas!$B$7 | E15: =-C15*Premissas!$B$8 | F15: =-C15*Premissas!$B$9 | G15: =-C15*Premissas!$B$10 | H15: =-Premissas!$B$11 | I15: =-Premissas!C25 | J15: =SUM(C15:I15) | K15: =J15-C15*Premissas!$B$12 | L15: =L14+K15
A16: 12 | B16: =IF(A16<=3,Premissas!$B$28,IF(A16<=6,Premissas!$B$29,IF(A16<=9,Premissas!$B$30,IF(A16<=12,Premissas!$B$31,Premissas!$B$32)))) | C16: =Premissas!C22*B16 | D16: =-C16*Premissas!$B$7 | E16: =-C16*Premissas!$B$8 | F16: =-C16*Premissas!$B$9 | G16: =-C16*Premissas!$B$10 | H16: =-Premissas!$B$11 | I16: =-Premissas!C25 | J16: =SUM(C16:I16) | K16: =J16-C16*Premissas!$B$12 | L16: =L15+K16
A17: 13 | B17: =IF(A17<=3,Premissas!$B$28,IF(A17<=6,Premissas!$B$29,IF(A17<=9,Premissas!$B$30,IF(A17<=12,Premissas!$B$31,Premissas!$B$32)))) | C17: =Premissas!C22*B17 | D17: =-C17*Premissas!$B$7 | E17: =-C17*Premissas!$B$8 | F17: =-C17*Premissas!$B$9 | G17: =-C17*Premissas!$B$10 | H17: =-Premissas!$B$11 | I17: =-Premissas!C25 | J17: =SUM(C17:I17) | K17: =J17-C17*Premissas!$B$12 | L17: =L16+K17
A18: 14 | B18: =IF(A18<=3,Premissas!$B$28,IF(A18<=6,Premissas!$B$29,IF(A18<=9,Premissas!$B$30,IF(A18<=12,Premissas!$B$31,Premissas!$B$32)))) | C18: =Premissas!C22*B18 | D18: =-C18*Premissas!$B$7 | E18: =-C18*Premissas!$B$8 | F18: =-C18*Premissas!$B$9 | G18: =-C18*Premissas!$B$10 | H18: =-Premissas!$B$11 | I18: =-Premissas!C25 | J18: =SUM(C18:I18) | K18: =J18-C18*Premissas!$B$12 | L18: =L17+K18
A19: 15 | B19: =IF(A19<=3,Premissas!$B$28,IF(A19<=6,Premissas!$B$29,IF(A19<=9,Premissas!$B$30,IF(A19<=12,Premissas!$B$31,Premissas!$B$32)))) | C19: =Premissas!C22*B19 | D19: =-C19*Premissas!$B$7 | E19: =-C19*Premissas!$B$8 | F19: =-C19*Premissas!$B$9 | G19: =-C19*Premissas!$B$10 | H19: =-Premissas!$B$11 | I19: =-Premissas!C25 | J19: =SUM(C19:I19) | K19: =J19-C19*Premissas!$B$12 | L19: =L18+K19
A20: 16 | B20: =IF(A20<=3,Premissas!$B$28,IF(A20<=6,Premissas!$B$29,IF(A20<=9,Premissas!$B$30,IF(A20<=12,Premissas!$B$31,Premissas!$B$32)))) | C20: =Premissas!C22*B20 | D20: =-C20*Premissas!$B$7 | E20: =-C20*Premissas!$B$8 | F20: =-C20*Premissas!$B$9 | G20: =-C20*Premissas!$B$10 | H20: =-Premissas!$B$11 | I20: =-Premissas!C25 | J20: =SUM(C20:I20) | K20: =J20-C20*Premissas!$B$12 | L20: =L19+K20
A21: 17 | B21: =IF(A21<=3,Premissas!$B$28,IF(A21<=6,Premissas!$B$29,IF(A21<=9,Premissas!$B$30,IF(A21<=12,Premissas!$B$31,Premissas!$B$32)))) | C21: =Premissas!C22*B21 | D21: =-C21*Premissas!$B$7 | E21: =-C21*Premissas!$B$8 | F21: =-C21*Premissas!$B$9 | G21: =-C21*Premissas!$B$10 | H21: =-Premissas!$B$11 | I21: =-Premissas!C25 | J21: =SUM(C21:I21) | K21: =J21-C21*Premissas!$B$12 | L21: =L20+K21
A22: 18 | B22: =IF(A22<=3,Premissas!$B$28,IF(A22<=6,Premissas!$B$29,IF(A22<=9,Premissas!$B$30,IF(A22<=12,Premissas!$B$31,Premissas!$B$32)))) | C22: =Premissas!C22*B22 | D22: =-C22*Premissas!$B$7 | E22: =-C22*Premissas!$B$8 | F22: =-C22*Premissas!$B$9 | G22: =-C22*Premissas!$B$10 | H22: =-Premissas!$B$11 | I22: =-Premissas!C25 | J22: =SUM(C22:I22) | K22: =J22-C22*Premissas!$B$12 | L22: =L21+K22
A23: 19 | B23: =IF(A23<=3,Premissas!$B$28,IF(A23<=6,Premissas!$B$29,IF(A23<=9,Premissas!$B$30,IF(A23<=12,Premissas!$B$31,Premissas!$B$32)))) | C23: =Premissas!C22*B23 | D23: =-C23*Premissas!$B$7 | E23: =-C23*Premissas!$B$8 | F23: =-C23*Premissas!$B$9 | G23: =-C23*Premissas!$B$10 | H23: =-Premissas!$B$11 | I23: =-Premissas!C25 | J23: =SUM(C23:I23) | K23: =J23-C23*Premissas!$B$12 | L23: =L22+K23
A24: 20 | B24: =IF(A24<=3,Premissas!$B$28,IF(A24<=6,Premissas!$B$29,IF(A24<=9,Premissas!$B$30,IF(A24<=12,Premissas!$B$31,Premissas!$B$32)))) | C24: =Premissas!C22*B24 | D24: =-C24*Premissas!$B$7 | E24: =-C24*Premissas!$B$8 | F24: =-C24*Premissas!$B$9 | G24: =-C24*Premissas!$B$10 | H24: =-Premissas!$B$11 | I24: =-Premissas!C25 | J24: =SUM(C24:I24) | K24: =J24-C24*Premissas!$B$12 | L24: =L23+K24
A25: 21 | B25: =IF(A25<=3,Premissas!$B$28,IF(A25<=6,Premissas!$B$29,IF(A25<=9,Premissas!$B$30,IF(A25<=12,Premissas!$B$31,Premissas!$B$32)))) | C25: =Premissas!C22*B25 | D25: =-C25*Premissas!$B$7 | E25: =-C25*Premissas!$B$8 | F25: =-C25*Premissas!$B$9 | G25: =-C25*Premissas!$B$10 | H25: =-Premissas!$B$11 | I25: =-Premissas!C25 | J25: =SUM(C25:I25) | K25: =J25-C25*Premissas!$B$12 | L25: =L24+K25
A26: 22 | B26: =IF(A26<=3,Premissas!$B$28,IF(A26<=6,Premissas!$B$29,IF(A26<=9,Premissas!$B$30,IF(A26<=12,Premissas!$B$31,Premissas!$B$32)))) | C26: =Premissas!C22*B26 | D26: =-C26*Premissas!$B$7 | E26: =-C26*Premissas!$B$8 | F26: =-C26*Premissas!$B$9 | G26: =-C26*Premissas!$B$10 | H26: =-Premissas!$B$11 | I26: =-Premissas!C25 | J26: =SUM(C26:I26) | K26: =J26-C26*Premissas!$B$12 | L26: =L25+K26
A27: 23 | B27: =IF(A27<=3,Premissas!$B$28,IF(A27<=6,Premissas!$B$29,IF(A27<=9,Premissas!$B$30,IF(A27<=12,Premissas!$B$31,Premissas!$B$32)))) | C27: =Premissas!C22*B27 | D27: =-C27*Premissas!$B$7 | E27: =-C27*Premissas!$B$8 | F27: =-C27*Premissas!$B$9 | G27: =-C27*Premissas!$B$10 | H27: =-Premissas!$B$11 | I27: =-Premissas!C25 | J27: =SUM(C27:I27) | K27: =J27-C27*Premissas!$B$12 | L27: =L26+K27
A28: 24 | B28: =IF(A28<=3,Premissas!$B$28,IF(A28<=6,Premissas!$B$29,IF(A28<=9,Premissas!$B$30,IF(A28<=12,Premissas!$B$31,Premissas!$B$32)))) | C28: =Premissas!C22*B28 | D28: =-C28*Premissas!$B$7 | E28: =-C28*Premissas!$B$8 | F28: =-C28*Premissas!$B$9 | G28: =-C28*Premissas!$B$10 | H28: =-Premissas!$B$11 | I28: =-Premissas!C25 | J28: =SUM(C28:I28) | K28: =J28-C28*Premissas!$B$12 | L28: =L27+K28
A29: 25 | B29: =IF(A29<=3,Premissas!$B$28,IF(A29<=6,Premissas!$B$29,IF(A29<=9,Premissas!$B$30,IF(A29<=12,Premissas!$B$31,Premissas!$B$32)))) | C29: =Premissas!C22*B29 | D29: =-C29*Premissas!$B$7 | E29: =-C29*Premissas!$B$8 | F29: =-C29*Premissas!$B$9 | G29: =-C29*Premissas!$B$10 | H29: =-Premissas!$B$11 | I29: =-Premissas!C25 | J29: =SUM(C29:I29) | K29: =J29-C29*Premissas!$B$12 | L29: =L28+K29
A30: 26 | B30: =IF(A30<=3,Premissas!$B$28,IF(A30<=6,Premissas!$B$29,IF(A30<=9,Premissas!$B$30,IF(A30<=12,Premissas!$B$31,Premissas!$B$32)))) | C30: =Premissas!C22*B30 | D30: =-C30*Premissas!$B$7 | E30: =-C30*Premissas!$B$8 | F30: =-C30*Premissas!$B$9 | G30: =-C30*Premissas!$B$10 | H30: =-Premissas!$B$11 | I30: =-Premissas!C25 | J30: =SUM(C30:I30) | K30: =J30-C30*Premissas!$B$12 | L30: =L29+K30
A31: 27 | B31: =IF(A31<=3,Premissas!$B$28,IF(A31<=6,Premissas!$B$29,IF(A31<=9,Premissas!$B$30,IF(A31<=12,Premissas!$B$31,Premissas!$B$32)))) | C31: =Premissas!C22*B31 | D31: =-C31*Premissas!$B$7 | E31: =-C31*Premissas!$B$8 | F31: =-C31*Premissas!$B$9 | G31: =-C31*Premissas!$B$10 | H31: =-Premissas!$B$11 | I31: =-Premissas!C25 | J31: =SUM(C31:I31) | K31: =J31-C31*Premissas!$B$12 | L31: =L30+K31
A32: 28 | B32: =IF(A32<=3,Premissas!$B$28,IF(A32<=6,Premissas!$B$29,IF(A32<=9,Premissas!$B$30,IF(A32<=12,Premissas!$B$31,Premissas!$B$32)))) | C32: =Premissas!C22*B32 | D32: =-C32*Premissas!$B$7 | E32: =-C32*Premissas!$B$8 | F32: =-C32*Premissas!$B$9 | G32: =-C32*Premissas!$B$10 | H32: =-Premissas!$B$11 | I32: =-Premissas!C25 | J32: =SUM(C32:I32) | K32: =J32-C32*Premissas!$B$12 | L32: =L31+K32
A33: 29 | B33: =IF(A33<=3,Premissas!$B$28,IF(A33<=6,Premissas!$B$29,IF(A33<=9,Premissas!$B$30,IF(A33<=12,Premissas!$B$31,Premissas!$B$32)))) | C33: =Premissas!C22*B33 | D33: =-C33*Premissas!$B$7 | E33: =-C33*Premissas!$B$8 | F33: =-C33*Premissas!$B$9 | G33: =-C33*Premissas!$B$10 | H33: =-Premissas!$B$11 | I33: =-Premissas!C25 | J33: =SUM(C33:I33) | K33: =J33-C33*Premissas!$B$12 | L33: =L32+K33
A34: 30 | B34: =IF(A34<=3,Premissas!$B$28,IF(A34<=6,Premissas!$B$29,IF(A34<=9,Premissas!$B$30,IF(A34<=12,Premissas!$B$31,Premissas!$B$32)))) | C34: =Premissas!C22*B34 | D34: =-C34*Premissas!$B$7 | E34: =-C34*Premissas!$B$8 | F34: =-C34*Premissas!$B$9 | G34: =-C34*Premissas!$B$10 | H34: =-Premissas!$B$11 | I34: =-Premissas!C25 | J34: =SUM(C34:I34) | K34: =J34-C34*Premissas!$B$12 | L34: =L33+K34
A35: 31 | B35: =IF(A35<=3,Premissas!$B$28,IF(A35<=6,Premissas!$B$29,IF(A35<=9,Premissas!$B$30,IF(A35<=12,Premissas!$B$31,Premissas!$B$32)))) | C35: =Premissas!C22*B35 | D35: =-C35*Premissas!$B$7 | E35: =-C35*Premissas!$B$8 | F35: =-C35*Premissas!$B$9 | G35: =-C35*Premissas!$B$10 | H35: =-Premissas!$B$11 | I35: =-Premissas!C25 | J35: =SUM(C35:I35) | K35: =J35-C35*Premissas!$B$12 | L35: =L34+K35
A36: 32 | B36: =IF(A36<=3,Premissas!$B$28,IF(A36<=6,Premissas!$B$29,IF(A36<=9,Premissas!$B$30,IF(A36<=12,Premissas!$B$31,Premissas!$B$32)))) | C36: =Premissas!C22*B36 | D36: =-C36*Premissas!$B$7 | E36: =-C36*Premissas!$B$8 | F36: =-C36*Premissas!$B$9 | G36: =-C36*Premissas!$B$10 | H36: =-Premissas!$B$11 | I36: =-Premissas!C25 | J36: =SUM(C36:I36) | K36: =J36-C36*Premissas!$B$12 | L36: =L35+K36
A37: 33 | B37: =IF(A37<=3,Premissas!$B$28,IF(A37<=6,Premissas!$B$29,IF(A37<=9,Premissas!$B$30,IF(A37<=12,Premissas!$B$31,Premissas!$B$32)))) | C37: =Premissas!C22*B37 | D37: =-C37*Premissas!$B$7 | E37: =-C37*Premissas!$B$8 | F37: =-C37*Premissas!$B$9 | G37: =-C37*Premissas!$B$10 | H37: =-Premissas!$B$11 | I37: =-Premissas!C25 | J37: =SUM(C37:I37) | K37: =J37-C37*Premissas!$B$12 | L37: =L36+K37
A38: 34 | B38: =IF(A38<=3,Premissas!$B$28,IF(A38<=6,Premissas!$B$29,IF(A38<=9,Premissas!$B$30,IF(A38<=12,Premissas!$B$31,Premissas!$B$32)))) | C38: =Premissas!C22*B38 | D38: =-C38*Premissas!$B$7 | E38: =-C38*Premissas!$B$8 | F38: =-C38*Premissas!$B$9 | G38: =-C38*Premissas!$B$10 | H38: =-Premissas!$B$11 | I38: =-Premissas!C25 | J38: =SUM(C38:I38) | K38: =J38-C38*Premissas!$B$12 | L38: =L37+K38
A39: 35 | B39: =IF(A39<=3,Premissas!$B$28,IF(A39<=6,Premissas!$B$29,IF(A39<=9,Premissas!$B$30,IF(A39<=12,Premissas!$B$31,Premissas!$B$32)))) | C39: =Premissas!C22*B39 | D39: =-C39*Premissas!$B$7 | E39: =-C39*Premissas!$B$8 | F39: =-C39*Premissas!$B$9 | G39: =-C39*Premissas!$B$10 | H39: =-Premissas!$B$11 | I39: =-Premissas!C25 | J39: =SUM(C39:I39) | K39: =J39-C39*Premissas!$B$12 | L39: =L38+K39
A40: 36 | B40: =IF(A40<=3,Premissas!$B$28,IF(A40<=6,Premissas!$B$29,IF(A40<=9,Premissas!$B$30,IF(A40<=12,Premissas!$B$31,Premissas!$B$32)))) | C40: =Premissas!C22*B40 | D40: =-C40*Premissas!$B$7 | E40: =-C40*Premissas!$B$8 | F40: =-C40*Premissas!$B$9 | G40: =-C40*Premissas!$B$10 | H40: =-Premissas!$B$11 | I40: =-Premissas!C25 | J40: =SUM(C40:I40) | K40: =J40-C40*Premissas!$B$12 | L40: =L39+K40
A41: 37 | B41: =IF(A41<=3,Premissas!$B$28,IF(A41<=6,Premissas!$B$29,IF(A41<=9,Premissas!$B$30,IF(A41<=12,Premissas!$B$31,Premissas!$B$32)))) | C41: =Premissas!C22*B41 | D41: =-C41*Premissas!$B$7 | E41: =-C41*Premissas!$B$8 | F41: =-C41*Premissas!$B$9 | G41: =-C41*Premissas!$B$10 | H41: =-Premissas!$B$11 | I41: =-Premissas!C25 | J41: =SUM(C41:I41) | K41: =J41-C41*Premissas!$B$12 | L41: =L40+K41
A42: 38 | B42: =IF(A42<=3,Premissas!$B$28,IF(A42<=6,Premissas!$B$29,IF(A42<=9,Premissas!$B$30,IF(A42<=12,Premissas!$B$31,Premissas!$B$32)))) | C42: =Premissas!C22*B42 | D42: =-C42*Premissas!$B$7 | E42: =-C42*Premissas!$B$8 | F42: =-C42*Premissas!$B$9 | G42: =-C42*Premissas!$B$10 | H42: =-Premissas!$B$11 | I42: =-Premissas!C25 | J42: =SUM(C42:I42) | K42: =J42-C42*Premissas!$B$12 | L42: =L41+K42
A43: 39 | B43: =IF(A43<=3,Premissas!$B$28,IF(A43<=6,Premissas!$B$29,IF(A43<=9,Premissas!$B$30,IF(A43<=12,Premissas!$B$31,Premissas!$B$32)))) | C43: =Premissas!C22*B43 | D43: =-C43*Premissas!$B$7 | E43: =-C43*Premissas!$B$8 | F43: =-C43*Premissas!$B$9 | G43: =-C43*Premissas!$B$10 | H43: =-Premissas!$B$11 | I43: =-Premissas!C25 | J43: =SUM(C43:I43) | K43: =J43-C43*Premissas!$B$12 | L43: =L42+K43
A44: 40 | B44: =IF(A44<=3,Premissas!$B$28,IF(A44<=6,Premissas!$B$29,IF(A44<=9,Premissas!$B$30,IF(A44<=12,Premissas!$B$31,Premissas!$B$32)))) | C44: =Premissas!C22*B44 | D44: =-C44*Premissas!$B$7 | E44: =-C44*Premissas!$B$8 | F44: =-C44*Premissas!$B$9 | G44: =-C44*Premissas!$B$10 | H44: =-Premissas!$B$11 | I44: =-Premissas!C25 | J44: =SUM(C44:I44) | K44: =J44-C44*Premissas!$B$12 | L44: =L43+K44
A45: 41 | B45: =IF(A45<=3,Premissas!$B$28,IF(A45<=6,Premissas!$B$29,IF(A45<=9,Premissas!$B$30,IF(A45<=12,Premissas!$B$31,Premissas!$B$32)))) | C45: =Premissas!C22*B45 | D45: =-C45*Premissas!$B$7 | E45: =-C45*Premissas!$B$8 | F45: =-C45*Premissas!$B$9 | G45: =-C45*Premissas!$B$10 | H45: =-Premissas!$B$11 | I45: =-Premissas!C25 | J45: =SUM(C45:I45) | K45: =J45-C45*Premissas!$B$12 | L45: =L44+K45
A46: 42 | B46: =IF(A46<=3,Premissas!$B$28,IF(A46<=6,Premissas!$B$29,IF(A46<=9,Premissas!$B$30,IF(A46<=12,Premissas!$B$31,Premissas!$B$32)))) | C46: =Premissas!C22*B46 | D46: =-C46*Premissas!$B$7 | E46: =-C46*Premissas!$B$8 | F46: =-C46*Premissas!$B$9 | G46: =-C46*Premissas!$B$10 | H46: =-Premissas!$B$11 | I46: =-Premissas!C25 | J46: =SUM(C46:I46) | K46: =J46-C46*Premissas!$B$12 | L46: =L45+K46
A47: 43 | B47: =IF(A47<=3,Premissas!$B$28,IF(A47<=6,Premissas!$B$29,IF(A47<=9,Premissas!$B$30,IF(A47<=12,Premissas!$B$31,Premissas!$B$32)))) | C47: =Premissas!C22*B47 | D47: =-C47*Premissas!$B$7 | E47: =-C47*Premissas!$B$8 | F47: =-C47*Premissas!$B$9 | G47: =-C47*Premissas!$B$10 | H47: =-Premissas!$B$11 | I47: =-Premissas!C25 | J47: =SUM(C47:I47) | K47: =J47-C47*Premissas!$B$12 | L47: =L46+K47
A48: 44 | B48: =IF(A48<=3,Premissas!$B$28,IF(A48<=6,Premissas!$B$29,IF(A48<=9,Premissas!$B$30,IF(A48<=12,Premissas!$B$31,Premissas!$B$32)))) | C48: =Premissas!C22*B48 | D48: =-C48*Premissas!$B$7 | E48: =-C48*Premissas!$B$8 | F48: =-C48*Premissas!$B$9 | G48: =-C48*Premissas!$B$10 | H48: =-Premissas!$B$11 | I48: =-Premissas!C25 | J48: =SUM(C48:I48) | K48: =J48-C48*Premissas!$B$12 | L48: =L47+K48
A49: 45 | B49: =IF(A49<=3,Premissas!$B$28,IF(A49<=6,Premissas!$B$29,IF(A49<=9,Premissas!$B$30,IF(A49<=12,Premissas!$B$31,Premissas!$B$32)))) | C49: =Premissas!C22*B49 | D49: =-C49*Premissas!$B$7 | E49: =-C49*Premissas!$B$8 | F49: =-C49*Premissas!$B$9 | G49: =-C49*Premissas!$B$10 | H49: =-Premissas!$B$11 | I49: =-Premissas!C25 | J49: =SUM(C49:I49) | K49: =J49-C49*Premissas!$B$12 | L49: =L48+K49
A50: 46 | B50: =IF(A50<=3,Premissas!$B$28,IF(A50<=6,Premissas!$B$29,IF(A50<=9,Premissas!$B$30,IF(A50<=12,Premissas!$B$31,Premissas!$B$32)))) | C50: =Premissas!C22*B50 | D50: =-C50*Premissas!$B$7 | E50: =-C50*Premissas!$B$8 | F50: =-C50*Premissas!$B$9 | G50: =-C50*Premissas!$B$10 | H50: =-Premissas!$B$11 | I50: =-Premissas!C25 | J50: =SUM(C50:I50) | K50: =J50-C50*Premissas!$B$12 | L50: =L49+K50
A51: 47 | B51: =IF(A51<=3,Premissas!$B$28,IF(A51<=6,Premissas!$B$29,IF(A51<=9,Premissas!$B$30,IF(A51<=12,Premissas!$B$31,Premissas!$B$32)))) | C51: =Premissas!C22*B51 | D51: =-C51*Premissas!$B$7 | E51: =-C51*Premissas!$B$8 | F51: =-C51*Premissas!$B$9 | G51: =-C51*Premissas!$B$10 | H51: =-Premissas!$B$11 | I51: =-Premissas!C25 | J51: =SUM(C51:I51) | K51: =J51-C51*Premissas!$B$12 | L51: =L50+K51
A52: 48 | B52: =IF(A52<=3,Premissas!$B$28,IF(A52<=6,Premissas!$B$29,IF(A52<=9,Premissas!$B$30,IF(A52<=12,Premissas!$B$31,Premissas!$B$32)))) | C52: =Premissas!C22*B52 | D52: =-C52*Premissas!$B$7 | E52: =-C52*Premissas!$B$8 | F52: =-C52*Premissas!$B$9 | G52: =-C52*Premissas!$B$10 | H52: =-Premissas!$B$11 | I52: =-Premissas!C25 | J52: =SUM(C52:I52) | K52: =J52-C52*Premissas!$B$12 | L52: =L51+K52
A53: 49 | B53: =IF(A53<=3,Premissas!$B$28,IF(A53<=6,Premissas!$B$29,IF(A53<=9,Premissas!$B$30,IF(A53<=12,Premissas!$B$31,Premissas!$B$32)))) | C53: =Premissas!C22*B53 | D53: =-C53*Premissas!$B$7 | E53: =-C53*Premissas!$B$8 | F53: =-C53*Premissas!$B$9 | G53: =-C53*Premissas!$B$10 | H53: =-Premissas!$B$11 | I53: =-Premissas!C25 | J53: =SUM(C53:I53) | K53: =J53-C53*Premissas!$B$12 | L53: =L52+K53
A54: 50 | B54: =IF(A54<=3,Premissas!$B$28,IF(A54<=6,Premissas!$B$29,IF(A54<=9,Premissas!$B$30,IF(A54<=12,Premissas!$B$31,Premissas!$B$32)))) | C54: =Premissas!C22*B54 | D54: =-C54*Premissas!$B$7 | E54: =-C54*Premissas!$B$8 | F54: =-C54*Premissas!$B$9 | G54: =-C54*Premissas!$B$10 | H54: =-Premissas!$B$11 | I54: =-Premissas!C25 | J54: =SUM(C54:I54) | K54: =J54-C54*Premissas!$B$12 | L54: =L53+K54
A55: 51 | B55: =IF(A55<=3,Premissas!$B$28,IF(A55<=6,Premissas!$B$29,IF(A55<=9,Premissas!$B$30,IF(A55<=12,Premissas!$B$31,Premissas!$B$32)))) | C55: =Premissas!C22*B55 | D55: =-C55*Premissas!$B$7 | E55: =-C55*Premissas!$B$8 | F55: =-C55*Premissas!$B$9 | G55: =-C55*Premissas!$B$10 | H55: =-Premissas!$B$11 | I55: =-Premissas!C25 | J55: =SUM(C55:I55) | K55: =J55-C55*Premissas!$B$12 | L55: =L54+K55
A56: 52 | B56: =IF(A56<=3,Premissas!$B$28,IF(A56<=6,Premissas!$B$29,IF(A56<=9,Premissas!$B$30,IF(A56<=12,Premissas!$B$31,Premissas!$B$32)))) | C56: =Premissas!C22*B56 | D56: =-C56*Premissas!$B$7 | E56: =-C56*Premissas!$B$8 | F56: =-C56*Premissas!$B$9 | G56: =-C56*Premissas!$B$10 | H56: =-Premissas!$B$11 | I56: =-Premissas!C25 | J56: =SUM(C56:I56) | K56: =J56-C56*Premissas!$B$12 | L56: =L55+K56
A57: 53 | B57: =IF(A57<=3,Premissas!$B$28,IF(A57<=6,Premissas!$B$29,IF(A57<=9,Premissas!$B$30,IF(A57<=12,Premissas!$B$31,Premissas!$B$32)))) | C57: =Premissas!C22*B57 | D57: =-C57*Premissas!$B$7 | E57: =-C57*Premissas!$B$8 | F57: =-C57*Premissas!$B$9 | G57: =-C57*Premissas!$B$10 | H57: =-Premissas!$B$11 | I57: =-Premissas!C25 | J57: =SUM(C57:I57) | K57: =J57-C57*Premissas!$B$12 | L57: =L56+K57
A58: 54 | B58: =IF(A58<=3,Premissas!$B$28,IF(A58<=6,Premissas!$B$29,IF(A58<=9,Premissas!$B$30,IF(A58<=12,Premissas!$B$31,Premissas!$B$32)))) | C58: =Premissas!C22*B58 | D58: =-C58*Premissas!$B$7 | E58: =-C58*Premissas!$B$8 | F58: =-C58*Premissas!$B$9 | G58: =-C58*Premissas!$B$10 | H58: =-Premissas!$B$11 | I58: =-Premissas!C25 | J58: =SUM(C58:I58) | K58: =J58-C58*Premissas!$B$12 | L58: =L57+K58
A59: 55 | B59: =IF(A59<=3,Premissas!$B$28,IF(A59<=6,Premissas!$B$29,IF(A59<=9,Premissas!$B$30,IF(A59<=12,Premissas!$B$31,Premissas!$B$32)))) | C59: =Premissas!C22*B59 | D59: =-C59*Premissas!$B$7 | E59: =-C59*Premissas!$B$8 | F59: =-C59*Premissas!$B$9 | G59: =-C59*Premissas!$B$10 | H59: =-Premissas!$B$11 | I59: =-Premissas!C25 | J59: =SUM(C59:I59) | K59: =J59-C59*Premissas!$B$12 | L59: =L58+K59
A60: 56 | B60: =IF(A60<=3,Premissas!$B$28,IF(A60<=6,Premissas!$B$29,IF(A60<=9,Premissas!$B$30,IF(A60<=12,Premissas!$B$31,Premissas!$B$32)))) | C60: =Premissas!C22*B60 | D60: =-C60*Premissas!$B$7 | E60: =-C60*Premissas!$B$8 | F60: =-C60*Premissas!$B$9 | G60: =-C60*Premissas!$B$10 | H60: =-Premissas!$B$11 | I60: =-Premissas!C25 | J60: =SUM(C60:I60) | K60: =J60-C60*Premissas!$B$12 | L60: =L59+K60
A61: 57 | B61: =IF(A61<=3,Premissas!$B$28,IF(A61<=6,Premissas!$B$29,IF(A61<=9,Premissas!$B$30,IF(A61<=12,Premissas!$B$31,Premissas!$B$32)))) | C61: =Premissas!C22*B61 | D61: =-C61*Premissas!$B$7 | E61: =-C61*Premissas!$B$8 | F61: =-C61*Premissas!$B$9 | G61: =-C61*Premissas!$B$10 | H61: =-Premissas!$B$11 | I61: =-Premissas!C25 | J61: =SUM(C61:I61) | K61: =J61-C61*Premissas!$B$12 | L61: =L60+K61
A62: 58 | B62: =IF(A62<=3,Premissas!$B$28,IF(A62<=6,Premissas!$B$29,IF(A62<=9,Premissas!$B$30,IF(A62<=12,Premissas!$B$31,Premissas!$B$32)))) | C62: =Premissas!C22*B62 | D62: =-C62*Premissas!$B$7 | E62: =-C62*Premissas!$B$8 | F62: =-C62*Premissas!$B$9 | G62: =-C62*Premissas!$B$10 | H62: =-Premissas!$B$11 | I62: =-Premissas!C25 | J62: =SUM(C62:I62) | K62: =J62-C62*Premissas!$B$12 | L62: =L61+K62
A63: 59 | B63: =IF(A63<=3,Premissas!$B$28,IF(A63<=6,Premissas!$B$29,IF(A63<=9,Premissas!$B$30,IF(A63<=12,Premissas!$B$31,Premissas!$B$32)))) | C63: =Premissas!C22*B63 | D63: =-C63*Premissas!$B$7 | E63: =-C63*Premissas!$B$8 | F63: =-C63*Premissas!$B$9 | G63: =-C63*Premissas!$B$10 | H63: =-Premissas!$B$11 | I63: =-Premissas!C25 | J63: =SUM(C63:I63) | K63: =J63-C63*Premissas!$B$12 | L63: =L62+K63
A64: 60 | B64: =IF(A64<=3,Premissas!$B$28,IF(A64<=6,Premissas!$B$29,IF(A64<=9,Premissas!$B$30,IF(A64<=12,Premissas!$B$31,Premissas!$B$32)))) | C64: =Premissas!C22*B64 | D64: =-C64*Premissas!$B$7 | E64: =-C64*Premissas!$B$8 | F64: =-C64*Premissas!$B$9 | G64: =-C64*Premissas!$B$10 | H64: =-Premissas!$B$11 | I64: =-Premissas!C25 | J64: =SUM(C64:I64) | K64: =J64-C64*Premissas!$B$12+Premissas!C20*Premissas!$B$13 | L64: =L63+K64
A70: RESULTADO
A71: Investimento total | B71: =Premissas!C24
A72: EBITDA maduro (mês 60) | B72: =J64
A73: Margem EBITDA madura | B73: =J64/C64
A74: Payback (meses) | B74: =MATCH(TRUE,INDEX(L5:L64>=0,0),0)
A75: TIR mensal | B75: =IRR(K4:K64)
A76: TIR anual | B76: =(1+B74)^12-1
A77: VPL @ TMA | B77: =NPV((1+Premissas!$B$6)^(1/12)-1,K5:K64)+K4
A78: ROI 5 anos (caixa/investimento) | B78: =SUM(K5:K64)/B71

Sheet Prime
A1: UNIDADE PRIME — FLUXO MENSAL (60 MESES)
A3: Mês | B3: % rampa | C3: Receita | D3: Impostos | E3: Variáveis | F3: Royalty | G3: Fundo | H3: Tecnologia | I3: Fixos | J3: EBITDA | K3: Fluxo livre | L3: Acumulado
A4: 0 | K4: =-Premissas!D24 | L4: =-Premissas!D24
A5: 1 | B5: =IF(A5<=3,Premissas!$B$28,IF(A5<=6,Premissas!$B$29,IF(A5<=9,Premissas!$B$30,IF(A5<=12,Premissas!$B$31,Premissas!$B$32)))) | C5: =Premissas!D22*B5 | D5: =-C5*Premissas!$B$7 | E5: =-C5*Premissas!$B$8 | F5: =-C5*Premissas!$B$9 | G5: =-C5*Premissas!$B$10 | H5: =-Premissas!$B$11 | I5: =-Premissas!D25 | J5: =SUM(C5:I5) | K5: =J5-C5*Premissas!$B$12 | L5: =L4+K5
A6: 2 | B6: =IF(A6<=3,Premissas!$B$28,IF(A6<=6,Premissas!$B$29,IF(A6<=9,Premissas!$B$30,IF(A6<=12,Premissas!$B$31,Premissas!$B$32)))) | C6: =Premissas!D22*B6 | D6: =-C6*Premissas!$B$7 | E6: =-C6*Premissas!$B$8 | F6: =-C6*Premissas!$B$9 | G6: =-C6*Premissas!$B$10 | H6: =-Premissas!$B$11 | I6: =-Premissas!D25 | J6: =SUM(C6:I6) | K6: =J6-C6*Premissas!$B$12 | L6: =L5+K6
A7: 3 | B7: =IF(A7<=3,Premissas!$B$28,IF(A7<=6,Premissas!$B$29,IF(A7<=9,Premissas!$B$30,IF(A7<=12,Premissas!$B$31,Premissas!$B$32)))) | C7: =Premissas!D22*B7 | D7: =-C7*Premissas!$B$7 | E7: =-C7*Premissas!$B$8 | F7: =-C7*Premissas!$B$9 | G7: =-C7*Premissas!$B$10 | H7: =-Premissas!$B$11 | I7: =-Premissas!D25 | J7: =SUM(C7:I7) | K7: =J7-C7*Premissas!$B$12 | L7: =L6+K7
A8: 4 | B8: =IF(A8<=3,Premissas!$B$28,IF(A8<=6,Premissas!$B$29,IF(A8<=9,Premissas!$B$30,IF(A8<=12,Premissas!$B$31,Premissas!$B$32)))) | C8: =Premissas!D22*B8 | D8: =-C8*Premissas!$B$7 | E8: =-C8*Premissas!$B$8 | F8: =-C8*Premissas!$B$9 | G8: =-C8*Premissas!$B$10 | H8: =-Premissas!$B$11 | I8: =-Premissas!D25 | J8: =SUM(C8:I8) | K8: =J8-C8*Premissas!$B$12 | L8: =L7+K8
A9: 5 | B9: =IF(A9<=3,Premissas!$B$28,IF(A9<=6,Premissas!$B$29,IF(A9<=9,Premissas!$B$30,IF(A9<=12,Premissas!$B$31,Premissas!$B$32)))) | C9: =Premissas!D22*B9 | D9: =-C9*Premissas!$B$7 | E9: =-C9*Premissas!$B$8 | F9: =-C9*Premissas!$B$9 | G9: =-C9*Premissas!$B$10 | H9: =-Premissas!$B$11 | I9: =-Premissas!D25 | J9: =SUM(C9:I9) | K9: =J9-C9*Premissas!$B$12 | L9: =L8+K9
A10: 6 | B10: =IF(A10<=3,Premissas!$B$28,IF(A10<=6,Premissas!$B$29,IF(A10<=9,Premissas!$B$30,IF(A10<=12,Premissas!$B$31,Premissas!$B$32)))) | C10: =Premissas!D22*B10 | D10: =-C10*Premissas!$B$7 | E10: =-C10*Premissas!$B$8 | F10: =-C10*Premissas!$B$9 | G10: =-C10*Premissas!$B$10 | H10: =-Premissas!$B$11 | I10: =-Premissas!D25 | J10: =SUM(C10:I10) | K10: =J10-C10*Premissas!$B$12 | L10: =L9+K10
A11: 7 | B11: =IF(A11<=3,Premissas!$B$28,IF(A11<=6,Premissas!$B$29,IF(A11<=9,Premissas!$B$30,IF(A11<=12,Premissas!$B$31,Premissas!$B$32)))) | C11: =Premissas!D22*B11 | D11: =-C11*Premissas!$B$7 | E11: =-C11*Premissas!$B$8 | F11: =-C11*Premissas!$B$9 | G11: =-C11*Premissas!$B$10 | H11: =-Premissas!$B$11 | I11: =-Premissas!D25 | J11: =SUM(C11:I11) | K11: =J11-C11*Premissas!$B$12 | L11: =L10+K11
A12: 8 | B12: =IF(A12<=3,Premissas!$B$28,IF(A12<=6,Premissas!$B$29,IF(A12<=9,Premissas!$B$30,IF(A12<=12,Premissas!$B$31,Premissas!$B$32)))) | C12: =Premissas!D22*B12 | D12: =-C12*Premissas!$B$7 | E12: =-C12*Premissas!$B$8 | F12: =-C12*Premissas!$B$9 | G12: =-C12*Premissas!$B$10 | H12: =-Premissas!$B$11 | I12: =-Premissas!D25 | J12: =SUM(C12:I12) | K12: =J12-C12*Premissas!$B$12 | L12: =L11+K12
A13: 9 | B13: =IF(A13<=3,Premissas!$B$28,IF(A13<=6,Premissas!$B$29,IF(A13<=9,Premissas!$B$30,IF(A13<=12,Premissas!$B$31,Premissas!$B$32)))) | C13: =Premissas!D22*B13 | D13: =-C13*Premissas!$B$7 | E13: =-C13*Premissas!$B$8 | F13: =-C13*Premissas!$B$9 | G13: =-C13*Premissas!$B$10 | H13: =-Premissas!$B$11 | I13: =-Premissas!D25 | J13: =SUM(C13:I13) | K13: =J13-C13*Premissas!$B$12 | L13: =L12+K13
A14: 10 | B14: =IF(A14<=3,Premissas!$B$28,IF(A14<=6,Premissas!$B$29,IF(A14<=9,Premissas!$B$30,IF(A14<=12,Premissas!$B$31,Premissas!$B$32)))) | C14: =Premissas!D22*B14 | D14: =-C14*Premissas!$B$7 | E14: =-C14*Premissas!$B$8 | F14: =-C14*Premissas!$B$9 | G14: =-C14*Premissas!$B$10 | H14: =-Premissas!$B$11 | I14: =-Premissas!D25 | J14: =SUM(C14:I14) | K14: =J14-C14*Premissas!$B$12 | L14: =L13+K14
A15: 11 | B15: =IF(A15<=3,Premissas!$B$28,IF(A15<=6,Premissas!$B$29,IF(A15<=9,Premissas!$B$30,IF(A15<=12,Premissas!$B$31,Premissas!$B$32)))) | C15: =Premissas!D22*B15 | D15: =-C15*Premissas!$B$7 | E15: =-C15*Premissas!$B$8 | F15: =-C15*Premissas!$B$9 | G15: =-C15*Premissas!$B$10 | H15: =-Premissas!$B$11 | I15: =-Premissas!D25 | J15: =SUM(C15:I15) | K15: =J15-C15*Premissas!$B$12 | L15: =L14+K15
A16: 12 | B16: =IF(A16<=3,Premissas!$B$28,IF(A16<=6,Premissas!$B$29,IF(A16<=9,Premissas!$B$30,IF(A16<=12,Premissas!$B$31,Premissas!$B$32)))) | C16: =Premissas!D22*B16 | D16: =-C16*Premissas!$B$7 | E16: =-C16*Premissas!$B$8 | F16: =-C16*Premissas!$B$9 | G16: =-C16*Premissas!$B$10 | H16: =-Premissas!$B$11 | I16: =-Premissas!D25 | J16: =SUM(C16:I16) | K16: =J16-C16*Premissas!$B$12 | L16: =L15+K16
A17: 13 | B17: =IF(A17<=3,Premissas!$B$28,IF(A17<=6,Premissas!$B$29,IF(A17<=9,Premissas!$B$30,IF(A17<=12,Premissas!$B$31,Premissas!$B$32)))) | C17: =Premissas!D22*B17 | D17: =-C17*Premissas!$B$7 | E17: =-C17*Premissas!$B$8 | F17: =-C17*Premissas!$B$9 | G17: =-C17*Premissas!$B$10 | H17: =-Premissas!$B$11 | I17: =-Premissas!D25 | J17: =SUM(C17:I17) | K17: =J17-C17*Premissas!$B$12 | L17: =L16+K17
A18: 14 | B18: =IF(A18<=3,Premissas!$B$28,IF(A18<=6,Premissas!$B$29,IF(A18<=9,Premissas!$B$30,IF(A18<=12,Premissas!$B$31,Premissas!$B$32)))) | C18: =Premissas!D22*B18 | D18: =-C18*Premissas!$B$7 | E18: =-C18*Premissas!$B$8 | F18: =-C18*Premissas!$B$9 | G18: =-C18*Premissas!$B$10 | H18: =-Premissas!$B$11 | I18: =-Premissas!D25 | J18: =SUM(C18:I18) | K18: =J18-C18*Premissas!$B$12 | L18: =L17+K18
A19: 15 | B19: =IF(A19<=3,Premissas!$B$28,IF(A19<=6,Premissas!$B$29,IF(A19<=9,Premissas!$B$30,IF(A19<=12,Premissas!$B$31,Premissas!$B$32)))) | C19: =Premissas!D22*B19 | D19: =-C19*Premissas!$B$7 | E19: =-C19*Premissas!$B$8 | F19: =-C19*Premissas!$B$9 | G19: =-C19*Premissas!$B$10 | H19: =-Premissas!$B$11 | I19: =-Premissas!D25 | J19: =SUM(C19:I19) | K19: =J19-C19*Premissas!$B$12 | L19: =L18+K19
A20: 16 | B20: =IF(A20<=3,Premissas!$B$28,IF(A20<=6,Premissas!$B$29,IF(A20<=9,Premissas!$B$30,IF(A20<=12,Premissas!$B$31,Premissas!$B$32)))) | C20: =Premissas!D22*B20 | D20: =-C20*Premissas!$B$7 | E20: =-C20*Premissas!$B$8 | F20: =-C20*Premissas!$B$9 | G20: =-C20*Premissas!$B$10 | H20: =-Premissas!$B$11 | I20: =-Premissas!D25 | J20: =SUM(C20:I20) | K20: =J20-C20*Premissas!$B$12 | L20: =L19+K20
A21: 17 | B21: =IF(A21<=3,Premissas!$B$28,IF(A21<=6,Premissas!$B$29,IF(A21<=9,Premissas!$B$30,IF(A21<=12,Premissas!$B$31,Premissas!$B$32)))) | C21: =Premissas!D22*B21 | D21: =-C21*Premissas!$B$7 | E21: =-C21*Premissas!$B$8 | F21: =-C21*Premissas!$B$9 | G21: =-C21*Premissas!$B$10 | H21: =-Premissas!$B$11 | I21: =-Premissas!D25 | J21: =SUM(C21:I21) | K21: =J21-C21*Premissas!$B$12 | L21: =L20+K21
A22: 18 | B22: =IF(A22<=3,Premissas!$B$28,IF(A22<=6,Premissas!$B$29,IF(A22<=9,Premissas!$B$30,IF(A22<=12,Premissas!$B$31,Premissas!$B$32)))) | C22: =Premissas!D22*B22 | D22: =-C22*Premissas!$B$7 | E22: =-C22*Premissas!$B$8 | F22: =-C22*Premissas!$B$9 | G22: =-C22*Premissas!$B$10 | H22: =-Premissas!$B$11 | I22: =-Premissas!D25 | J22: =SUM(C22:I22) | K22: =J22-C22*Premissas!$B$12 | L22: =L21+K22
A23: 19 | B23: =IF(A23<=3,Premissas!$B$28,IF(A23<=6,Premissas!$B$29,IF(A23<=9,Premissas!$B$30,IF(A23<=12,Premissas!$B$31,Premissas!$B$32)))) | C23: =Premissas!D22*B23 | D23: =-C23*Premissas!$B$7 | E23: =-C23*Premissas!$B$8 | F23: =-C23*Premissas!$B$9 | G23: =-C23*Premissas!$B$10 | H23: =-Premissas!$B$11 | I23: =-Premissas!D25 | J23: =SUM(C23:I23) | K23: =J23-C23*Premissas!$B$12 | L23: =L22+K23
A24: 20 | B24: =IF(A24<=3,Premissas!$B$28,IF(A24<=6,Premissas!$B$29,IF(A24<=9,Premissas!$B$30,IF(A24<=12,Premissas!$B$31,Premissas!$B$32)))) | C24: =Premissas!D22*B24 | D24: =-C24*Premissas!$B$7 | E24: =-C24*Premissas!$B$8 | F24: =-C24*Premissas!$B$9 | G24: =-C24*Premissas!$B$10 | H24: =-Premissas!$B$11 | I24: =-Premissas!D25 | J24: =SUM(C24:I24) | K24: =J24-C24*Premissas!$B$12 | L24: =L23+K24
A25: 21 | B25: =IF(A25<=3,Premissas!$B$28,IF(A25<=6,Premissas!$B$29,IF(A25<=9,Premissas!$B$30,IF(A25<=12,Premissas!$B$31,Premissas!$B$32)))) | C25: =Premissas!D22*B25 | D25: =-C25*Premissas!$B$7 | E25: =-C25*Premissas!$B$8 | F25: =-C25*Premissas!$B$9 | G25: =-C25*Premissas!$B$10 | H25: =-Premissas!$B$11 | I25: =-Premissas!D25 | J25: =SUM(C25:I25) | K25: =J25-C25*Premissas!$B$12 | L25: =L24+K25
A26: 22 | B26: =IF(A26<=3,Premissas!$B$28,IF(A26<=6,Premissas!$B$29,IF(A26<=9,Premissas!$B$30,IF(A26<=12,Premissas!$B$31,Premissas!$B$32)))) | C26: =Premissas!D22*B26 | D26: =-C26*Premissas!$B$7 | E26: =-C26*Premissas!$B$8 | F26: =-C26*Premissas!$B$9 | G26: =-C26*Premissas!$B$10 | H26: =-Premissas!$B$11 | I26: =-Premissas!D25 | J26: =SUM(C26:I26) | K26: =J26-C26*Premissas!$B$12 | L26: =L25+K26
A27: 23 | B27: =IF(A27<=3,Premissas!$B$28,IF(A27<=6,Premissas!$B$29,IF(A27<=9,Premissas!$B$30,IF(A27<=12,Premissas!$B$31,Premissas!$B$32)))) | C27: =Premissas!D22*B27 | D27: =-C27*Premissas!$B$7 | E27: =-C27*Premissas!$B$8 | F27: =-C27*Premissas!$B$9 | G27: =-C27*Premissas!$B$10 | H27: =-Premissas!$B$11 | I27: =-Premissas!D25 | J27: =SUM(C27:I27) | K27: =J27-C27*Premissas!$B$12 | L27: =L26+K27
A28: 24 | B28: =IF(A28<=3,Premissas!$B$28,IF(A28<=6,Premissas!$B$29,IF(A28<=9,Premissas!$B$30,IF(A28<=12,Premissas!$B$31,Premissas!$B$32)))) | C28: =Premissas!D22*B28 | D28: =-C28*Premissas!$B$7 | E28: =-C28*Premissas!$B$8 | F28: =-C28*Premissas!$B$9 | G28: =-C28*Premissas!$B$10 | H28: =-Premissas!$B$11 | I28: =-Premissas!D25 | J28: =SUM(C28:I28) | K28: =J28-C28*Premissas!$B$12 | L28: =L27+K28
A29: 25 | B29: =IF(A29<=3,Premissas!$B$28,IF(A29<=6,Premissas!$B$29,IF(A29<=9,Premissas!$B$30,IF(A29<=12,Premissas!$B$31,Premissas!$B$32)))) | C29: =Premissas!D22*B29 | D29: =-C29*Premissas!$B$7 | E29: =-C29*Premissas!$B$8 | F29: =-C29*Premissas!$B$9 | G29: =-C29*Premissas!$B$10 | H29: =-Premissas!$B$11 | I29: =-Premissas!D25 | J29: =SUM(C29:I29) | K29: =J29-C29*Premissas!$B$12 | L29: =L28+K29
A30: 26 | B30: =IF(A30<=3,Premissas!$B$28,IF(A30<=6,Premissas!$B$29,IF(A30<=9,Premissas!$B$30,IF(A30<=12,Premissas!$B$31,Premissas!$B$32)))) | C30: =Premissas!D22*B30 | D30: =-C30*Premissas!$B$7 | E30: =-C30*Premissas!$B$8 | F30: =-C30*Premissas!$B$9 | G30: =-C30*Premissas!$B$10 | H30: =-Premissas!$B$11 | I30: =-Premissas!D25 | J30: =SUM(C30:I30) | K30: =J30-C30*Premissas!$B$12 | L30: =L29+K30
A31: 27 | B31: =IF(A31<=3,Premissas!$B$28,IF(A31<=6,Premissas!$B$29,IF(A31<=9,Premissas!$B$30,IF(A31<=12,Premissas!$B$31,Premissas!$B$32)))) | C31: =Premissas!D22*B31 | D31: =-C31*Premissas!$B$7 | E31: =-C31*Premissas!$B$8 | F31: =-C31*Premissas!$B$9 | G31: =-C31*Premissas!$B$10 | H31: =-Premissas!$B$11 | I31: =-Premissas!D25 | J31: =SUM(C31:I31) | K31: =J31-C31*Premissas!$B$12 | L31: =L30+K31
A32: 28 | B32: =IF(A32<=3,Premissas!$B$28,IF(A32<=6,Premissas!$B$29,IF(A32<=9,Premissas!$B$30,IF(A32<=12,Premissas!$B$31,Premissas!$B$32)))) | C32: =Premissas!D22*B32 | D32: =-C32*Premissas!$B$7 | E32: =-C32*Premissas!$B$8 | F32: =-C32*Premissas!$B$9 | G32: =-C32*Premissas!$B$10 | H32: =-Premissas!$B$11 | I32: =-Premissas!D25 | J32: =SUM(C32:I32) | K32: =J32-C32*Premissas!$B$12 | L32: =L31+K32
A33: 29 | B33: =IF(A33<=3,Premissas!$B$28,IF(A33<=6,Premissas!$B$29,IF(A33<=9,Premissas!$B$30,IF(A33<=12,Premissas!$B$31,Premissas!$B$32)))) | C33: =Premissas!D22*B33 | D33: =-C33*Premissas!$B$7 | E33: =-C33*Premissas!$B$8 | F33: =-C33*Premissas!$B$9 | G33: =-C33*Premissas!$B$10 | H33: =-Premissas!$B$11 | I33: =-Premissas!D25 | J33: =SUM(C33:I33) | K33: =J33-C33*Premissas!$B$12 | L33: =L32+K33
A34: 30 | B34: =IF(A34<=3,Premissas!$B$28,IF(A34<=6,Premissas!$B$29,IF(A34<=9,Premissas!$B$30,IF(A34<=12,Premissas!$B$31,Premissas!$B$32)))) | C34: =Premissas!D22*B34 | D34: =-C34*Premissas!$B$7 | E34: =-C34*Premissas!$B$8 | F34: =-C34*Premissas!$B$9 | G34: =-C34*Premissas!$B$10 | H34: =-Premissas!$B$11 | I34: =-Premissas!D25 | J34: =SUM(C34:I34) | K34: =J34-C34*Premissas!$B$12 | L34: =L33+K34
A35: 31 | B35: =IF(A35<=3,Premissas!$B$28,IF(A35<=6,Premissas!$B$29,IF(A35<=9,Premissas!$B$30,IF(A35<=12,Premissas!$B$31,Premissas!$B$32)))) | C35: =Premissas!D22*B35 | D35: =-C35*Premissas!$B$7 | E35: =-C35*Premissas!$B$8 | F35: =-C35*Premissas!$B$9 | G35: =-C35*Premissas!$B$10 | H35: =-Premissas!$B$11 | I35: =-Premissas!D25 | J35: =SUM(C35:I35) | K35: =J35-C35*Premissas!$B$12 | L35: =L34+K35
A36: 32 | B36: =IF(A36<=3,Premissas!$B$28,IF(A36<=6,Premissas!$B$29,IF(A36<=9,Premissas!$B$30,IF(A36<=12,Premissas!$B$31,Premissas!$B$32)))) | C36: =Premissas!D22*B36 | D36: =-C36*Premissas!$B$7 | E36: =-C36*Premissas!$B$8 | F36: =-C36*Premissas!$B$9 | G36: =-C36*Premissas!$B$10 | H36: =-Premissas!$B$11 | I36: =-Premissas!D25 | J36: =SUM(C36:I36) | K36: =J36-C36*Premissas!$B$12 | L36: =L35+K36
A37: 33 | B37: =IF(A37<=3,Premissas!$B$28,IF(A37<=6,Premissas!$B$29,IF(A37<=9,Premissas!$B$30,IF(A37<=12,Premissas!$B$31,Premissas!$B$32)))) | C37: =Premissas!D22*B37 | D37: =-C37*Premissas!$B$7 | E37: =-C37*Premissas!$B$8 | F37: =-C37*Premissas!$B$9 | G37: =-C37*Premissas!$B$10 | H37: =-Premissas!$B$11 | I37: =-Premissas!D25 | J37: =SUM(C37:I37) | K37: =J37-C37*Premissas!$B$12 | L37: =L36+K37
A38: 34 | B38: =IF(A38<=3,Premissas!$B$28,IF(A38<=6,Premissas!$B$29,IF(A38<=9,Premissas!$B$30,IF(A38<=12,Premissas!$B$31,Premissas!$B$32)))) | C38: =Premissas!D22*B38 | D38: =-C38*Premissas!$B$7 | E38: =-C38*Premissas!$B$8 | F38: =-C38*Premissas!$B$9 | G38: =-C38*Premissas!$B$10 | H38: =-Premissas!$B$11 | I38: =-Premissas!D25 | J38: =SUM(C38:I38) | K38: =J38-C38*Premissas!$B$12 | L38: =L37+K38
A39: 35 | B39: =IF(A39<=3,Premissas!$B$28,IF(A39<=6,Premissas!$B$29,IF(A39<=9,Premissas!$B$30,IF(A39<=12,Premissas!$B$31,Premissas!$B$32)))) | C39: =Premissas!D22*B39 | D39: =-C39*Premissas!$B$7 | E39: =-C39*Premissas!$B$8 | F39: =-C39*Premissas!$B$9 | G39: =-C39*Premissas!$B$10 | H39: =-Premissas!$B$11 | I39: =-Premissas!D25 | J39: =SUM(C39:I39) | K39: =J39-C39*Premissas!$B$12 | L39: =L38+K39
A40: 36 | B40: =IF(A40<=3,Premissas!$B$28,IF(A40<=6,Premissas!$B$29,IF(A40<=9,Premissas!$B$30,IF(A40<=12,Premissas!$B$31,Premissas!$B$32)))) | C40: =Premissas!D22*B40 | D40: =-C40*Premissas!$B$7 | E40: =-C40*Premissas!$B$8 | F40: =-C40*Premissas!$B$9 | G40: =-C40*Premissas!$B$10 | H40: =-Premissas!$B$11 | I40: =-Premissas!D25 | J40: =SUM(C40:I40) | K40: =J40-C40*Premissas!$B$12 | L40: =L39+K40
A41: 37 | B41: =IF(A41<=3,Premissas!$B$28,IF(A41<=6,Premissas!$B$29,IF(A41<=9,Premissas!$B$30,IF(A41<=12,Premissas!$B$31,Premissas!$B$32)))) | C41: =Premissas!D22*B41 | D41: =-C41*Premissas!$B$7 | E41: =-C41*Premissas!$B$8 | F41: =-C41*Premissas!$B$9 | G41: =-C41*Premissas!$B$10 | H41: =-Premissas!$B$11 | I41: =-Premissas!D25 | J41: =SUM(C41:I41) | K41: =J41-C41*Premissas!$B$12 | L41: =L40+K41
A42: 38 | B42: =IF(A42<=3,Premissas!$B$28,IF(A42<=6,Premissas!$B$29,IF(A42<=9,Premissas!$B$30,IF(A42<=12,Premissas!$B$31,Premissas!$B$32)))) | C42: =Premissas!D22*B42 | D42: =-C42*Premissas!$B$7 | E42: =-C42*Premissas!$B$8 | F42: =-C42*Premissas!$B$9 | G42: =-C42*Premissas!$B$10 | H42: =-Premissas!$B$11 | I42: =-Premissas!D25 | J42: =SUM(C42:I42) | K42: =J42-C42*Premissas!$B$12 | L42: =L41+K42
A43: 39 | B43: =IF(A43<=3,Premissas!$B$28,IF(A43<=6,Premissas!$B$29,IF(A43<=9,Premissas!$B$30,IF(A43<=12,Premissas!$B$31,Premissas!$B$32)))) | C43: =Premissas!D22*B43 | D43: =-C43*Premissas!$B$7 | E43: =-C43*Premissas!$B$8 | F43: =-C43*Premissas!$B$9 | G43: =-C43*Premissas!$B$10 | H43: =-Premissas!$B$11 | I43: =-Premissas!D25 | J43: =SUM(C43:I43) | K43: =J43-C43*Premissas!$B$12 | L43: =L42+K43
A44: 40 | B44: =IF(A44<=3,Premissas!$B$28,IF(A44<=6,Premissas!$B$29,IF(A44<=9,Premissas!$B$30,IF(A44<=12,Premissas!$B$31,Premissas!$B$32)))) | C44: =Premissas!D22*B44 | D44: =-C44*Premissas!$B$7 | E44: =-C44*Premissas!$B$8 | F44: =-C44*Premissas!$B$9 | G44: =-C44*Premissas!$B$10 | H44: =-Premissas!$B$11 | I44: =-Premissas!D25 | J44: =SUM(C44:I44) | K44: =J44-C44*Premissas!$B$12 | L44: =L43+K44
A45: 41 | B45: =IF(A45<=3,Premissas!$B$28,IF(A45<=6,Premissas!$B$29,IF(A45<=9,Premissas!$B$30,IF(A45<=12,Premissas!$B$31,Premissas!$B$32)))) | C45: =Premissas!D22*B45 | D45: =-C45*Premissas!$B$7 | E45: =-C45*Premissas!$B$8 | F45: =-C45*Premissas!$B$9 | G45: =-C45*Premissas!$B$10 | H45: =-Premissas!$B$11 | I45: =-Premissas!D25 | J45: =SUM(C45:I45) | K45: =J45-C45*Premissas!$B$12 | L45: =L44+K45
A46: 42 | B46: =IF(A46<=3,Premissas!$B$28,IF(A46<=6,Premissas!$B$29,IF(A46<=9,Premissas!$B$30,IF(A46<=12,Premissas!$B$31,Premissas!$B$32)))) | C46: =Premissas!D22*B46 | D46: =-C46*Premissas!$B$7 | E46: =-C46*Premissas!$B$8 | F46: =-C46*Premissas!$B$9 | G46: =-C46*Premissas!$B$10 | H46: =-Premissas!$B$11 | I46: =-Premissas!D25 | J46: =SUM(C46:I46) | K46: =J46-C46*Premissas!$B$12 | L46: =L45+K46
A47: 43 | B47: =IF(A47<=3,Premissas!$B$28,IF(A47<=6,Premissas!$B$29,IF(A47<=9,Premissas!$B$30,IF(A47<=12,Premissas!$B$31,Premissas!$B$32)))) | C47: =Premissas!D22*B47 | D47: =-C47*Premissas!$B$7 | E47: =-C47*Premissas!$B$8 | F47: =-C47*Premissas!$B$9 | G47: =-C47*Premissas!$B$10 | H47: =-Premissas!$B$11 | I47: =-Premissas!D25 | J47: =SUM(C47:I47) | K47: =J47-C47*Premissas!$B$12 | L47: =L46+K47
A48: 44 | B48: =IF(A48<=3,Premissas!$B$28,IF(A48<=6,Premissas!$B$29,IF(A48<=9,Premissas!$B$30,IF(A48<=12,Premissas!$B$31,Premissas!$B$32)))) | C48: =Premissas!D22*B48 | D48: =-C48*Premissas!$B$7 | E48: =-C48*Premissas!$B$8 | F48: =-C48*Premissas!$B$9 | G48: =-C48*Premissas!$B$10 | H48: =-Premissas!$B$11 | I48: =-Premissas!D25 | J48: =SUM(C48:I48) | K48: =J48-C48*Premissas!$B$12 | L48: =L47+K48
A49: 45 | B49: =IF(A49<=3,Premissas!$B$28,IF(A49<=6,Premissas!$B$29,IF(A49<=9,Premissas!$B$30,IF(A49<=12,Premissas!$B$31,Premissas!$B$32)))) | C49: =Premissas!D22*B49 | D49: =-C49*Premissas!$B$7 | E49: =-C49*Premissas!$B$8 | F49: =-C49*Premissas!$B$9 | G49: =-C49*Premissas!$B$10 | H49: =-Premissas!$B$11 | I49: =-Premissas!D25 | J49: =SUM(C49:I49) | K49: =J49-C49*Premissas!$B$12 | L49: =L48+K49
A50: 46 | B50: =IF(A50<=3,Premissas!$B$28,IF(A50<=6,Premissas!$B$29,IF(A50<=9,Premissas!$B$30,IF(A50<=12,Premissas!$B$31,Premissas!$B$32)))) | C50: =Premissas!D22*B50 | D50: =-C50*Premissas!$B$7 | E50: =-C50*Premissas!$B$8 | F50: =-C50*Premissas!$B$9 | G50: =-C50*Premissas!$B$10 | H50: =-Premissas!$B$11 | I50: =-Premissas!D25 | J50: =SUM(C50:I50) | K50: =J50-C50*Premissas!$B$12 | L50: =L49+K50
A51: 47 | B51: =IF(A51<=3,Premissas!$B$28,IF(A51<=6,Premissas!$B$29,IF(A51<=9,Premissas!$B$30,IF(A51<=12,Premissas!$B$31,Premissas!$B$32)))) | C51: =Premissas!D22*B51 | D51: =-C51*Premissas!$B$7 | E51: =-C51*Premissas!$B$8 | F51: =-C51*Premissas!$B$9 | G51: =-C51*Premissas!$B$10 | H51: =-Premissas!$B$11 | I51: =-Premissas!D25 | J51: =SUM(C51:I51) | K51: =J51-C51*Premissas!$B$12 | L51: =L50+K51
A52: 48 | B52: =IF(A52<=3,Premissas!$B$28,IF(A52<=6,Premissas!$B$29,IF(A52<=9,Premissas!$B$30,IF(A52<=12,Premissas!$B$31,Premissas!$B$32)))) | C52: =Premissas!D22*B52 | D52: =-C52*Premissas!$B$7 | E52: =-C52*Premissas!$B$8 | F52: =-C52*Premissas!$B$9 | G52: =-C52*Premissas!$B$10 | H52: =-Premissas!$B$11 | I52: =-Premissas!D25 | J52: =SUM(C52:I52) | K52: =J52-C52*Premissas!$B$12 | L52: =L51+K52
A53: 49 | B53: =IF(A53<=3,Premissas!$B$28,IF(A53<=6,Premissas!$B$29,IF(A53<=9,Premissas!$B$30,IF(A53<=12,Premissas!$B$31,Premissas!$B$32)))) | C53: =Premissas!D22*B53 | D53: =-C53*Premissas!$B$7 | E53: =-C53*Premissas!$B$8 | F53: =-C53*Premissas!$B$9 | G53: =-C53*Premissas!$B$10 | H53: =-Premissas!$B$11 | I53: =-Premissas!D25 | J53: =SUM(C53:I53) | K53: =J53-C53*Premissas!$B$12 | L53: =L52+K53
A54: 50 | B54: =IF(A54<=3,Premissas!$B$28,IF(A54<=6,Premissas!$B$29,IF(A54<=9,Premissas!$B$30,IF(A54<=12,Premissas!$B$31,Premissas!$B$32)))) | C54: =Premissas!D22*B54 | D54: =-C54*Premissas!$B$7 | E54: =-C54*Premissas!$B$8 | F54: =-C54*Premissas!$B$9 | G54: =-C54*Premissas!$B$10 | H54: =-Premissas!$B$11 | I54: =-Premissas!D25 | J54: =SUM(C54:I54) | K54: =J54-C54*Premissas!$B$12 | L54: =L53+K54
A55: 51 | B55: =IF(A55<=3,Premissas!$B$28,IF(A55<=6,Premissas!$B$29,IF(A55<=9,Premissas!$B$30,IF(A55<=12,Premissas!$B$31,Premissas!$B$32)))) | C55: =Premissas!D22*B55 | D55: =-C55*Premissas!$B$7 | E55: =-C55*Premissas!$B$8 | F55: =-C55*Premissas!$B$9 | G55: =-C55*Premissas!$B$10 | H55: =-Premissas!$B$11 | I55: =-Premissas!D25 | J55: =SUM(C55:I55) | K55: =J55-C55*Premissas!$B$12 | L55: =L54+K55
A56: 52 | B56: =IF(A56<=3,Premissas!$B$28,IF(A56<=6,Premissas!$B$29,IF(A56<=9,Premissas!$B$30,IF(A56<=12,Premissas!$B$31,Premissas!$B$32)))) | C56: =Premissas!D22*B56 | D56: =-C56*Premissas!$B$7 | E56: =-C56*Premissas!$B$8 | F56: =-C56*Premissas!$B$9 | G56: =-C56*Premissas!$B$10 | H56: =-Premissas!$B$11 | I56: =-Premissas!D25 | J56: =SUM(C56:I56) | K56: =J56-C56*Premissas!$B$12 | L56: =L55+K56
A57: 53 | B57: =IF(A57<=3,Premissas!$B$28,IF(A57<=6,Premissas!$B$29,IF(A57<=9,Premissas!$B$30,IF(A57<=12,Premissas!$B$31,Premissas!$B$32)))) | C57: =Premissas!D22*B57 | D57: =-C57*Premissas!$B$7 | E57: =-C57*Premissas!$B$8 | F57: =-C57*Premissas!$B$9 | G57: =-C57*Premissas!$B$10 | H57: =-Premissas!$B$11 | I57: =-Premissas!D25 | J57: =SUM(C57:I57) | K57: =J57-C57*Premissas!$B$12 | L57: =L56+K57
A58: 54 | B58: =IF(A58<=3,Premissas!$B$28,IF(A58<=6,Premissas!$B$29,IF(A58<=9,Premissas!$B$30,IF(A58<=12,Premissas!$B$31,Premissas!$B$32)))) | C58: =Premissas!D22*B58 | D58: =-C58*Premissas!$B$7 | E58: =-C58*Premissas!$B$8 | F58: =-C58*Premissas!$B$9 | G58: =-C58*Premissas!$B$10 | H58: =-Premissas!$B$11 | I58: =-Premissas!D25 | J58: =SUM(C58:I58) | K58: =J58-C58*Premissas!$B$12 | L58: =L57+K58
A59: 55 | B59: =IF(A59<=3,Premissas!$B$28,IF(A59<=6,Premissas!$B$29,IF(A59<=9,Premissas!$B$30,IF(A59<=12,Premissas!$B$31,Premissas!$B$32)))) | C59: =Premissas!D22*B59 | D59: =-C59*Premissas!$B$7 | E59: =-C59*Premissas!$B$8 | F59: =-C59*Premissas!$B$9 | G59: =-C59*Premissas!$B$10 | H59: =-Premissas!$B$11 | I59: =-Premissas!D25 | J59: =SUM(C59:I59) | K59: =J59-C59*Premissas!$B$12 | L59: =L58+K59
A60: 56 | B60: =IF(A60<=3,Premissas!$B$28,IF(A60<=6,Premissas!$B$29,IF(A60<=9,Premissas!$B$30,IF(A60<=12,Premissas!$B$31,Premissas!$B$32)))) | C60: =Premissas!D22*B60 | D60: =-C60*Premissas!$B$7 | E60: =-C60*Premissas!$B$8 | F60: =-C60*Premissas!$B$9 | G60: =-C60*Premissas!$B$10 | H60: =-Premissas!$B$11 | I60: =-Premissas!D25 | J60: =SUM(C60:I60) | K60: =J60-C60*Premissas!$B$12 | L60: =L59+K60
A61: 57 | B61: =IF(A61<=3,Premissas!$B$28,IF(A61<=6,Premissas!$B$29,IF(A61<=9,Premissas!$B$30,IF(A61<=12,Premissas!$B$31,Premissas!$B$32)))) | C61: =Premissas!D22*B61 | D61: =-C61*Premissas!$B$7 | E61: =-C61*Premissas!$B$8 | F61: =-C61*Premissas!$B$9 | G61: =-C61*Premissas!$B$10 | H61: =-Premissas!$B$11 | I61: =-Premissas!D25 | J61: =SUM(C61:I61) | K61: =J61-C61*Premissas!$B$12 | L61: =L60+K61
A62: 58 | B62: =IF(A62<=3,Premissas!$B$28,IF(A62<=6,Premissas!$B$29,IF(A62<=9,Premissas!$B$30,IF(A62<=12,Premissas!$B$31,Premissas!$B$32)))) | C62: =Premissas!D22*B62 | D62: =-C62*Premissas!$B$7 | E62: =-C62*Premissas!$B$8 | F62: =-C62*Premissas!$B$9 | G62: =-C62*Premissas!$B$10 | H62: =-Premissas!$B$11 | I62: =-Premissas!D25 | J62: =SUM(C62:I62) | K62: =J62-C62*Premissas!$B$12 | L62: =L61+K62
A63: 59 | B63: =IF(A63<=3,Premissas!$B$28,IF(A63<=6,Premissas!$B$29,IF(A63<=9,Premissas!$B$30,IF(A63<=12,Premissas!$B$31,Premissas!$B$32)))) | C63: =Premissas!D22*B63 | D63: =-C63*Premissas!$B$7 | E63: =-C63*Premissas!$B$8 | F63: =-C63*Premissas!$B$9 | G63: =-C63*Premissas!$B$10 | H63: =-Premissas!$B$11 | I63: =-Premissas!D25 | J63: =SUM(C63:I63) | K63: =J63-C63*Premissas!$B$12 | L63: =L62+K63
A64: 60 | B64: =IF(A64<=3,Premissas!$B$28,IF(A64<=6,Premissas!$B$29,IF(A64<=9,Premissas!$B$30,IF(A64<=12,Premissas!$B$31,Premissas!$B$32)))) | C64: =Premissas!D22*B64 | D64: =-C64*Premissas!$B$7 | E64: =-C64*Premissas!$B$8 | F64: =-C64*Premissas!$B$9 | G64: =-C64*Premissas!$B$10 | H64: =-Premissas!$B$11 | I64: =-Premissas!D25 | J64: =SUM(C64:I64) | K64: =J64-C64*Premissas!$B$12+Premissas!D20*Premissas!$B$13 | L64: =L63+K64
A70: RESULTADO
A71: Investimento total | B71: =Premissas!D24
A72: EBITDA maduro (mês 60) | B72: =J64
A73: Margem EBITDA madura | B73: =J64/C64
A74: Payback (meses) | B74: =MATCH(TRUE,INDEX(L5:L64>=0,0),0)
A75: TIR mensal | B75: =IRR(K4:K64)
A76: TIR anual | B76: =(1+B74)^12-1
A77: VPL @ TMA | B77: =NPV((1+Premissas!$B$6)^(1/12)-1,K5:K64)+K4
A78: ROI 5 anos (caixa/investimento) | B78: =SUM(K5:K64)/B71
